Workbook

Sheet ССРСС
A1: "УТВЕРЖДАЮ" | F1: (Внешний файл)
A2: Заместитель директора | F2: Приложение 3 к Техническому заданию
A3: ГАУ "МосжилНИИпроект"
A4: __________________И.А. Клоков
C6: 2026 г.
B8: Сводный сметный расчет в сумме | D8: =H39 -> 66697.21 | E8: руб.
A10: СВОДНЫЙ СМЕТНЫЙ РАСЧЕТ СТОИМОСТИ СТРОИТЕЛЬСТВА
A11: Выполнение работ по капитальному ремонту здания в Басманном районе ЦАО города Москвы
A13: Составлен в текущих ценах по состоянию на 2 квартал 2026 г.
A14: № п/п | B14: Обоснование | C14: Наименование глав, объектов, работ и затрат | D14: Сметная стоимость, тыс.руб.
D15: Строительные работы | E15: Монтажные работы | F15: Оборудование | G15: Прочие | H15: Общая
A16: 1 | B16: 2 | C16: 3 | D16: 4 | E16: 5 | F16: 6 | G16: 7 | H16: 8
A17: Глава 2. Основные объекты строительства, реконструкции, капитального ремонта
A18: 1 | B18: ОСР №02-01 | C18: Выполнение работ по капитальному ремонту | D18: ='ОСР 02-01'!D34 -> 20114.37 | E18: ='ОСР 02-01'!E34 -> 17104.55 | F18: ='ОСР 02-01'!F34 -> 13858.18 | G18: - | H18: =SUM(D18:G18) -> 51077.1
A19: в т.ч. Оборудование , не облагаемое НДС | F19: ='ОСР 02-01'!F33 -> 58.11
A20: Итого по гл. 2 | D20: =D18 -> 20114.37 | E20: =E18 -> 17104.55 | F20: =F18 -> 13858.18 | G20: - | H20: =SUM(D20:G20) -> 51077.1
A21: Итого по гл. 1-7 | D21: =D20 -> 20114.37 | E21: =E20 -> 17104.55 | F21: =F20 -> 13858.18 | G21: - | H21: =SUM(D21:G21) -> 51077.1
A23: Глава 8. Временные здания и сооружения
A24: 2 | B24: МОС.05.05-006.2025 прил. В.3, п. 1.2 | C24: Временные здания и сооружения 1,4% | D24: =D18*0.014 -> 281.6 | E24: =E18*0.014 -> 239.46 | F24: - | G24: - | H24: =SUM(D24:G24) -> 521.06
A25: Итого по гл. 8 | D25: =D24 -> 281.6 | E25: =E24 -> 239.46 | F25: - | G25: - | H25: =SUM(D25:G25) -> 521.06
A26: Итого по гл. 1-8 | D26: =D21+D25 -> 20395.97 | E26: =E21+E25 -> 17344.01 | F26: =F21 -> 13858.18 | G26: - | H26: =SUM(D26:G26) -> 51598.16
A27: Глава 9. Прочие работы и затраты
A28: 3 | B28: ЛС 09-01-01 | C28: Пусконаладочные работы | D28: 0 | E28: 0 | F28: 0 | G28: ='ЛС 09-01-01'!J14 -> 2010 | H28: =SUM(D28:G28) -> 2010
A29: Итого по гл. 9 | D29: =SUM(D28:D28) -> 0 | E29: =SUM(E28:E28) -> 0 | F29: =SUM(F28:F28) -> 0 | G29: =G28 -> 2010 | H29: =SUM(D29:G29) -> 2010
A30: Итого по гл. 1-9 | D30: =D26 -> 20395.97 | E30: =E26 -> 17344.01 | F30: =F26 -> 13858.18 | G30: =G29 -> 2010 | H30: =SUM(D30:G30) -> 53608.16
A31: Итого по гл. 1-12 | D31: =D30 -> 20395.97 | E31: =E30 -> 17344.01 | F31: =F30 -> 13858.18 | G31: =G30 -> 2010 | H31: =SUM(D31:G31) -> 53608.16
A32: Непредвиденные затраты
A33: 4 | B33: ТСН-2001.12 прил.5 п.13.1 | C33: Резерв средств на непредвиденные работы и затраты - 2% | D33: =D31*0.02 -> 407.92 | E33: =E31*0.02 -> 346.88 | F33: =F31*0.02 -> 277.16 | G33: =G31*0.02 -> 40.2 | H33: =SUM(D33:G33) -> 1072.16
A34: Итого непредвиденные затраты | D34: =D33 -> 407.92 | E34: =E33 -> 346.88 | F34: =F33 -> 277.16 | G34: =G33 -> 40.2 | H34: =SUM(D34:G34) -> 1072.16
A35: Итого по сводному сметному расчету без НДС | D35: =D31+D34 -> 20803.89 | E35: =E31+E34 -> 17690.89 | F35: =F31+F34 -> 14135.34 | G35: =G31+G34 -> 2050.2 | H35: =SUM(D35:G35) -> 54680.32
A36: Налоги и обязательные платежи
A37: 5 | B37: ТСН-2001.12 прил.5 п.13.2 | C37: НДС 22% | D37: =D35*0.22 -> 4576.86 | E37: =E35*0.22 -> 3892 | F37: =(F35-F19)*0.22 -> 3096.99 | G37: =G35*0.22 -> 451.04 | H37: =SUM(D37:G37) -> 12016.89
A38: Итого "Налоги и обязательные платежи" | D38: =D37 -> 4576.86 | E38: =E37 -> 3892 | F38: =F37 -> 3096.99 | G38: =G37 -> 451.04 | H38: =SUM(D38:G38) -> 12016.89
A39: Итого по сводному сметному расчету | D39: =D35+D38 -> 25380.75 | E39: =E35+E38 -> 21582.89 | F39: =F35+F38 -> 17232.33 | G39: =G35+G38 -> 2501.24 | H39: =SUM(D39:G39) -> 66697.21
A40: 6 | B40: ТСН-2001.12 прил.5 п.13.3 | C40: Возвратные средства без НДС (справочно) | D40: - | E40: - | F40: - | G40: =Возврат!J13 -> 31.51 | H40: =G40 -> 31.51

Sheet ОСР 02-01
A1: ОБЪЕКТНАЯ СМЕТА № ОС 02-01
A3: =ССРСС!A11 -> Выполнение работ по капитальному ремонту здания в Басманном районе ЦАО города Москвы
A4: (наименование объекта, комплекса работ и затрат)
A6: Сметная стоимость | D6: =H34 -> 51077.1 | E6: тыс.руб.
A9: Составлен(а) в уровне текущих (прогнозных) цен II квартал 2026 года
A11: № п/п | B11: Номера локальных сметных расчетов (смет) | C11: Наименование работ и затрат | D11: Сметная стоимость, тыс.руб.
D12: строительных (ремонтно-строительных) работ | E12: работ по монтажу оборудования | F12: оборудования, мебели и инвентаря | G12: прочих затрат | H12: всего
A13: 1 | B13: 2 | C13: 3 | D13: 4 | E13: 5 | F13: 6 | G13: 7 | H13: 8
A14: 1 | B14: ЛС 02-01-01 | C14: Архитектурные решения | D14: ='ЛС 02-01-01'!J14 -> 16184.58 | E14: - | F14: ='ЛС 02-01-01'!J15 -> 9.39 | G14: - | H14: =SUM(D14:G14) -> 16193.97
A15: 2 | B15: ЛС 02-01-02 | C15: Демонтажные работы | D15: ='ЛС 02-01-02'!J14 -> 137.41 | E15: ='ЛС 02-01-02'!J15 -> 40.53 | F15: - | G15: - | H15: =SUM(D15:G15) -> 177.94
A16: 3 | B16: ЛС 02-01-03 | C16: Система электроснабжения | D16: ='ЛС 02-01-03'!J14 -> 456.62 | E16: ='ЛС 02-01-03'!J15 -> 8504.41 | F16: ='ЛС 02-01-03'!J16 -> 3088.99 | G16: - | H16: =SUM(D16:G16) -> 12050.02
A17: 4 | B17: ЛС 02-01-04 | C17: Система водоснабжения | D17: ='ЛС 02-01-04'!J14 -> 568.39 | E17: ='ЛС 02-01-04'!J15 -> 14.13 | F17: - | G17: - | H17: =SUM(D17:G17) -> 582.52
A18: 5 | B18: ЛС 02-01-05 | C18: Система водоотведения | D18: ='ЛС 02-01-05'!J14 -> 841.37 | E18: - | F18: - | G18: - | H18: =SUM(D18:G18) -> 841.37
A19: 6 | B19: ЛС 02-01-06 | C19: Отопление | D19: ='ЛС 02-01-06'!J14 -> 611.12 | E19: ='ЛС 02-01-06'!J15 -> 4.57 | F19: ='ЛС 02-01-06'!J16 -> 3.42 | G19: - | H19: =SUM(D19:G19) -> 619.11
A20: 7 | B20: ЛС 02-01-07 | C20: Кондиционирование | D20: ='ЛС 02-01-07'!J14 -> 575.3 | E20: ='ЛС 02-01-07'!J15 -> 6.54 | F20: ='ЛС 02-01-07'!J16 -> 1228.01 | G20: - | H20: =SUM(D20:G20) -> 1809.85
A21: 8 | B21: ЛС 02-01-08 | C21: Автоматическая пожарная сигнализация | D21: ='ЛС 02-01-08'!J14 -> 50.39 | E21: ='ЛС 02-01-08'!J15 -> 1044.06 | F21: ='ЛС 02-01-08'!J16 -> 400.68 | G21: - | H21: =SUM(D21:G21) -> 1495.13
A22: 9 | B22: ЛС 02-01-09 | C22: Система оповещения и управления эвакуацией | D22: ='ЛС 02-01-09'!J14 -> 9.71 | E22: ='ЛС 02-01-09'!J15 -> 1243.28 | F22: ='ЛС 02-01-09'!J16 -> 220.82 | G22: - | H22: =SUM(D22:G22) -> 1473.81
A23: 10 | B23: ЛС 02-01-10 | C23: Система охранно-тревожной сигнализации. | D23: ='ЛС 02-01-10'!J14 -> 86.71 | E23: ='ЛС 02-01-10'!J15 -> 792.76 | F23: ='ЛС 02-01-10'!J16 -> 407.16 | G23: - | H23: =SUM(D23:G23) -> 1286.63
A24: 11 | B24: ЛС 02-01-11 | C24: Радиотрансляционная сеть | D24: ='ЛС 02-01-11'!J14 -> 7.09 | E24: ='ЛС 02-01-11'!J15 -> 146.82 | F24: ='ЛС 02-01-11'!J16 -> 1309.56 | G24: - | H24: =SUM(D24:G24) -> 1463.47
A25: 12 | B25: ЛС 02-01-12 | C25: Система кабельного телевидения | D25: ='ЛС 02-01-12'!J14 -> 6.12 | E25: ='ЛС 02-01-12'!J15 -> 243.07 | F25: ='ЛС 02-01-12'!J16 -> 82.53 | G25: - | H25: =SUM(D25:G25) -> 331.72
A26: 13 | B26: ЛС 02-01-13 | C26: Структурированная кабельная сеть | D26: ='ЛС 02-01-13'!J14 -> 347.43 | E26: ='ЛС 02-01-13'!J15 -> 1217.23 | F26: ='ЛС 02-01-13'!J16 -> 2352.16 | G26: - | H26: =SUM(D26:G26) -> 3916.82
A27: 14 | B27: ЛС 02-01-14 | C27: Система охранного теленаблюдения | D27: ='ЛС 02-01-14'!J14 -> 126.04 | E27: ='ЛС 02-01-14'!J15 -> 872.27 | F27: ='ЛС 02-01-14'!J16 -> 567.45 | G27: - | H27: =SUM(D27:G27) -> 1565.76
A28: 15 | B28: ЛС 02-01-15 | C28: Система контроля и управления доступом | D28: ='ЛС 02-01-15'!J14 -> 37.84 | E28: ='ЛС 02-01-15'!J15 -> 2662.88 | F28: ='ЛС 02-01-15'!J16 -> 1531.58 | G28: - | H28: =SUM(D28:G28) -> 4232.3
A29: 16 | B29: ЛС 02-01-16 | C29: Система двусторонней связи | D29: ='ЛС 02-01-16'!J14 -> 2.49 | E29: ='ЛС 02-01-16'!J15 -> 40.54 | F29: ='ЛС 02-01-16'!J16 -> 54.25 | G29: - | H29: =SUM(D29:G29) -> 97.28
A30: 17 | B30: ЛС 02-01-17 | C30: Автоматизация и диспетчеризация инженерных систем | D30: - | E30: ='ЛС 02-01-17'!J14 -> 269.15 | F30: ='ЛС 02-01-17'!J15 -> 106.86 | G30: - | H30: =SUM(D30:G30) -> 376.01
A31: 18 | B31: ЛС 02-01-18 | C31: Мероприятия по противодействию террористическим актам | D31: - | E31: - | F31: ='ЛС 02-01-18'!J14 -> 2437.21 | G31: - | H31: =SUM(D31:G31) -> 2437.21
A32: 19 | B32: ЛС 02-01-19 | C32: Мероприятия по обеспечению доступа инвалидов | D32: ='ЛС 02-01-19'!J14 -> 65.76 | E32: ='ЛС 02-01-19'!J15 -> 2.31 | F32: ='ЛС 02-01-19'!J16 -> 58.11 | G32: - | H32: =SUM(D32:G32) -> 126.18
C33: в том числе оборудование необлагаемое НДС | F33: 58.11 | H33: =SUM(D33:G33) -> 58.11
C34: ИТОГО: | D34: =SUM(D14:D33) -> 20114.37 | E34: =SUM(E14:E33) -> 17104.55 | F34: =SUM(F14:F32) -> 13858.18 | G34: - | H34: =SUM(D34:G34) -> 51077.1

Sheet ЛС 02-01-01
J2: Форма № 4б
A3: =ССРСС!A11 -> Выполнение работ по капитальному ремонту здания в Басманном районе ЦАО города Москвы
A4: (наименование стройки и/или объекта)
A6: ЛОКАЛЬНЫЙ СМЕТНЫЙ РАСЧЕТ № 02-01-01
A8: Архитектурные решения
A9: (наименование работ и затрат)
I12: В базисном уровне цен | J12: В текущем уровне цен
E13: Сметная стоимость | I13: 1011.48 | J13: 16193.97 | K13: тыс.руб.
E14: Строительные работы | I14: 1009.53 | J14: 16184.58 | K14: тыс.руб.
E15: Оборудование | I15: 1.95 | J15: 9.39 | K15: тыс.руб.
E16: Средства на оплату труда | I16: 71.22 | J16: 4063.18 | K16: тыс.руб.
E17: Затраты труда | I17: 4444.17 | K17: чел.-ч.
A19: Составлен(а) по ТСН-2001 с учетом Дополнения №: 81
A20: № и период сборника коэффициентов (индексов) пересчета: Коэффициенты к ТСН-2001 МГЭ Дополнение 81, ремонт №220 II квартал 2026 года и Коэффициенты к ТСН-2001.13-2 Дополнение 47 №65 II квартал 2026 года
A21: № п/п | B21: Шифр расценки и коды ресурсов | C21: Наименование работ и затрат | D21: Ед. изм. | E21: Кол-во единиц | F21: Цена на ед. изм., руб. | G21: Попра- вочные коэффи- циенты | H21: Коэффи- циенты зимних удорожа- ний | I21: Всего в ценах на январь 2000 года, руб. | J21: Коэффи- циенты (индек- сы) пере- счета, нормы НР и СП | K21: ВСЕГО затрат в текущем уровне цен, руб.
A22: 1 | B22: 2 | C22: 3 | D22: 4 | E22: 5 | F22: 6 | G22: 7 | H22: 8 | I22: 9 | J22: 10 | K22: 11
A23: Подраздел: Фасад
A24: 1 | B24: 3.9-66-1 | C24: Установка флагодержателей стальных | D24: 1 флагодержатель | E24: 1
C25: ЗП | F25: 6.04 | G25: 1,15*1,2 | H25: 1 | I25: 8.34 | J25: 57.05 | K25: 475.8
C26: МР | F26: 0.31 | H26: 1 | I26: 0.31 | J26: 11.39 | K26: 3.53
A27: 1,1 | B27: 1.7-8-7 | C27: Флагодержатель из листовой стали, для двух флагов, окрашенный, размер 145х300х80 мм | D27: шт. | E27: 1 | F27: 68.18 | H27: 1 | I27: 68.18 | J27: 10.43 | K27: 711.12
C28: НР от ФОТ | D28: % | E28: 84 | I28: 7.01 | J28: 84 | K28: 399.67
C29: СП от ФОТ | D29: % | E29: 53 | I29: 4.42 | J29: 53 | K29: 252.17
C30: ЗТР | D30: чел-ч | E30: 0.52 | G30: 1,15*1,2 | H30: 1 | I30: 0.72
C31: ВСЕГО работ по позиции: | H31: 88.26 | J31: 1842.29
C32: ВСЕГО по позиции: | H32: 88.26 | J32: 1842.29
A34: 2 | B34: 3.9-65-3 | C34: Установка номерных табличек с номерами подъезда и квартир / установка домового знака | D34: 1 ШТ. | E34: 1
C35: ЗП | F35: 10.9 | G35: 1,15*1,2 | H35: 1 | I35: 15.04 | J35: 57.05 | K35: 858.03
C36: МР | F36: 1 | H36: 1 | I36: 1 | J36: 16.42 | K36: 16.42
A37: 2,1 | B37: 13.3-2-63 | C37: ОБОРУДОВАНИЕ:_x000D_ Табло фасадное, габаритные размеры 300х400 мм. Материал анодированный алюминий | D37: шт. | E37: 1 | F37: 1952.68 | H37: 1 | I37: 1952.68 | J37: 4.81 | K37: 9392.39
C38: НР от ФОТ | D38: % | E38: 84 | I38: 12.63 | J38: 84 | K38: 720.75
C39: СП от ФОТ | D39: % | E39: 53 | I39: 7.97 | J39: 53 | K39: 454.76
C40: ЗТР | D40: чел-ч | E40: 0.95 | G40: 1,15*1,2 | H40: 1 | I40: 1.31
C41: ВСЕГО работ по позиции: | H41: 36.64 | J41: 2049.96
C42: ВСЕГО оборудование по позиции: | H42: 1952.68 | J42: 9392.39
C43: ВСЕГО по позиции: | H43: 1989.32 | J43: 11442.35
A46: Итого по подразделу: Фасад | H46: 2077.58 | J46: 13284.64
A48: Подраздел: Кровля
A49: 3 | B49: 6.58-18-2 | C49: Устройство настенных желобов из листовой стали | D49: 100 м | E49: 0.583
C50: Объем: 0,583=58,3/100
C51: ЗП | F51: 236.39 | G51: 1,2 | H51: 1 | I51: 165.38 | J51: 57.05 | K51: 9434.93
C52: МР | F52: 516.77 | H52: 1 | I52: 301.28 | J52: 76.03 | K52: 22906.32
A53: 3,1 | B53: 1.1-1-925 | C53: Поковки строительные (скобы, закрепы, хомуты) оцинкованные, масса 1,8 кг | D53: т | E53: 0.038478 | F53: 7383.97 | H53: 1 | I53: 284.12 | J53: 9.56 | K53: 2716.19
A54: 3,2 | B54: 1.1-1-1086 | C54: Лист стальной, оцинкованный, толщина от 0,55 до 0,65 мм | D54: т | E54: 0.178398 | F54: 14730.29 | H54: 1 | I54: 2627.85 | J54: 5.12 | K54: 13454.59
C55: НР от ФОТ | D55: % | E55: 90 | I55: 148.84 | J55: 90 | K55: 8491.44
C56: СП от ФОТ | D56: % | E56: 46 | I56: 76.07 | J56: 46 | K56: 4340.07
C57: ЗТР | D57: чел-ч | E57: 21.51 | G57: 1,2 | H57: 1 | I57: 15.05
C58: ВСЕГО работ по позиции: | H58: 3603.54 | J58: 61343.54
C59: ВСЕГО по позиции: | H59: 3603.54 | J59: 61343.54
A61: 4 | B61: 3.12-16-1 | C61: Ограждение кровель перилами | D61: 100 м ограждения | E61: 0.81
C62: Объем: 0,81=81/100
C63: ЗП | F63: 68.5 | G63: 1,15*1,2 | H63: 1 | I63: 76.57 | J63: 57.05 | K63: 4368.32
C64: ЭМ | F64: 40.02 | G64: 1,25*1,2 | H64: 1 | I64: 48.62 | J64: 15.19 | K64: 738.54
C65: в т.ч. ЗПМ | F65: 3.33 | G65: 1,25*1,2 | H65: 1 | I65: 4.05 | J65: 57.05 | K65: 231.05
C66: МР | F66: 15.61 | H66: 1 | I66: 12.64 | J66: 6.53 | K66: 82.54
A67: 4,1 | B67: 1.6-1-218 | C67: Ограждения из прокатных и гнутых профилей полосовой и круглой стали | D67: т | E67: 0.243 | F67: 14872.56 | H67: 1 | I67: 3614.03 | J67: 9.92 | K67: 35851.18
C68: НР от ФОТ | D68: % | E68: 98 | I68: 79.01 | J68: 98 | K68: 4507.38
C69: СП от ФОТ | D69: % | E69: 48 | I69: 38.7 | J69: 48 | K69: 2207.7
C70: ЗТР | D70: чел-ч | E70: 5.9 | G70: 1,15*1,2 | H70: 1 | I70: 6.6
C71: ВСЕГО работ по позиции: | H71: 3869.57 | J71: 47755.66
C72: ВСЕГО по позиции: | H72: 3869.57 | J72: 47755.66
A74: 5 | B74: 6.58-19-2 | C74: Навеска водосточных труб с вышек съемных монтажных | D74: 100 м труб | E74: 0.596
C75: Объем: 0,596=59,6/100
C76: ЗП | F76: 560.83 | G76: 1,2 | H76: 1 | I76: 401.11 | J76: 57.05 | K76: 22883.33
C77: ЭМ | F77: 2.49 | G77: 1,2 | H77: 1 | I77: 1.78 | J77: 17.47 | K77: 31.1
C78: в т.ч. ЗПМ | F78: 0.38 | G78: 1,2 | H78: 1 | I78: 0.27 | J78: 57.05 | K78: 15.4
C79: МР | F79: 651.77 | H79: 1 | I79: 388.45 | J79: 7.86 | K79: 3053.22
A80: 5,1 | B80: 1.7-1-2 | C80: Деталь устройства кровли и водостока по фасаду здания из оцинкованной кровельной стали для водосточных наружных труб, диаметр от 120 до 250 мм, звенья | D80: м | E80: 59.6 | F80: 70.84 | H80: 1 | I80: 4222.06 | J80: 4.25 | K80: 17943.76
C81: НР от ФОТ | D81: % | E81: 90 | I81: 361.24 | J81: 90 | K81: 20608.86
C82: СП от ФОТ | D82: % | E82: 46 | I82: 184.63 | J82: 46 | K82: 10533.42
C83: ЗТР | D83: чел-ч | E83: 44.44 | G83: 1,2 | H83: 1 | I83: 31.78
C84: ВСЕГО работ по позиции: | H84: 5559.27 | J84: 75053.69
C85: ВСЕГО по позиции: | H85: 5559.27 | J85: 75053.69
A87: 6 | B87: 6.58-29-1 | C87: Устройство коньковых флюгарок из оцинкованной стали, толщина 1 мм / продухов | D87: 1 ШТ. | E87: 7
C88: ЗП | F88: 30.05 | G88: 1,2 | H88: 1 | I88: 252.42 | J88: 57.05 | K88: 14400.56
C89: МР | F89: 8.53 | H89: 1 | I89: 59.71 | J89: 6.7 | K89: 400.06
C90: НР от ФОТ | D90: % | E90: 90 | I90: 227.18 | J90: 90 | K90: 12960.5
C91: СП от ФОТ | D91: % | E91: 46 | I91: 116.11 | J91: 46 | K91: 6624.26
C92: ЗТР | D92: чел-ч | E92: 2.62 | G92: 1,2 | H92: 1 | I92: 22.01
C93: ВСЕГО работ по позиции: | H93: 655.42 | J93: 34385.38
C94: ВСЕГО по позиции: | H94: 655.42 | J94: 34385.38
A96: 7 | B96: Прайс-лист | C96: Кровельный аэратор 196,29 = [2 390 / 1,22 / 10,18] + 2% Заг.скл | D96: ШТ | E96: 7 | F96: 196.29 | H96: 1 | I96: 1374.03 | J96: 10.18 | K96: 13987.63
C97: ВСЕГО по позиции: | H97: 1374.03 | J97: 13987.63
A100: Итого по подразделу: Кровля | H100: 15061.83 | J100: 232525.9
A102: Подраздел: Наружные двери
A103: 8 | B103: 3.9-36-1 | C103: Монтаж конструкций дверей и люков | D103: 1 т конструкций | E103: 0.1733
C104: Объем: 0,1733=0,052+0,1213
C105: ЗП | F105: 1083.72 | G105: 1,15*1,2 | H105: 1 | I105: 259.18 | J105: 57.05 | K105: 14786.22
C106: ЭМ | F106: 150.77 | G106: 1,25*1,2 | H106: 1 | I106: 39.19 | J106: 16.08 | K106: 630.18
C107: в т.ч. ЗПМ | F107: 17.54 | G107: 1,25*1,2 | H107: 1 | I107: 4.56 | J107: 57.05 | K107: 260.15
C108: МР | F108: 50.95 | H108: 1 | I108: 8.83 | J108: 10.23 | K108: 90.33
C109: НР от ФОТ | D109: % | E109: 84 | I109: 221.54 | J109: 84 | K109: 12638.95
C110: СП от ФОТ | D110: % | E110: 53 | I110: 139.78 | J110: 53 | K110: 7974.58
C111: ЗТР | D111: чел-ч | E111: 82.1 | G111: 1,15*1,2 | H111: 1 | I111: 19.63
C112: ВСЕГО работ по позиции: | H112: 668.52 | J112: 36120.26
C113: ВСЕГО по позиции: | H113: 668.52 | J113: 36120.26
A115: 9 | B115: 1.7-2-93 | C115: Блок дверной металлический противопожарный с заполнением минеральной ватой, остекленный стеклом толщиной 17 мм (0,12 м2), окрашенный порошковой краской, предел огнестойкости EI 30, однопольный, 1100х2100 мм, масса 116,5 кг, с замком-защелкой, без доводчика | D115: т | E115: 1 | F115: 49100.56 | H115: 1 | I115: 49100.56 | J115: 4.62 | K115: 226844.59
C116: ВСЕГО по позиции: | H116: 49100.56 | J116: 226844.59
A118: 10 | B118: 1.7-2-132 | C118: Блок дверной металлический противопожарный, дымогазонепроницаемый, теплоизолированный плитами на основе базальтового волокна, остекленный стеклом толщиной 24 мм (0,12 м2), окрашенный порошковой краской, ДПМДО-02/60, двупольный, 1400х2100 мм, масса 150 кг, с замком-защелкой, без доводчика | D118: т | E118: 1 | F118: 52224.34 | H118: 1 | I118: 52224.34 | J118: 4.56 | K118: 238142.99
C119: ВСЕГО по позиции: | H119: 52224.34 | J119: 238142.99
...

Sheet ЛС 02-01-02
J2: Форма № 4б
A3: =ССРСС!A11 -> Выполнение работ по капитальному ремонту здания в Басманном районе ЦАО города Москвы
A4: (наименование стройки и/или объекта)
A6: ЛОКАЛЬНЫЙ СМЕТНЫЙ РАСЧЕТ № 02-01-02
A8: Демонтажные работы
A9: (наименование работ и затрат)
I12: В базисном уровне цен | J12: В текущем уровне цен
E13: Сметная стоимость | I13: 3.15 | J13: 177.94 | K13: тыс.руб.
E14: Строительные работы | I14: 2.43 | J14: 137.41 | K14: тыс.руб.
E15: Работы по монтажу оборудования | I15: 0.72 | J15: 40.53 | K15: тыс.руб.
E16: Средства на оплату труда | I16: 1.32 | J16: 75.45 | K16: тыс.руб.
E17: Затраты труда | I17: 114.48 | K17: чел.-ч.
A19: Составлен(а) по ТСН-2001 с учетом Дополнения №: 81
A20: № и период сборника коэффициентов (индексов) пересчета: Коэффициенты к ТСН-2001 МГЭ Дополнение 81, ремонт №220 II квартал 2026 года и Коэффициенты к ТСН-2001.13-2 Дополнение 47 №65 II квартал 2026 года
A21: № п/п | B21: Шифр расценки и коды ресурсов | C21: Наименование работ и затрат | D21: Ед. изм. | E21: Кол-во единиц | F21: Цена на ед. изм., руб. | G21: Попра- вочные коэффи- циенты | H21: Коэффи- циенты зимних удорожа- ний | I21: Всего в ценах на январь 2000 года, руб. | J21: Коэффи- циенты (индек- сы) пере- счета, нормы НР и СП | K21: ВСЕГО затрат в текущем уровне цен, руб.
A22: 1 | B22: 2 | C22: 3 | D22: 4 | E22: 5 | F22: 6 | G22: 7 | H22: 8 | I22: 9 | J22: 10 | K22: 11
A24: Раздел: Электроснабжение
A25: 1 | B25: 4.8-251-9 | C25: Демонтаж щитка осветительного, устанавливаемого на стене распорными дюбелями, масса щитка до 6 кг / демонтаж | D25: 1 ШТ. | E25: 21
C26: ЗП | F26: 37.67 | G26: 1,2*0,3 | H26: 1 | I26: 284.79 | J26: 57.05 | K26: 16247.27
C27: ЭМ | F27: 1.32 | G27: 1,2*0,3 | H27: 1 | I27: 9.98 | J27: 14.96 | K27: 149.3
C28: в т.ч. ЗПМ | F28: 0.13 | G28: 1,2*0,3 | H28: 1 | I28: 0.98 | J28: 57.05 | K28: 55.91
C29: НР от ФОТ | D29: % | E29: 97 | I29: 277.2 | J29: 97 | K29: 15814.08
C30: СП от ФОТ | D30: % | E30: 51 | I30: 145.74 | J30: 51 | K30: 8314.62
C31: ЗТР | D31: чел-ч | E31: 2.9 | G31: 1,2*0,3 | H31: 1 | I31: 21.92
C32: ВСЕГО работ по позиции: | H32: 717.71 | J32: 40525.27
C33: ВСЕГО по позиции: | H33: 717.71 | J33: 40525.27
A35: 2 | B35: 6.67-4-1 | C35: Демонтаж электропроводки скрытой | D35: 100 м | E35: 3.92
C36: Объем: 3,92=392/100
C37: ЗП | F37: 26.44 | H37: 1 | I37: 103.64 | J37: 57.05 | K37: 5912.66
C38: НР от ФОТ | D38: % | E38: 91 | I38: 94.31 | J38: 91 | K38: 5380.52
C39: СП от ФОТ | D39: % | E39: 48 | I39: 49.75 | J39: 48 | K39: 2838.08
C40: ЗТР | D40: чел-ч | E40: 2.54 | H40: 1 | I40: 9.96
C41: ВСЕГО работ по позиции: | H41: 247.7 | J41: 14131.26
C42: ВСЕГО по позиции: | H42: 247.7 | J42: 14131.26
A45: Итого по разделу: Электроснабжение | H45: 965.41 | J45: 54656.53
A47: Раздел: Водоснабжение и водоотведение
A48: 8 | B48: 6.65-1-1 | C48: Разборка трубопроводов из водогазопроводных труб диаметром до 25 мм | D48: 100 м | E48: 0.66
C49: Объем: 0,66=(5+21+40)/100
C50: ЗП | F50: 284.19 | G50: 1,2 | H50: 1 | I50: 225.08 | J50: 57.05 | K50: 12840.81
C51: ЭМ | F51: 0.7 | G51: 1,2 | H51: 1 | I51: 0.55 | J51: 9.71 | K51: 5.34
C52: МР | F52: 32.56 | H52: 1 | I52: 21.49 | J52: 14.63 | K52: 314.4
C53: НР от ФОТ | D53: % | E53: 87 | I53: 195.82 | J53: 87 | K53: 11171.5
C54: СП от ФОТ | D54: % | E54: 44 | I54: 99.04 | J54: 44 | K54: 5649.96
C55: ЗТР | D55: чел-ч | E55: 26.56 | G55: 1,2 | H55: 1 | I55: 21.04
C56: ВСЕГО работ по позиции: | H56: 541.98 | J56: 29982.01
C57: ВСЕГО по позиции: | H57: 541.98 | J57: 29982.01
A59: 9 | B59: 6.65-2-2 | C59: Разборка трубопроводов из чугунных канализационных труб диаметром до 100 мм | D59: 100 м | E59: 0.3327
C60: Объем: 0,3327=33,27/100
C61: ЗП | F61: 1003.13 | G61: 1,2 | H61: 1 | I61: 400.49 | J61: 57.05 | K61: 22847.95
C62: НР от ФОТ | D62: % | E62: 87 | I62: 348.43 | J62: 87 | K62: 19877.72
C63: СП от ФОТ | D63: % | E63: 44 | I63: 176.22 | J63: 44 | K63: 10053.1
C64: ЗТР | D64: чел-ч | E64: 85.3 | G64: 1,2 | H64: 1 | I64: 34.06
C65: ВСЕГО работ по позиции: | H65: 925.14 | J65: 52778.77
C66: ВСЕГО по позиции: | H66: 925.14 | J66: 52778.77
A68: 10 | B68: 6.65-3-4 | C68: Демонтаж задвижки фланцевой диаметром 100 мм | D68: 100 шт. | E68: 0.12
C69: Объем: 0,12=12/100
C70: ЗП | F70: 2135.38 | G70: 1,2 | H70: 1 | I70: 307.49 | J70: 57.05 | K70: 17542.3
C71: НР от ФОТ | D71: % | E71: 87 | I71: 267.52 | J71: 87 | K71: 15261.8
C72: СП от ФОТ | D72: % | E72: 44 | I72: 135.3 | J72: 44 | K72: 7718.61
C73: ЗТР | D73: чел-ч | E73: 191 | G73: 1,2 | H73: 1 | I73: 27.5
C74: ВСЕГО работ по позиции: | H74: 710.31 | J74: 40522.71
C75: ВСЕГО по позиции: | H75: 710.31 | J75: 40522.71
A78: Итого по разделу: Водоснабжение и водоотведение | H78: 2177.43 | J78: 123283.49
A80: Итого по смете: | H80: 3142.84 | J80: 177940.02

Sheet ЛС 02-01-03
J2: Форма № 4б
A3: =ССРСС!A11 -> Выполнение работ по капитальному ремонту здания в Басманном районе ЦАО города Москвы
A4: (наименование стройки и/или объекта)
A6: ЛОКАЛЬНАЯ СМЕТА № 02-01-03
A8: ЭОМ
A9: (наименование работ и затрат)
I12: В базисном уровне цен | J12: В текущем уровне цен
E13: Сметная стоимость | I13: 1126.21 | J13: 12050.02 | K13: тыс.руб.
E14: Строительные работы | I14: 36.78 | J14: 456.62 | K14: тыс.руб.
E15: Работы по монтажу оборудования | I15: 679.75 | J15: 8504.41 | K15: тыс.руб.
E16: Оборудование | I16: 409.68 | J16: 3088.99 | K16: тыс.руб.
E17: Средства на оплату труда | I17: 30.72 | J17: 1752.76 | K17: тыс.руб.
E18: Затраты труда | I18: 2394.12 | K18: чел.-ч.
A20: Составлен(а) по ТСН-2001 с учетом Дополнения №: 81
A21: № и период сборника коэффициентов (индексов) пересчета: Коэффициенты к ТСН-2001 МГЭ Дополнение 81, ремонт №220 II квартал 2026 года и Коэффициенты к ТСН-2001.13-2 Дополнение 47 №65 II квартал 2026 года
A22: № п/п | B22: Шифр расценки и коды ресурсов | C22: Наименование работ и затрат | D22: Ед. изм. | E22: Кол-во единиц | F22: Цена на ед. изм., руб. | G22: Попра- вочные коэффи- циенты | H22: Коэффи- циенты зимних удорожа- ний | I22: Всего в ценах на январь 2000 года, руб. | J22: Коэффи- циенты (индек- сы) пере- счета, нормы НР и СП | K22: ВСЕГО затрат в текущем уровне цен, руб.
A23: 1 | B23: 2 | C23: 3 | D23: 4 | E23: 5 | F23: 6 | G23: 7 | H23: 8 | I23: 9 | J23: 10 | K23: 11
A24: Раздел: ВРУ
A25: 1 | B25: 4.8-238-2 Поправка: Гл.12.Прил.8.п.8. 3_12.00.01.11.001 | C25: Монтаж щитов и стеллажей с блоками резисторов (ящиками сопротивлений) высотой свыше 1700 мм, щита, собираемого из отдельных панелей и блоков управления, однорядного или двухрядного, без блоков резисторов глубиной до 800 мм шкафного исполнения | D25: 1 м ширины по фронту | E25: 0.8
C26: ЗП | F26: 267.59 | G26: 1,2 | H26: 1 | I26: 256.89 | J26: 57.05 | K26: 14655.57
C27: ЭМ | F27: 95.26 | G27: 1,2 | H27: 1 | I27: 91.45 | J27: 16.55 | K27: 1513.5
C28: в т.ч. ЗПМ | F28: 11.61 | G28: 1,2 | H28: 1 | I28: 11.15 | J28: 57.05 | K28: 636.11
C29: МР | F29: 263.81 | H29: 1 | I29: 211.05 | J29: 3.7 | K29: 780.89
A30: 1,1 | B30: 1.1-1-8146 | C30: Болты стальные оцинкованные с шестигранной головкой, с полной резьбой, с гайкой оцинкованной, М6, длина от 12 до 60 мм | D30: кг | E30: 1 | F30: 31.08 | H30: 1 | I30: 31.08 | J30: 3.59 | K30: 111.58
C31: НР от ФОТ | D31: % | E31: 97 | I31: 260 | J31: 97 | K31: 14832.93
C32: СП от ФОТ | D32: % | E32: 51 | I32: 136.7 | J32: 51 | K32: 7798.76
C33: ЗТР | D33: чел-ч | E33: 20.6 | G33: 1,2 | H33: 1 | I33: 19.78
C34: ВСЕГО работ по позиции: | H34: 987.17 | J34: 39693.23
C35: ВСЕГО по позиции: | H35: 987.17 | J35: 39693.23
A37: 2 | B37: Прайс-лист | C37: ОБОРУДОВАНИЕ:_x000D_ Вводная панель 800х450х1800 37 841,08 = [333 946,55 / 1,22 / 7,54] + 3% Трансп + 1,2% Заг.скл | D37: ШТ | E37: 1 | F37: 37841.08 | H37: 1 | I37: 37841.08 | J37: 7.54 | K37: 285321.74
C38: ВСЕГО по позиции: | H38: 37841.08 | J38: 285321.74
A40: 3 | B40: 4.8-238-2 Поправка: Гл.12.Прил.8.п.8. 3_12.00.01.11.001 | C40: Монтаж щитов и стеллажей с блоками резисторов (ящиками сопротивлений) высотой свыше 1700 мм, щита, собираемого из отдельных панелей и блоков управления, однорядного или двухрядного, без блоков резисторов глубиной до 800 мм шкафного исполнения | D40: 1 м ширины по фронту | E40: 0.45
C41: ЗП | F41: 267.59 | G41: 1,2 | H41: 1 | I41: 144.5 | J41: 57.05 | K41: 8243.73
C42: ЭМ | F42: 95.26 | G42: 1,2 | H42: 1 | I42: 51.44 | J42: 16.55 | K42: 851.33
C43: в т.ч. ЗПМ | F43: 11.61 | G43: 1,2 | H43: 1 | I43: 6.27 | J43: 57.05 | K43: 357.7
C44: МР | F44: 263.81 | H44: 1 | I44: 118.71 | J44: 3.7 | K44: 439.23
A45: 3,1 | B45: 1.1-1-8146 Поправка: Гл.12.Прил.8.п.8. 3_12.00.01.11.001 | C45: Болты стальные оцинкованные с шестигранной головкой, с полной резьбой, с гайкой оцинкованной, М6, длина от 12 до 60 мм | D45: кг | E45: 0.5625 | F45: 31.08 | H45: 1 | I45: 17.48 | J45: 3.59 | K45: 62.75
C46: НР от ФОТ | D46: % | E46: 97 | I46: 146.25 | J46: 97 | K46: 8343.39
C47: СП от ФОТ | D47: % | E47: 51 | I47: 76.89 | J47: 51 | K47: 4386.73
C48: ЗТР | D48: чел-ч | E48: 20.6 | G48: 1,2 | H48: 1 | I48: 11.12
C49: ВСЕГО работ по позиции: | H49: 555.27 | J49: 22327.16
C50: ВСЕГО по позиции: | H50: 555.27 | J50: 22327.16
A52: 4 | B52: Прайс-лист | C52: ОБОРУДОВАНИЕ: Распределительная панель (на два ввода) 450х450х1800 14 665,86 = [129 425,83 / 1,22 / 7,54] + 3% Трансп + 1,2% Заг.скл | D52: ШТ | E52: 1 | F52: 14665.86 | H52: 1 | I52: 14665.86 | J52: 7.54 | K52: 110580.58
C53: ВСЕГО по позиции: | H53: 14665.86 | J53: 110580.58
A56: Итого по разделу: ВРУ | H56: 54049.38 | J56: 457922.71
A58: Раздел: ЩАП на 25А щит автоматического переключения резерва
A59: 5 | B59: 4.8-238-2 Поправка: Гл.12.Прил.8.п.8. 3_12.00.01.11.001 | C59: Монтаж щитов и стеллажей с блоками резисторов (ящиками сопротивлений) высотой свыше 1700 мм, щита, собираемого из отдельных панелей и блоков управления, однорядного или двухрядного, без блоков резисторов глубиной до 800 мм шкафного исполнения | D59: 1 м ширины по фронту | E59: 0.45
C60: ЗП | F60: 267.59 | G60: 1,2 | H60: 1 | I60: 144.5 | J60: 57.05 | K60: 8243.73
C61: ЭМ | F61: 95.26 | G61: 1,2 | H61: 1 | I61: 51.44 | J61: 16.55 | K61: 851.33
C62: в т.ч. ЗПМ | F62: 11.61 | G62: 1,2 | H62: 1 | I62: 6.27 | J62: 57.05 | K62: 357.7
C63: МР | F63: 263.81 | H63: 1 | I63: 118.71 | J63: 3.7 | K63: 439.23
A64: 5,1 | B64: 1.1-1-8146 Поправка: Гл.12.Прил.8.п.8. 3_12.00.01.11.001 | C64: Болты стальные оцинкованные с шестигранной головкой, с полной резьбой, с гайкой оцинкованной, М6, длина от 12 до 60 мм | D64: кг | E64: 0.5625 | F64: 31.08 | H64: 1 | I64: 17.48 | J64: 3.59 | K64: 62.75
C65: НР от ФОТ | D65: % | E65: 97 | I65: 146.25 | J65: 97 | K65: 8343.39
C66: СП от ФОТ | D66: % | E66: 51 | I66: 76.89 | J66: 51 | K66: 4386.73
C67: ЗТР | D67: чел-ч | E67: 20.6 | G67: 1,2 | H67: 1 | I67: 11.12
C68: ВСЕГО работ по позиции: | H68: 555.27 | J68: 22327.16
C69: ВСЕГО по позиции: | H69: 555.27 | J69: 22327.16
A71: 6 | B71: Прайс-лист | C71: ОБОРУДОВАНИЕ:_x000D_ Распределительная панель (от ЩАП) 450х450х2000 11 421,94 = [100 798,38 / 1,22 / 7,54] + 3% Трансп + 1,2% Заг.скл | D71: ШТ | E71: 1 | F71: 11421.94 | H71: 1 | I71: 11421.94 | J71: 7.54 | K71: 86121.43
C72: ВСЕГО по позиции: | H72: 11421.94 | J72: 86121.43
A75: Итого по разделу: ЩАП на 25А щит автоматического переключения резерва | H75: 11977.21 | J75: 108448.59
A77: Раздел: ЩМК96 для контроля напряжения - 8шт
A78: 7 | B78: 4.8-238-2 Поправка: Гл.12.Прил.8.п.8. 3_12.00.01.11.001 | C78: Монтаж щитов и стеллажей с блоками резисторов (ящиками сопротивлений) высотой свыше 1700 мм, щита, собираемого из отдельных панелей и блоков управления, однорядного или двухрядного, без блоков резисторов глубиной до 800 мм шкафного исполнения | D78: 1 м ширины по фронту | E78: 3.6
C79: Объем: 3,6=0,45*8
C80: ЗП | F80: 267.59 | G80: 1,2 | H80: 1 | I80: 1155.99 | J80: 57.05 | K80: 65949.23
C81: ЭМ | F81: 95.26 | G81: 1,2 | H81: 1 | I81: 411.52 | J81: 16.55 | K81: 6810.66
C82: в т.ч. ЗПМ | F82: 11.61 | G82: 1,2 | H82: 1 | I82: 50.16 | J82: 57.05 | K82: 2861.63
C83: МР | F83: 263.81 | H83: 1 | I83: 949.72 | J83: 3.7 | K83: 3513.96
A84: 7,1 | B84: 1.1-1-8146 Поправка: Гл.12.Прил.8.п.8. 3_12.00.01.11.001 | C84: Болты стальные оцинкованные с шестигранной головкой, с полной резьбой, с гайкой оцинкованной, М6, длина от 12 до 60 мм | D84: кг | E84: 4.5 | F84: 31.08 | H84: 1 | I84: 139.86 | J84: 3.59 | K84: 502.1
C85: НР от ФОТ | D85: % | E85: 97 | I85: 1169.97 | J85: 97 | K85: 66746.53
C86: СП от ФОТ | D86: % | E86: 51 | I86: 615.14 | J86: 51 | K86: 35093.54
C87: ЗТР | D87: чел-ч | E87: 20.6 | G87: 1,2 | H87: 1 | I87: 88.99
C88: ВСЕГО работ по позиции: | H88: 4442.2 | J88: 178616.02
C89: ВСЕГО по позиции: | H89: 4442.2 | J89: 178616.02
A91: 8 | B91: Прайс-лист | C91: ОБОРУДОВАНИЕ: Распределительная панель (АВР) ПЭ СПЗ 450х450х2000, РП3 10 856,46 = [95 807,98 / 1,22 / 7,54] + 3% Трансп + 1,2% Заг.скл | D91: ШТ | E91: 8 | F91: 10856.46 | H91: 1 | I91: 86851.68 | J91: 7.54 | K91: 654861.67
C92: ВСЕГО по позиции: | H92: 86851.68 | J92: 654861.67
A94: 9 | B94: 4.8-238-2 Поправка: Гл.12.Прил.8.п.8. 3_12.00.01.11.001 | C94: Монтаж щитов и стеллажей с блоками резисторов (ящиками сопротивлений) высотой свыше 1700 мм, щита, собираемого из отдельных панелей и блоков управления, однорядного или двухрядного, без блоков резисторов глубиной до 800 мм шкафного исполнения | D94: 1 м ширины по фронту | E94: 3.6
C95: Объем: 3,6=0,45*8
C96: ЗП | F96: 267.59 | G96: 1,2 | H96: 1 | I96: 1155.99 | J96: 57.05 | K96: 65949.23
C97: ЭМ | F97: 95.26 | G97: 1,2 | H97: 1 | I97: 411.52 | J97: 16.55 | K97: 6810.66
C98: в т.ч. ЗПМ | F98: 11.61 | G98: 1,2 | H98: 1 | I98: 50.16 | J98: 57.05 | K98: 2861.63
C99: МР | F99: 263.81 | H99: 1 | I99: 949.72 | J99: 3.7 | K99: 3513.96
A100: 9,1 | B100: 1.1-1-8146 Поправка: Гл.12.Прил.8.п.8. 3_12.00.01.11.001 | C100: Болты стальные оцинкованные с шестигранной головкой, с полной резьбой, с гайкой оцинкованной, М6, длина от 12 до 60 мм | D100: кг | E100: 4.5 | F100: 31.08 | H100: 1 | I100: 139.86 | J100: 3.59 | K100: 502.1
C101: НР от ФОТ | D101: % | E101: 97 | I101: 1169.97 | J101: 97 | K101: 66746.53
C102: СП от ФОТ | D102: % | E102: 51 | I102: 615.14 | J102: 51 | K102: 35093.54
C103: ЗТР | D103: чел-ч | E103: 20.6 | G103: 1,2 | H103: 1 | I103: 88.99
C104: ВСЕГО работ по позиции: | H104: 4442.2 | J104: 178616.02
C105: ВСЕГО по позиции: | H105: 4442.2 | J105: 178616.02
A107: 10 | B107: Прайс-лист | C107: ОБОРУДОВАНИЕ: Панель АВР 100А 450х450х2000 18 649,18 = [164 578,46 / 1,22 / 7,54] + 3% Трансп + 1,2% Заг.скл | D107: ШТ | E107: 8 | F107: 18649.18 | H107: 1 | I107: 149193.44 | J107: 7.54 | K107: 1124918.5
C108: ВСЕГО по позиции: | H108: 149193.44 | J108: 1124918.5
A111: Итого по разделу: ЩМК96 для контроля напряжения - 8шт | H111: 244929.52 | J111: 2137012.2
A113: Раздел: Щитовое оборудование
A114: 11 | B114: 4.8-240-4 Поправка: Гл.12.Прил.8.п.8. 3_12.00.01.11.001 | C114: Монтаж пультов и шкафов управления, шкафа (пульта) управления навесного, высотой, шириной, глубиной до 600х600х350 мм | D114: 1 ШТ. | E114: 8
C115: ЗП | F115: 26.76 | G115: 1,2 | H115: 1 | I115: 256.9 | J115: 57.05 | K115: 14656.15
C116: ЭМ | F116: 17.42 | G116: 1,2 | H116: 1 | I116: 167.23 | J116: 20.11 | K116: 3363
C117: в т.ч. ЗПМ | F117: 3.16 | G117: 1,2 | H117: 1 | I117: 30.34 | J117: 57.05 | K117: 1730.9
C118: МР | F118: 1.46 | H118: 1 | I118: 11.68 | J118: 13.13 | K118: 153.36
A119: 11,1 | B119: 1.1-1-60 | C119: Болты строительные с шестигранной головкой с гайками, М6 | D119: т | E119: 0.0008 | F119: 22524.65 | H119: 1 | I119: 18.02 | J119: 5.94 | K119: 107.04
C120: НР от ФОТ | D120: % | E120: 97 | I120: 278.62 | J120: 97 | K120: 15895.44
C121: СП от ФОТ | D121: % | E121: 51 | I121: 146.49 | J121: 51 | K121: 8357.4
C122: ЗТР | D122: чел-ч | E122: 2.06 | G122: 1,2 | H122: 1 | I122: 19.78
...

Sheet ЛС 02-01-04
J2: Форма № 4б
A3: =ССРСС!A11 -> Выполнение работ по капитальному ремонту здания в Басманном районе ЦАО города Москвы
A4: (наименование стройки и/или объекта)
A6: ЛОКАЛЬНАЯ СМЕТА № 02-01-04
A8: Водоснабжение
A9: (наименование работ и затрат)
I12: В базисном уровне цен | J12: В текущем уровне цен
E13: Сметная стоимость | I13: 38.23 | J13: 582.52 | K13: тыс.руб.
E14: Строительные работы | I14: 37.97 | J14: 568.39 | K14: тыс.руб.
E15: Работы по монтажу оборудования | I15: 0.26 | J15: 14.13 | K15: тыс.руб.
E16: Средства на оплату труда | I16: 2.28 | J16: 129.93 | K16: тыс.руб.
E17: Затраты труда | I17: 180.6 | K17: чел.-ч.
A19: Составлен(а) по ТСН-2001 с учетом Дополнения №: 81
A20: № и период сборника коэффициентов (индексов) пересчета: Коэффициенты к ТСН-2001 МГЭ Дополнение 81, ремонт №220 II квартал 2026 года и Коэффициенты к ТСН-2001.13-2 Дополнение 47 №65 II квартал 2026 года
A21: № п/п | B21: Шифр расценки и коды ресурсов | C21: Наименование работ и затрат | D21: Ед. изм. | E21: Кол-во единиц | F21: Цена на ед. изм., руб. | G21: Попра- вочные коэффи- циенты | H21: Коэффи- циенты зимних удорожа- ний | I21: Всего в ценах на январь 2000 года, руб. | J21: Коэффи- циенты (индек- сы) пере- счета, нормы НР и СП | K21: ВСЕГО затрат в текущем уровне цен, руб.
A22: 1 | B22: 2 | C22: 3 | D22: 4 | E22: 5 | F22: 6 | G22: 7 | H22: 8 | I22: 9 | J22: 10 | K22: 11
A23: Раздел: Внутренние сети холодного водоснабжения
A24: 1 | B24: 3.16-38-1 Поправка: Гл.6.Прил.2.2.п.2.2.6_06.00.01.07.001 Поправка: Гл.12.Прил.8.п.8. 3_12.00.01.11.001 | C24: Прокладка трубопроводов из стальных труб на бессварных разъемных муфтовых соединениях диаметром до 25 мм | D24: 100 м | E24: 0.66
C25: Объем: 0,66=(5+21+40)/100
C26: ЗП | F26: 236.83 | G26: 1,15*1,2 | H26: 1 | I26: 215.7 | J26: 57.05 | K26: 12305.69
C27: ЭМ | F27: 4.07 | G27: 1,25*1,2 | H27: 1 | I27: 4.03 | J27: 13.79 | K27: 55.57
C28: в т.ч. ЗПМ | F28: 0.3 | G28: 1,25*1,2 | H28: 1 | I28: 0.3 | J28: 57.05 | K28: 17.12
C29: МР | F29: 30.04 | H29: 1 | I29: 19.83 | J29: 1.83 | K29: 36.29
C30: НР от ФОТ | D30: % | E30: 109 | I30: 235.44 | J30: 109 | K30: 13431.86
C31: СП от ФОТ | D31: % | E31: 61 | I31: 131.76 | J31: 61 | K31: 7516.91
C32: ЗТР | D32: чел-ч | E32: 19.12 | G32: 1,15*1,2 | H32: 1 | I32: 17.41
C33: ВСЕГО работ по позиции: | H33: 606.76 | J33: 33346.32
C34: ВСЕГО по позиции: | H34: 606.76 | J34: 33346.32
A36: 2 | B36: 1.12-1-52 | C36: Узел трубопровода из стальных водогазопроводных оцинкованных труб, с гильзами, для водоснабжения, диаметр условного прохода 15 мм | D36: м | E36: 5 | F36: 28.1 | H36: 1 | I36: 140.5 | J36: 18.63 | K36: 2617.52
C37: ВСЕГО по позиции: | H37: 140.5 | J37: 2617.52
A39: 3 | B39: 1.12-2-1163 | C39: Хомуты из оцинкованной стали с резиновыми прокладками для жесткого и скользящего крепления полипропиленовых труб, наружный диаметр 20 мм/15мм | D39: шт. | E39: 130 | F39: 17.33 | H39: 1 | I39: 2252.9 | J39: 0.98 | K39: 2207.84
C40: ВСЕГО по позиции: | H40: 2252.9 | J40: 2207.84
A42: 4 | B42: 1.12-1-53 | C42: Узел трубопровода из стальных водогазопроводных оцинкованных труб, с гильзами, для водоснабжения, диаметр условного прохода 20 мм | D42: м | E42: 21 | F42: 31.41 | H42: 1 | I42: 659.61 | J42: 18.51 | K42: 12209.38
C43: ВСЕГО по позиции: | H43: 659.61 | J43: 12209.38
A45: 5 | B45: 1.12-2-1163 | C45: Хомуты из оцинкованной стали с резиновыми прокладками для жесткого и скользящего крепления полипропиленовых труб, наружный диаметр 20 мм | D45: шт. | E45: 20 | F45: 17.33 | H45: 1 | I45: 346.6 | J45: 0.98 | K45: 339.67
C46: ВСЕГО по позиции: | H46: 346.6 | J46: 339.67
A48: 6 | B48: 1.1-1-59 | C48: Болты строительные анкерные с гайками | D48: т | E48: 0.00072 | F48: 26867.38 | H48: 1 | I48: 19.34 | J48: 4.39 | K48: 84.9
C49: Объем: 0,00072=0,018*40/1000
C50: ВСЕГО по позиции: | H50: 19.34 | J50: 84.9
A52: 7 | B52: 1.12-1-54 | C52: Узел трубопровода из стальных водогазопроводных оцинкованных труб, с гильзами, для водоснабжения, диаметр условного прохода 25 мм | D52: м | E52: 40 | F52: 41.57 | H52: 1 | I52: 1662.8 | J52: 16.56 | K52: 27535.97
C53: ВСЕГО по позиции: | H53: 1662.8 | J53: 27535.97
A55: 8 | B55: 1.12-2-1164 | C55: Хомуты из оцинкованной стали с резиновыми прокладками для жесткого и скользящего крепления полипропиленовых труб, наружный диаметр 32 мм /25мм | D55: шт. | E55: 20 | F55: 19.61 | H55: 1 | I55: 392.2 | J55: 0.91 | K55: 356.9
C56: ВСЕГО по позиции: | H56: 392.2 | J56: 356.9
A58: 9 | B58: 1.1-1-59 | C58: Болты строительные анкерные с гайками | D58: т | E58: 0.00072 | F58: 26867.38 | H58: 1 | I58: 19.34 | J58: 4.39 | K58: 84.9
C59: Объем: 0,00072=0,018*40/1000
C60: ВСЕГО по позиции: | H60: 19.34 | J60: 84.9
A62: 10 | B62: 1.13-4-125 | C62: Кран шаровой, латунный, полнопроходной, муфтовый, 11б27п1, номинальное давление PN 1,6 МПа, номинальный диаметр DN 15 мм | D62: шт. | E62: 10 | F62: 17.59 | H62: 1 | I62: 175.9 | J62: 7.1 | K62: 1248.89
C63: ВСЕГО по позиции: | H63: 175.9 | J63: 1248.89
A65: 11 | B65: 1.13-4-126 | C65: Кран шаровой, латунный, полнопроходной, муфтовый, 11б27п1, номинальное давление PN 1,6 МПа, номинальный диаметр DN 20 мм | D65: шт. | E65: 5 | F65: 28.16 | H65: 1 | I65: 140.8 | J65: 5.38 | K65: 757.5
C66: ВСЕГО по позиции: | H66: 140.8 | J66: 757.5
A68: 12 | B68: 1.13-4-127 | C68: Кран шаровой, латунный, полнопроходной, муфтовый, 11б27п1, номинальное давление PN 1,6 МПа, номинальный диаметр DN 25 мм | D68: шт. | E68: 2 | F68: 66.81 | H68: 1 | I68: 133.62 | J68: 3.99 | K68: 533.14
C69: ВСЕГО по позиции: | H69: 133.62 | J69: 533.14
A71: 13 | B71: 3.16-40-1 Поправка: Гл.6.Прил.2.2.п.2.2.6_06.00.01.07.001 Поправка: Гл.12.Прил.8.п.8. 3_12.00.01.11.001 | C71: Прокладка напорного трубопровода водоснабжения и отопления из многослойного полипропилена, армированного стекловолокном, из заранее собранных узлов, наружный диаметр 20 мм | D71: 100 м | E71: 0.5
C72: Объем: 0,5=50/100
C73: ЗП | F73: 180.31 | G73: 1,15*1,2 | H73: 1 | I73: 124.41 | J73: 57.05 | K73: 7097.59
C74: ЭМ | F74: 18.38 | G74: 1,25*1,2 | H74: 1 | I74: 13.79 | J74: 12.64 | K74: 174.31
C75: в т.ч. ЗПМ | F75: 0.5 | G75: 1,25*1,2 | H75: 1 | I75: 0.38 | J75: 57.05 | K75: 21.68
C76: МР | F76: 153.1 | H76: 1 | I76: 76.55 | J76: 1.95 | K76: 149.27
A77: 13,1 | B77: 1.12-5-573 | C77: Трубы напорные многослойные, армированные стекловолокном из полипропилена PPR100/PPRGF/PPR100, ГОСТ 32415-2013, диаметр 20 мм, толщина стенки 2,8 мм | D77: м | E77: 51.25 | F77: 16.1 | H77: 1 | I77: 825.13 | J77: 2.66 | K77: 2194.85
A78: 13,2 | B78: 1.7-3-8 | C78: Сверло победитовое, диаметр 8 мм, длина 80 мм | D78: шт. | E78: 0.525 | F78: 11.82 | H78: 1 | I78: 6.21 | J78: 5.77 | K78: 35.83
C79: НР от ФОТ | D79: % | E79: 109 | I79: 136.02 | J79: 109 | K79: 7760
C80: СП от ФОТ | D80: % | E80: 61 | I80: 76.12 | J80: 61 | K80: 4342.75
C81: ЗТР | D81: чел-ч | E81: 14.56 | G81: 1,15*1,2 | H81: 1 | I81: 10.05
C82: ВСЕГО работ по позиции: | H82: 1258.23 | J82: 21754.6
C83: ВСЕГО по позиции: | H83: 1258.23 | J83: 21754.6
A85: 14 | B85: 3.16-41-1 Поправка: Гл.6.Прил.2.2.п.2.2.6_06.00.01.07.001 Поправка: Гл.12.Прил.8.п.8. 3_12.00.01.11.001 | C85: Сборка узла напорного трубопровода водоснабжения и отопления из многослойного полипропилена, армированного стекловолокном, раструбная сварка, наружный диаметр 20 мм | D85: 100 сварных соединений | E85: 2.11
C86: Объем: 2,11=(50*2+17*3+30*2)/100
C87: ЗП | F87: 21.01 | G87: 1,15*1,2 | H87: 1 | I87: 61.18 | J87: 57.05 | K87: 3490.32
C88: ЭМ | F88: 1.1 | G88: 1,25*1,2 | H88: 1 | I88: 3.48 | J88: 13.09 | K88: 45.55
C89: НР от ФОТ | D89: % | E89: 109 | I89: 66.69 | J89: 109 | K89: 3804.45
C90: СП от ФОТ | D90: % | E90: 61 | I90: 37.32 | J90: 61 | K90: 2129.1
C91: ЗТР | D91: чел-ч | E91: 1.56 | G91: 1,15*1,2 | H91: 1 | I91: 4.54
C92: ВСЕГО работ по позиции: | H92: 168.67 | J92: 9469.42
C93: ВСЕГО по позиции: | H93: 168.67 | J93: 9469.42
A95: 15 | B95: 1.12-5-879 | C95: Муфта из полипропилена PP-R, ГОСТ 32415-2013, комбинированная с металлом, номинальное давление PN 25, номинальный диаметр DN 20 мм, наружная резьба 1/2'' | D95: шт. | E95: 50 | F95: 44.79 | H95: 1 | I95: 2239.5 | J95: 4.27 | K95: 9562.67
C96: ВСЕГО по позиции: | H96: 2239.5 | J96: 9562.67
A98: 16 | B98: 1.12-5-898 | C98: Тройник из полипропилена PP-R, ГОСТ 32415-2013, комбинированный с металлом, номинальное давление PN 25, номинальный диаметр DN 20 мм, внутренняя резьба 1/2" | D98: шт. | E98: 17 | F98: 21.19 | H98: 1 | I98: 360.23 | J98: 6.74 | K98: 2427.95
C99: ВСЕГО по позиции: | H99: 360.23 | J99: 2427.95
A101: 17 | B101: 1.12-5-347 | C101: Угольник из полипропилена PP-R80, для трубопроводов холодного и горячего водоснабжения и отопления, диаметр 20 мм | D101: шт. | E101: 30 | F101: 7.39 | H101: 1 | I101: 221.7 | J101: 14.62 | K101: 3241.25
C102: ВСЕГО по позиции: | H102: 221.7 | J102: 3241.25
A104: 18 | B104: 3.16-40-2 Поправка: Гл.6.Прил.2.2.п.2.2.6_06.00.01.07.001 Поправка: Гл.12.Прил.8.п.8. 3_12.00.01.11.001 | C104: Прокладка напорного трубопровода водоснабжения и отопления из многослойного полипропилена, армированного стекловолокном, из заранее собранных узлов, наружный диаметр 25 мм | D104: 100 м | E104: 0.04
C105: Объем: 0,04=4/100
C106: ЗП | F106: 174.07 | G106: 1,15*1,2 | H106: 1 | I106: 9.61 | J106: 57.05 | K106: 548.25
C107: ЭМ | F107: 19.67 | G107: 1,25*1,2 | H107: 1 | I107: 1.18 | J107: 13.12 | K107: 15.48
C108: в т.ч. ЗПМ | F108: 0.76 | G108: 1,25*1,2 | H108: 1 | I108: 0.05 | J108: 57.05 | K108: 2.85
C109: МР | F109: 134.7 | H109: 1 | I109: 5.39 | J109: 2.11 | K109: 11.37
A110: 18,1 | B110: 1.12-5-574 | C110: Трубы напорные многослойные, армированные стекловолокном из полипропилена PPR100/PPRGF/PPR100, ГОСТ 32415-2013, диаметр 25 мм, толщина стенки 3,5 мм | D110: м | E110: 4.1 | F110: 25.04 | H110: 1 | I110: 102.66 | J110: 2.52 | K110: 258.7
A111: 18,2 | B111: 1.7-3-8 | C111: Сверло победитовое, диаметр 8 мм, длина 80 мм | D111: шт. | E111: 0.036 | F111: 11.82 | H111: 1 | I111: 0.43 | J111: 5.77 | K111: 2.48
C112: НР от ФОТ | D112: % | E112: 109 | I112: 10.53 | J112: 109 | K112: 600.7
C113: СП от ФОТ | D113: % | E113: 61 | I113: 5.89 | J113: 61 | K113: 336.17
C114: ЗТР | D114: чел-ч | E114: 14.08 | G114: 1,15*1,2 | H114: 1 | I114: 0.78
C115: ВСЕГО работ по позиции: | H115: 135.69 | J115: 1773.15
C116: ВСЕГО по позиции: | H116: 135.69 | J116: 1773.15
A118: 19 | B118: 3.16-41-2 Поправка: Гл.6.Прил.2.2.п.2.2.6_06.00.01.07.001 Поправка: Гл.12.Прил.8.п.8. 3_12.00.01.11.001 | C118: Сборка узла напорного трубопровода водоснабжения и отопления из многослойного полипропилена, армированного стекловолокном, раструбная сварка, наружный диаметр 25 мм | D118: 100 сварных соединений | E118: 0.45
C119: Объем: 0,45=(5*2+5*3+5*2+5*2)/100
C120: ЗП | F120: 31.49 | G120: 1,15*1,2 | H120: 1 | I120: 19.56 | J120: 57.05 | K120: 1115.9
C121: ЭМ | F121: 1.57 | G121: 1,25*1,2 | H121: 1 | I121: 1.06 | J121: 13.1 | K121: 13.89
C122: НР от ФОТ | D122: % | E122: 109 | I122: 21.32 | J122: 109 | K122: 1216.33
C123: СП от ФОТ | D123: % | E123: 61 | I123: 11.93 | J123: 61 | K123: 680.7
C124: ЗТР | D124: чел-ч | E124: 2.34 | G124: 1,15*1,2 | H124: 1 | I124: 1.45
...

Sheet ЛС 02-01-05
J2: Форма № 4б
A3: =ССРСС!A11 -> Выполнение работ по капитальному ремонту здания в Басманном районе ЦАО города Москвы
A4: (наименование стройки и/или объекта)
A6: ЛОКАЛЬНАЯ СМЕТА № 02-01-05
A8: Водоотведение
A9: (наименование работ и затрат)
I12: В базисном уровне цен | J12: В текущем уровне цен
E13: Сметная стоимость | I13: 66.73 | J13: 841.37 | K13: тыс.руб.
E14: Строительные работы | I14: 66.73 | J14: 841.37 | K14: тыс.руб.
E15: Средства на оплату труда | I15: 2.3 | J15: 131.45 | K15: тыс.руб.
E16: Затраты труда | I16: 185.35 | K16: чел.-ч.
A18: Составлен(а) по ТСН-2001 с учетом Дополнения №: 81
A19: № и период сборника коэффициентов (индексов) пересчета: Коэффициенты к ТСН-2001 МГЭ Дополнение 81, ремонт №220 II квартал 2026 года и Коэффициенты к ТСН-2001.13-2 Дополнение 47 №65 II квартал 2026 года
A20: № п/п | B20: Шифр расценки и коды ресурсов | C20: Наименование работ и затрат | D20: Ед. изм. | E20: Кол-во единиц | F20: Цена на ед. изм., руб. | G20: Попра- вочные коэффи- циенты | H20: Коэффи- циенты зимних удорожа- ний | I20: Всего в ценах на январь 2000 года, руб. | J20: Коэффи- циенты (индек- сы) пере- счета, нормы НР и СП | K20: ВСЕГО затрат в текущем уровне цен, руб.
A21: 1 | B21: 2 | C21: 3 | D21: 4 | E21: 5 | F21: 6 | G21: 7 | H21: 8 | I21: 9 | J21: 10 | K21: 11
A22: Раздел: Канализация хозяйственно-бытовая (К1)
A23: 1 | B23: 3.16-2-3 Поправка: Гл.6.Прил.2.2.п.2.2.6_06.00.01.07.001 Поправка: Гл.12.Прил.8.п.8. 3_12.00.01.11.001 | C23: Прокладка по стенам зданий и в каналах труб чугунных напорных раструбных диаметром 100 мм | D23: 100 м труб | E23: 0.5
C24: Объем: 0,5=50/100
C25: ЗП | F25: 1395.48 | G25: 1,15*1,2 | H25: 1 | I25: 962.88 | J25: 57.05 | K25: 54932.3
C26: ЭМ | F26: 144.95 | G26: 1,25*1,2 | H26: 1 | I26: 108.71 | J26: 17.13 | K26: 1862.2
C27: в т.ч. ЗПМ | F27: 20.7 | G27: 1,25*1,2 | H27: 1 | I27: 15.53 | J27: 57.05 | K27: 885.99
C28: МР | F28: 202.76 | H28: 1 | I28: 101.38 | J28: 10.9 | K28: 1105.04
A29: 1,1 | B29: 1.12-1-69 | C29: Узлы трубопроводов из чугунных канализационных труб с фасонными частями, диаметр условного прохода 100 мм | D29: м | E29: 50.5 | F29: 129.06 | H29: 1 | I29: 6517.53 | J29: 24.94 | K29: 162547.2
C30: НР от ФОТ | D30: % | E30: 109 | I30: 1066.47 | J30: 109 | K30: 60841.94
C31: СП от ФОТ | D31: % | E31: 61 | I31: 596.83 | J31: 61 | K31: 34049.16
C32: ЗТР | D32: чел-ч | E32: 116 | G32: 1,15*1,2 | H32: 1 | I32: 80.04
C33: ВСЕГО работ по позиции: | H33: 9353.8 | J33: 315337.84
C34: ВСЕГО по позиции: | H34: 9353.8 | J34: 315337.84
A36: 2 | B36: 1.12-10-16 | C36: Ревизия чугунная, диаметр условного прохода 100 мм | D36: шт. | E36: 6 | F36: 66.36 | H36: 1 | I36: 398.16 | J36: 23.78 | K36: 9468.24
C37: ВСЕГО по позиции: | H37: 398.16 | J37: 9468.24
A39: 3 | B39: 3.16-28-2 Поправка: Гл.6.Прил.2.2.п.2.2.6_06.00.01.07.001 Поправка: Гл.12.Прил.8.п.8. 3_12.00.01.11.001 | C39: Врезки в действующие внутренние сети трубопроводов канализации диаметром 100 мм | D39: 1 врезка | E39: 1
C40: ЗП | F40: 99.95 | G40: 1,15*1,2 | H40: 1 | I40: 137.93 | J40: 57.05 | K40: 7868.91
C41: ЭМ | F41: 0.83 | G41: 1,25*1,2 | H41: 1 | I41: 1.25 | J41: 17.47 | K41: 21.84
C42: в т.ч. ЗПМ | F42: 0.13 | G42: 1,25*1,2 | H42: 1 | I42: 0.2 | J42: 57.05 | K42: 11.41
C43: МР | F43: 8.01 | H43: 1 | I43: 8.01 | J43: 22.99 | K43: 184.15
C44: НР от ФОТ | D44: % | E44: 109 | I44: 150.56 | J44: 109 | K44: 8589.55
C45: СП от ФОТ | D45: % | E45: 61 | I45: 84.26 | J45: 61 | K45: 4807
C46: ЗТР | D46: чел-ч | E46: 8.94 | G46: 1,15*1,2 | H46: 1 | I46: 12.34
C47: ВСЕГО работ по позиции: | H47: 382.01 | J47: 21471.45
C48: ВСЕГО по позиции: | H48: 382.01 | J48: 21471.45
A50: 4 | B50: 3.16-13-2 Поправка: Гл.6.Прил.2.2.п.2.2.6_06.00.01.07.001 Поправка: Гл.12.Прил.8.п.8. 3_12.00.01.11.001 | C50: Прокладка трубопроводов канализации из ПВХ труб диаметром 100 мм - 150 мм | D50: 100 м | E50: 0.62
C51: Объем: 0,62=62/100
C52: ЗП | F52: 716.8 | G52: 1,15*1,2 | H52: 1 | I52: 613.29 | J52: 57.05 | K52: 34988.19
C53: ЭМ | F53: 20.2 | G53: 1,25*1,2 | H53: 1 | I53: 18.79 | J53: 17.06 | K53: 320.56
C54: в т.ч. ЗПМ | F54: 2.86 | G54: 1,25*1,2 | H54: 1 | I54: 2.66 | J54: 57.05 | K54: 151.75
C55: МР | F55: 231.71 | H55: 1 | I55: 143.66 | J55: 12.69 | K55: 1823.05
A56: 4,1 | B56: 1.12-2-1167 | C56: Хомуты из оцинкованной стали с резиновыми прокладками для жесткого и скользящего крепления полипропиленовых труб, наружный диаметр 110 мм | D56: шт. | E56: 75 | F56: 54.28 | H56: 1 | I56: 4071 | J56: 0.82 | K56: 3338.22
A57: 4,2 | B57: 1.12-1-80 | C57: Заготовка трубная из непластифицированного поливинилхлорида, для внутренней канализации, без средств крепления, диаметр 110 мм | D57: м | E57: 62 | F57: 179.22 | H57: 1 | I57: 11111.64 | J57: 2.28 | K57: 25334.54
A58: 4,3 | B58: 1.12-5-133 | C58: Ревизия из полиэтилена, диаметр 110 мм | D58: шт. | E58: 6 | F58: 53.05 | H58: 1 | I58: 318.3 | J58: 3.92 | K58: 1247.74
C59: НР от ФОТ | D59: % | E59: 109 | I59: 671.39 | J59: 109 | K59: 38302.53
C60: СП от ФОТ | D60: % | E60: 61 | I60: 375.73 | J60: 61 | K60: 21435.36
C61: ЗТР | D61: чел-ч | E61: 56 | G61: 1,15*1,2 | H61: 1 | I61: 47.91
C62: ВСЕГО работ по позиции: | H62: 17323.8 | J62: 126790.19
C63: ВСЕГО по позиции: | H63: 17323.8 | J63: 126790.19
A65: 5 | B65: 1.12-5-134 | C65: Крышка ревизии из полиэтилена, диаметр 110 мм | D65: шт. | E65: 6 | F65: 20.21 | H65: 1 | I65: 121.26 | J65: 4.67 | K65: 566.28
C66: ВСЕГО по позиции: | H66: 121.26 | J66: 566.28
A68: 6 | B68: 1.12-5-133 | C68: Ревизия из полиэтилена, диаметр 110 мм / прочистка | D68: шт. | E68: 5 | F68: 53.05 | H68: 1 | I68: 265.25 | J68: 3.92 | K68: 1039.78
C69: ВСЕГО по позиции: | H69: 265.25 | J69: 1039.78
A71: 7 | B71: 1.1-1-59 | C71: Болты строительные анкерные с гайками | D71: т | E71: 0.045 | F71: 26867.38 | H71: 1 | I71: 1209.03 | J71: 4.39 | K71: 5307.64
C72: Объем: 0,045=0,3*150/1000
C73: ВСЕГО по позиции: | H73: 1209.03 | J73: 5307.64
A75: 8 | B75: 3.16-13-1 Поправка: Гл.6.Прил.2.2.п.2.2.6_06.00.01.07.001 Поправка: Гл.12.Прил.8.п.8. 3_12.00.01.11.001 | C75: Прокладка трубопроводов канализации из ПВХ труб диаметром до 50 мм | D75: 100 м | E75: 0.17
C76: Объем: 0,17=17/100
C77: ЗП | F77: 747.52 | G77: 1,15*1,2 | H77: 1 | I77: 175.37 | J77: 57.05 | K77: 10004.86
C78: ЭМ | F78: 10.1 | G78: 1,25*1,2 | H78: 1 | I78: 2.58 | J78: 17.06 | K78: 44.01
C79: в т.ч. ЗПМ | F79: 1.43 | G79: 1,25*1,2 | H79: 1 | I79: 0.36 | J79: 57.05 | K79: 20.54
C80: МР | F80: 85.16 | H80: 1 | I80: 14.48 | J80: 12.65 | K80: 183.17
A81: 8,1 | B81: 1.12-2-1165 | C81: Хомуты из оцинкованной стали с резиновыми прокладками для жесткого и скользящего крепления полипропиленовых труб, наружный диаметр 50 мм | D81: шт. | E81: 23 | F81: 21.9 | H81: 1 | I81: 503.7 | J81: 0.93 | K81: 468.44
A82: 8,2 | B82: 1.12-1-79 | C82: Заготовка трубная из непластифицированного поливинилхлорида, для внутренней канализации, без средств крепления, диаметр 50 мм | D82: м | E82: 17 | F82: 123.2 | H82: 1 | I82: 2094.4 | J82: 1.76 | K82: 3686.14
A83: 8,3 | B83: 1.12-5-97 | C83: Ревизия из полиэтилена низкого давления, с крышкой, для канализации, диаметр 50 мм / прочистка | D83: шт. | E83: 1 | F83: 16.74 | H83: 1 | I83: 16.74 | J83: 3.51 | K83: 58.76
C84: НР от ФОТ | D84: % | E84: 109 | I84: 191.55 | J84: 109 | K84: 10927.69
C85: СП от ФОТ | D85: % | E85: 61 | I85: 107.2 | J85: 61 | K85: 6115.49
C86: ЗТР | D86: чел-ч | E86: 58.4 | G86: 1,15*1,2 | H86: 1 | I86: 13.7
C87: ВСЕГО работ по позиции: | H87: 3106.02 | J87: 31488.56
C88: ВСЕГО по позиции: | H88: 3106.02 | J88: 31488.56
A90: 9 | B90: 1.1-1-59 | C90: Болты строительные анкерные с гайками | D90: т | E90: 0.0138 | F90: 26867.38 | H90: 1 | I90: 370.77 | J90: 4.39 | K90: 1627.68
C91: Объем: 0,0138=0,3*46/1000
C92: ВСЕГО по позиции: | H92: 370.77 | J92: 1627.68
A94: 10 | B94: 3.16-33-1 Поправка: Гл.6.Прил.2.2.п.2.2.6_06.00.01.07.001 Поправка: Гл.12.Прил.8.п.8. 3_12.00.01.11.001 | C94: Установка противопожарных муфт на канализационных стояках из полипропиленовых труб в междуэтажных перекрытиях, муфт обжимных | D94: 100 шт. | E94: 0.15
C95: Объем: 0,15=(3+12)/100
C96: ЗП | F96: 184.13 | G96: 1,15*1,2 | H96: 1 | I96: 38.11 | J96: 57.05 | K96: 2174.18
C97: НР от ФОТ | D97: % | E97: 109 | I97: 41.54 | J97: 109 | K97: 2369.86
C98: СП от ФОТ | D98: % | E98: 61 | I98: 23.25 | J98: 61 | K98: 1326.25
C99: ЗТР | D99: чел-ч | E99: 14.63 | G99: 1,15*1,2 | H99: 1 | I99: 3.03
C100: ВСЕГО работ по позиции: | H100: 102.9 | J100: 5870.29
C101: ВСЕГО по позиции: | H101: 102.9 | J101: 5870.29
A103: 11 | B103: 1.12-5-542 | C103: Муфта противопожарная из нержавеющей стали, с вкладышем из терморасширяющейся резины, для трубы диаметром 50 мм | D103: шт. | E103: 3 | F103: 181.59 | H103: 1 | I103: 544.77 | J103: 0.76 | K103: 414.03
C104: ВСЕГО по позиции: | H104: 544.77 | J104: 414.03
A106: 12 | B106: 1.12-5-456 | C106: Муфта противопожарная из нержавеющей стали, с вкладышем из терморасширяющейся резины, для трубы диаметром 110 мм | D106: шт. | E106: 12 | F106: 265.24 | H106: 1 | I106: 3182.88 | J106: 0.83 | K106: 2641.79
C107: ВСЕГО по позиции: | H107: 3182.88 | J107: 2641.79
A109: 13 | B109: 3.22-27-3 Поправка: Гл.6.Прил.2.2.п.2.2.6_06.00.01.07.001 Поправка: Гл.12.Прил.8.п.8. 3_12.00.01.11.001 | C109: Промывка без дезинфекции трубопроводов диаметром 100 мм / промывка сущ.выпусков канализации диам100мм гидродинамическим способом | D109: 1 КМ | E109: 0.01
C110: Объем: 0,01=10/1000
C111: ЗП | F111: 226.39 | G111: 1,15*1,2 | H111: 1 | I111: 3.12 | J111: 57.05 | K111: 178
C112: МР | F112: 199.37 | H112: 1 | I112: 1.99 | J112: 7.75 | K112: 15.42
C113: НР от ФОТ | D113: % | E113: 105 | I113: 3.28 | J113: 105 | K113: 186.9
C114: СП от ФОТ | D114: % | E114: 63 | I114: 1.97 | J114: 63 | K114: 112.14
C115: ЗТР | D115: чел-ч | E115: 20.6 | G115: 1,15*1,2 | H115: 1 | I115: 0.28
C116: ВСЕГО работ по позиции: | H116: 10.36 | J116: 492.46
C117: ВСЕГО по позиции: | H117: 10.36 | J117: 492.46
A119: 14 | B119: 3.26-16-1 Поправка: Гл.6.Прил.2.2.п.2.2.6_06.00.01.07.001 Поправка: Гл.12.Прил.8.п.8. 3_12.00.01.11.001 | C119: Изоляция трубопроводов изделиями из вспененного каучука, вспененного полиэтилена, трубками | D119: 10 м изоляции | E119: 1.5
...

Sheet ЛС 02-01-06
J2: Форма № 4б
A3: =ССРСС!A11 -> Выполнение работ по капитальному ремонту здания в Басманном районе ЦАО города Москвы
A4: (наименование стройки и/или объекта)
A6: ЛОКАЛЬНАЯ СМЕТА № 02-01-06
A8: Отопление
A9: (наименование работ и затрат)
I12: В базисном уровне цен | J12: В текущем уровне цен
E13: Сметная стоимость | I13: 68.45 | J13: 619.11 | K13: тыс.руб.
E14: Строительные работы | I14: 67.91 | J14: 611.12 | K14: тыс.руб.
E15: Работы по монтажу оборудования | I15: 0.08 | J15: 4.57 | K15: тыс.руб.
E16: Оборудование | I16: 0.46 | J16: 3.42 | K16: тыс.руб.
E17: Средства на оплату труда | I17: 1.59 | J17: 90.69 | K17: тыс.руб.
E18: Затраты труда | I18: 123.28 | K18: чел.-ч.
A20: Составлен(а) по ТСН-2001 с учетом Дополнения №: 81
A21: № и период сборника коэффициентов (индексов) пересчета: Коэффициенты к ТСН-2001 МГЭ Дополнение 81, ремонт №220 II квартал 2026 года и Коэффициенты к ТСН-2001.13-2 Дополнение 47 №65 II квартал 2026 года
A22: № п/п | B22: Шифр расценки и коды ресурсов | C22: Наименование работ и затрат | D22: Ед. изм. | E22: Кол-во единиц | F22: Цена на ед. изм., руб. | G22: Попра- вочные коэффи- циенты | H22: Коэффи- циенты зимних удорожа- ний | I22: Всего в ценах на январь 2000 года, руб. | J22: Коэффи- циенты (индек- сы) пере- счета, нормы НР и СП | K22: ВСЕГО затрат в текущем уровне цен, руб.
A23: 1 | B23: 2 | C23: 3 | D23: 4 | E23: 5 | F23: 6 | G23: 7 | H23: 8 | I23: 9 | J23: 10 | K23: 11
A24: Раздел: Устакновка радиаторов
A25: 1 | B25: 3.18-26-1 Поправка: Гл.6.Прил.2.2.п.2.2.6_06.00.01.07.001 Поправка: Гл.12.Прил.8.п.8. 3_12.00.01.11.001 Поправка: 3-18. О.П. п.1.8 | C25: Установка радиаторов алюминиевых и биметаллических с креплением к стене с числом секций до 4 шт. | D25: 100 шт. | E25: 0.02
C26: Объем: 0,02=2/100
C27: ЗП | F27: 716.97 | G27: 1,15*1,2*1,03 | H27: 1 | I27: 20.38 | J27: 57.05 | K27: 1162.68
C28: ЭМ | F28: 28.37 | G28: 1,25*1,2*1,03 | H28: 1 | I28: 0.88 | J28: 15.89 | K28: 13.98
C29: в т.ч. ЗПМ | F29: 3.21 | G29: 1,25*1,2*1,03 | H29: 1 | I29: 0.1 | J29: 57.05 | K29: 5.71
C30: МР | F30: 2962.2 | H30: 1 | I30: 59.24 | J30: 7.01 | K30: 415.27
C31: НР от ФОТ | D31: % | E31: 109 | I31: 22.32 | J31: 109 | K31: 1273.55
C32: СП от ФОТ | D32: % | E32: 61 | I32: 12.49 | J32: 61 | K32: 712.72
C33: ЗТР | D33: чел-ч | E33: 58.34 | G33: 1,15*1,2*1,03 | H33: 1 | I33: 1.66
C34: ВСЕГО работ по позиции: | H34: 115.31 | J34: 3578.2
C35: ВСЕГО по позиции: | H35: 115.31 | J35: 3578.2
A37: 2 | B37: 1.18-4-1270 | C37: Радиатор отопительный, биметаллический, секционный, ГОСТ 31311, размер секции 80х95х360 мм, межосевое расстояние 300 мм, 4 секции, теплоотдача 0,484 кВт | D37: шт. | E37: 2 | F37: 676.08 | H37: 1 | I37: 1352.16 | J37: 4.79 | K37: 6476.85
C38: ВСЕГО по позиции: | H38: 1352.16 | J38: 6476.85
A40: 3 | B40: 3.18-26-2 Поправка: Гл.6.Прил.2.2.п.2.2.6_06.00.01.07.001 Поправка: Гл.12.Прил.8.п.8. 3_12.00.01.11.001 Поправка: 3-18. О.П. п.1.8 | C40: Установка радиаторов алюминиевых и биметаллических с креплением к стене с числом секций свыше 4 до 10 шт. | D40: 100 шт. | E40: 0.23
C41: Объем: 0,23=(3+3+9+3+4+1)/100
C42: ЗП | F42: 873.14 | G42: 1,15*1,2*1,03 | H42: 1 | I42: 285.45 | J42: 57.05 | K42: 16284.92
C43: ЭМ | F43: 80.36 | G43: 1,25*1,2*1,03 | H43: 1 | I43: 28.56 | J43: 15.84 | K43: 452.39
C44: в т.ч. ЗПМ | F44: 8.91 | G44: 1,25*1,2*1,03 | H44: 1 | I44: 3.17 | J44: 57.05 | K44: 180.85
C45: МР | F45: 3737.88 | H45: 1 | I45: 859.71 | J45: 6.64 | K45: 5708.47
C46: НР от ФОТ | D46: % | E46: 109 | I46: 314.6 | J46: 109 | K46: 17947.69
C47: СП от ФОТ | D47: % | E47: 61 | I47: 176.06 | J47: 61 | K47: 10044.12
C48: ЗТР | D48: чел-ч | E48: 71.13 | G48: 1,15*1,2*1,03 | H48: 1 | I48: 23.25
C49: ВСЕГО работ по позиции: | H49: 1664.38 | J49: 50437.59
C50: ВСЕГО по позиции: | H50: 1664.38 | J50: 50437.59
A52: 4 | B52: 1.18-4-1271 | C52: Радиатор отопительный, биметаллический, секционный, ГОСТ 31311, размер секции 80х95х360 мм, межосевое расстояние 300 мм, 5 секций, теплоотдача 0,605 кВт | D52: шт. | E52: 3 | F52: 844.86 | H52: 1 | I52: 2534.58 | J52: 4.8 | K52: 12165.98
C53: ВСЕГО по позиции: | H53: 2534.58 | J53: 12165.98
A55: 5 | B55: 1.18-4-1272 | C55: Радиатор отопительный, биметаллический, секционный, ГОСТ 31311, размер секции 80х95х360 мм, межосевое расстояние 300 мм, 6 секций, теплоотдача 0,726 кВт | D55: шт. | E55: 3 | F55: 1013.97 | H55: 1 | I55: 3041.91 | J55: 4.79 | K55: 14570.75
C56: ВСЕГО по позиции: | H56: 3041.91 | J56: 14570.75
A58: 6 | B58: 1.18-4-1273 | C58: Радиатор отопительный, биметаллический, секционный, ГОСТ 31311, размер секции 80х95х360 мм, межосевое расстояние 300 мм, 7 секций, теплоотдача 0,847 кВт | D58: шт. | E58: 9 | F58: 1183.07 | H58: 1 | I58: 10647.63 | J58: 4.79 | K58: 51002.15
C59: ВСЕГО по позиции: | H59: 10647.63 | J59: 51002.15
A61: 7 | B61: 1.18-4-1274 | C61: Радиатор отопительный, биметаллический, секционный, ГОСТ 31311, размер секции 80х95х360 мм, межосевое расстояние 300 мм, 8 секций, теплоотдача 0,968 кВт | D61: шт. | E61: 3 | F61: 1351.85 | H61: 1 | I61: 4055.55 | J61: 4.8 | K61: 19466.64
C62: ВСЕГО по позиции: | H62: 4055.55 | J62: 19466.64
A64: 8 | B64: 1.18-4-1275 | C64: Радиатор отопительный, биметаллический, секционный, ГОСТ 31311, размер секции 80х95х360 мм, межосевое расстояние 300 мм, 9 секций, теплоотдача 1,089 кВт | D64: шт. | E64: 4 | F64: 1520.95 | H64: 1 | I64: 6083.8 | J64: 4.79 | K64: 29141.4
C65: ВСЕГО по позиции: | H65: 6083.8 | J65: 29141.4
A67: 9 | B67: 1.18-4-1276 | C67: Радиатор отопительный, биметаллический, секционный, ГОСТ 31311, размер секции 80х95х360 мм, межосевое расстояние 300 мм, 10 секций, теплоотдача 1,210 кВт | D67: шт. | E67: 1 | F67: 1690.06 | H67: 1 | I67: 1690.06 | J67: 4.79 | K67: 8095.39
C68: ВСЕГО по позиции: | H68: 1690.06 | J68: 8095.39
A70: 10 | B70: 3.18-26-3 Поправка: Гл.6.Прил.2.2.п.2.2.6_06.00.01.07.001 Поправка: Гл.12.Прил.8.п.8. 3_12.00.01.11.001 Поправка: 3-18. О.П. п.1.8 | C70: Установка радиаторов алюминиевых и биметаллических с креплением к стене с числом секций свыше 10 до 16 шт. | D70: 100 шт. | E70: 0.02
C71: Объем: 0,02=2/100
C72: ЗП | F72: 1059.44 | G72: 1,15*1,2*1,03 | H72: 1 | I72: 30.12 | J72: 57.05 | K72: 1718.35
C73: ЭМ | F73: 140.35 | G73: 1,25*1,2*1,03 | H73: 1 | I73: 4.34 | J73: 15.8 | K73: 68.57
C74: в т.ч. ЗПМ | F74: 15.41 | G74: 1,25*1,2*1,03 | H74: 1 | I74: 0.48 | J74: 57.05 | K74: 27.38
C75: МР | F75: 4513.71 | H75: 1 | I75: 90.27 | J75: 6.4 | K75: 577.73
C76: НР от ФОТ | D76: % | E76: 109 | I76: 33.35 | J76: 109 | K76: 1902.85
C77: СП от ФОТ | D77: % | E77: 61 | I77: 18.67 | J77: 61 | K77: 1064.9
C78: ЗТР | D78: чел-ч | E78: 86.51 | G78: 1,15*1,2*1,03 | H78: 1 | I78: 2.46
C79: ВСЕГО работ по позиции: | H79: 176.75 | J79: 5332.4
C80: ВСЕГО по позиции: | H80: 176.75 | J80: 5332.4
A82: 11 | B82: 1.18-4-1277 | C82: Радиатор отопительный, биметаллический, секционный, ГОСТ 31311, размер секции 80х95х360 мм, межосевое расстояние 300 мм, 11 секций, теплоотдача 1,331 кВт | D82: шт. | E82: 2 | F82: 1858.84 | H82: 1 | I82: 3717.68 | J82: 4.8 | K82: 17844.86
C83: ВСЕГО по позиции: | H83: 3717.68 | J83: 17844.86
A85: 12 | B85: 3.18-26-1 Поправка: Гл.6.Прил.2.2.п.2.2.6_06.00.01.07.001 Поправка: Гл.12.Прил.8.п.8. 3_12.00.01.11.001 Поправка: 3-18. О.П. п.1.8 | C85: Установка радиаторов алюминиевых и биметаллических с креплением к стене с числом секций до 4 шт. | D85: 100 шт. | E85: 0.01
C86: Объем: 0,01=1/100
C87: ЗП | F87: 716.97 | G87: 1,15*1,2*1,03 | H87: 1 | I87: 10.19 | J87: 57.05 | K87: 581.34
C88: ЭМ | F88: 28.37 | G88: 1,25*1,2*1,03 | H88: 1 | I88: 0.44 | J88: 15.89 | K88: 6.99
C89: в т.ч. ЗПМ | F89: 3.21 | G89: 1,25*1,2*1,03 | H89: 1 | I89: 0.05 | J89: 57.05 | K89: 2.85
C90: МР | F90: 2962.2 | H90: 1 | I90: 29.62 | J90: 7.01 | K90: 207.64
C91: НР от ФОТ | D91: % | E91: 109 | I91: 11.16 | J91: 109 | K91: 636.77
C92: СП от ФОТ | D92: % | E92: 61 | I92: 6.25 | J92: 61 | K92: 356.36
C93: ЗТР | D93: чел-ч | E93: 58.34 | G93: 1,15*1,2*1,03 | H93: 1 | I93: 0.83
C94: ВСЕГО работ по позиции: | H94: 57.66 | J94: 1789.1
C95: ВСЕГО по позиции: | H95: 57.66 | J95: 1789.1
A97: 13 | B97: 1.18-4-1296 | C97: Радиатор отопительный, биметаллический, секционный, ГОСТ 31311, с двумя секциями нижнего подключения соединенными глухим и проходным ниппелями, распределителем потока и клапанной вставкой, размер секции 80х95х560 мм, межосевое расстояние 500 мм, 4 секции, теплоотдача 0,740 кВт | D97: КОМПЛЕКТ | E97: 1 | F97: 1163.77 | H97: 1 | I97: 1163.77 | J97: 4.44 | K97: 5167.14
C98: ВСЕГО по позиции: | H98: 1163.77 | J98: 5167.14
A100: 14 | B100: 3.18-26-2 Поправка: Гл.6.Прил.2.2.п.2.2.6_06.00.01.07.001 Поправка: Гл.12.Прил.8.п.8. 3_12.00.01.11.001 Поправка: 3-18. О.П. п.1.8 | C100: Установка радиаторов алюминиевых и биметаллических с креплением к стене с числом секций свыше 4 до 10 шт. | D100: 100 шт. | E100: 0.06
C101: Объем: 0,06=(1+1+2+2)/100
C102: ЗП | F102: 873.14 | G102: 1,15*1,2*1,03 | H102: 1 | I102: 74.46 | J102: 57.05 | K102: 4247.94
C103: ЭМ | F103: 80.36 | G103: 1,25*1,2*1,03 | H103: 1 | I103: 7.45 | J103: 15.84 | K103: 118.01
C104: в т.ч. ЗПМ | F104: 8.91 | G104: 1,25*1,2*1,03 | H104: 1 | I104: 0.83 | J104: 57.05 | K104: 47.35
C105: МР | F105: 3737.88 | H105: 1 | I105: 224.27 | J105: 6.64 | K105: 1489.15
C106: НР от ФОТ | D106: % | E106: 109 | I106: 82.07 | J106: 109 | K106: 4681.87
C107: СП от ФОТ | D107: % | E107: 61 | I107: 45.93 | J107: 61 | K107: 2620.13
C108: ЗТР | D108: чел-ч | E108: 71.13 | G108: 1,15*1,2*1,03 | H108: 1 | I108: 6.07
C109: ВСЕГО работ по позиции: | H109: 434.18 | J109: 13157.1
C110: ВСЕГО по позиции: | H110: 434.18 | J110: 13157.1
A112: 15 | B112: 1.18-4-1297 | C112: Радиатор отопительный, биметаллический, секционный, ГОСТ 31311, с двумя секциями нижнего подключения соединенными глухим и проходным ниппелями, распределителем потока и клапанной вставкой, размер секции 80х95х560 мм, межосевое расстояние 500 мм, 5 секций, теплоотдача 0,925 кВт | D112: КОМПЛЕКТ | E112: 1 | F112: 1344.39 | H112: 1 | I112: 1344.39 | J112: 4.54 | K112: 6103.53
C113: ВСЕГО по позиции: | H113: 1344.39 | J113: 6103.53
A115: 16 | B115: 1.18-4-1299 | C115: Радиатор отопительный, биметаллический, секционный, ГОСТ 31311, с двумя секциями нижнего подключения соединенными глухим и проходным ниппелями, распределителем потока и клапанной вставкой, размер секции 80х95х560 мм, межосевое расстояние 500 мм, 7 секций, теплоотдача 1,295 кВт | D115: КОМПЛЕКТ | E115: 1 | F115: 1708.79 | H115: 1 | I115: 1708.79 | J115: 4.65 | K115: 7945.87
C116: ВСЕГО по позиции: | H116: 1708.79 | J116: 7945.87
A118: 17 | B118: 1.18-4-1300 | C118: Радиатор отопительный, биметаллический, секционный, ГОСТ 31311, с двумя секциями нижнего подключения соединенными глухим и проходным ниппелями, распределителем потока и клапанной вставкой, размер секции 80х95х560 мм, межосевое расстояние 500 мм, 8 секций, теплоотдача 1,480 кВт | D118: КОМПЛЕКТ | E118: 2 | F118: 1890.36 | H118: 1 | I118: 3780.72 | J118: 4.7 | K118: 17769.38
C119: ВСЕГО по позиции: | H119: 3780.72 | J119: 17769.38
A121: 18 | B121: 1.18-4-1301 | C121: Радиатор отопительный, биметаллический, секционный, ГОСТ 31311, с двумя секциями нижнего подключения соединенными глухим и проходным ниппелями, распределителем потока и клапанной вставкой, размер секции 80х95х560 мм, межосевое расстояние 500 мм, 9 секций, теплоотдача 1,665 кВт | D121: КОМПЛЕКТ | E121: 2 | F121: 2071.93 | H121: 1 | I121: 4143.86 | J121: 4.73 | K121: 19600.46
C122: ВСЕГО по позиции: | H122: 4143.86 | J122: 19600.46
A124: 19 | B124: 3.18-26-3 Поправка: Гл.6.Прил.2.2.п.2.2.6_06.00.01.07.001 Поправка: Гл.12.Прил.8.п.8. 3_12.00.01.11.001 Поправка: 3-18. О.П. п.1.8 | C124: Установка радиаторов алюминиевых и биметаллических с креплением к стене с числом секций свыше 10 до 16 шт. | D124: 100 шт. | E124: 0.02
...

Sheet ЛС 02-01-07
J2: Форма № 4б
A3: =ССРСС!A11 -> Выполнение работ по капитальному ремонту здания в Басманном районе ЦАО города Москвы
A4: (наименование стройки и/или объекта)
A6: ЛОКАЛЬНАЯ СМЕТА № 02-01-07
A8: Кондиционирование
A9: (наименование работ и затрат)
I12: В базисном уровне цен | J12: В текущем уровне цен
E13: Сметная стоимость | I13: 187.84 | J13: 1809.85 | K13: тыс.руб.
E14: Строительные работы | I14: 24.86 | J14: 575.3 | K14: тыс.руб.
E15: Работы по монтажу оборудования | I15: 0.11 | J15: 6.54 | K15: тыс.руб.
E16: Оборудование | I16: 162.87 | J16: 1228.01 | K16: тыс.руб.
E17: Средства на оплату труда | I17: 3.16 | J17: 180.19 | K17: тыс.руб.
E18: Затраты труда | I18: 242.54 | K18: чел.-ч.
A20: Составлен(а) по ТСН-2001 с учетом Дополнения №: 81
A21: № и период сборника коэффициентов (индексов) пересчета: Коэффициенты к ТСН-2001 МГЭ Дополнение 81, ремонт №220 II квартал 2026 года и Коэффициенты к ТСН-2001.13-2 Дополнение 47 №65 II квартал 2026 года
A22: № п/п | B22: Шифр расценки и коды ресурсов | C22: Наименование работ и затрат | D22: Ед. изм. | E22: Кол-во единиц | F22: Цена на ед. изм., руб. | G22: Попра- вочные коэффи- циенты | H22: Коэффи- циенты зимних удорожа- ний | I22: Всего в ценах на январь 2000 года, руб. | J22: Коэффи- циенты (индек- сы) пере- счета, нормы НР и СП | K22: ВСЕГО затрат в текущем уровне цен, руб.
A23: 1 | B23: 2 | C23: 3 | D23: 4 | E23: 5 | F23: 6 | G23: 7 | H23: 8 | I23: 9 | J23: 10 | K23: 11
A24: Раздел: Кондиционирование
A25: 1 | B25: 3.20-59-1 Поправка: Гл.12.Прил.8.п.8. 3_12.00.01.11.001 Поправка: Гл.6.Прил.2.2.п.2.2.6_06.00.01.07.001 | C25: Установка наружного блока сплит-системы мощностью до 6,5 кВт на кронштейны | D25: 1 блок | E25: 25
C26: Объем: 25=2+2+2+1+1+1+1+1+1+1+1+1+1+1+1+1+1+1+1+1+1+1
C27: ЗП | F27: 11.06 | G27: 1,2*1,15 | H27: 1 | I27: 381.57 | J27: 57.05 | K27: 21768.57
C28: ЭМ | F28: 0.65 | G28: 1,2*1,25 | H28: 1 | I28: 24.38 | J28: 14.32 | K28: 349.12
C29: в т.ч. ЗПМ | F29: 0.06 | G29: 1,2*1,25 | H29: 1 | I29: 2.25 | J29: 57.05 | K29: 128.36
C30: МР | F30: 98.58 | H30: 1 | I30: 2464.5 | J30: 5.14 | K30: 12667.53
C31: НР от ФОТ | D31: % | E31: 109 | I31: 418.36 | J31: 109 | K31: 23867.65
C32: СП от ФОТ | D32: % | E32: 61 | I32: 234.13 | J32: 61 | K32: 13357.13
C33: ЗТР | D33: чел-ч | E33: 0.82 | G33: 1,2*1,15 | H33: 1 | I33: 28.29
C34: ВСЕГО работ по позиции: | H34: 3522.94 | J34: 72010
C35: ВСЕГО по позиции: | H35: 3522.94 | J35: 72010
A37: 2 | B37: 3.20-58-1 Поправка: Гл.12.Прил.8.п.8. 3_12.00.01.11.001 Поправка: Гл.6.Прил.2.2.п.2.2.6_06.00.01.07.001 | C37: Установка внутреннего блока сплит-системы настенного типа мощностью до 6,5 кВт | D37: 1 блок | E37: 25
C38: ЗП | F38: 79.45 | G38: 1,2*1,15 | H38: 1 | I38: 2741.03 | J38: 57.05 | K38: 156375.76
C39: ЭМ | F39: 0.89 | G39: 1,2*1,25 | H39: 1 | I39: 33.38 | J39: 12.98 | K39: 433.27
C40: в т.ч. ЗПМ | F40: 0.05 | G40: 1,2*1,25 | H40: 1 | I40: 1.88 | J40: 57.05 | K40: 107.25
C41: МР | F41: 289.06 | H41: 1 | I41: 7226.5 | J41: 8.03 | K41: 58028.8
C42: НР от ФОТ | D42: % | E42: 109 | I42: 2989.77 | J42: 109 | K42: 170566.48
C43: СП от ФОТ | D43: % | E43: 61 | I43: 1673.18 | J43: 61 | K43: 95454.64
C44: ЗТР | D44: чел-ч | E44: 6.14 | G44: 1,2*1,15 | H44: 1 | I44: 211.83
C45: ВСЕГО работ по позиции: | H45: 14663.86 | J45: 480858.95
C46: ВСЕГО по позиции: | H46: 14663.86 | J46: 480858.95
A48: 3 | B48: 1.12-5-61 Поправка: Гл.12.Прил.8.п.8. 3_12.00.01.11.001 Поправка: Гл.6.Прил.2.2.п.2.2.6_06.00.01.07.001 | C48: Трубка дренажная из ПВХ, диаметр 16 мм | D48: м | E48: -76.875 | F48: 10.78 | H48: 1 | I48: -828.71 | J48: 1.56 | K48: -1292.79
C49: Объем: -76,875=25*-3,075
C50: ВСЕГО по позиции: | H50: -828.71 | J50: -1292.79
A52: 4 | B52: 1.12-7-186 Поправка: Гл.12.Прил.8.п.8. 3_12.00.01.11.001 Поправка: Гл.6.Прил.2.2.п.2.2.6_06.00.01.07.001 | C52: Трубы медные для отопления и водоснабжения, наружный диаметр 6,35 мм, толщина стенки 0,76 мм | D52: м | E52: -76.875 | F52: 4.37 | H52: 1 | I52: -335.94 | J52: 35.03 | K52: -11767.98
C53: Объем: -76,875=25*-3,075
C54: ВСЕГО по позиции: | H54: -335.94 | J54: -11767.98
A56: 5 | B56: 1.12-7-188 Поправка: Гл.12.Прил.8.п.8. 3_12.00.01.11.001 Поправка: Гл.6.Прил.2.2.п.2.2.6_06.00.01.07.001 | C56: Трубы медные для отопления и водоснабжения, наружный диаметр 12,7 мм, толщина стенки 0,81 мм | D56: м | E56: -76.875 | F56: 10.28 | H56: 1 | I56: -790.28 | J56: 31.66 | K56: -25020.26
C57: Объем: -76,875=25*-3,075
C58: ВСЕГО по позиции: | H58: -790.28 | J58: -25020.26
A60: 6 | B60: Прайс-лист | C60: ОБОРУДОВАНИЕ: Сплит-система, универсальный внутренний блок, цвет белый, inverter, R32, 3Ф. В комплекте ИК пульт, мощность на охлаждение 4,8 кВт, обогрев 4,8 кВт. Площадь помещения до 50 м2 8 657,25 = [76 400 / 1,22 / 7,54] + 3% Трансп + 1,2% Заг.скл | D60: ШТ | E60: 6 | F60: 8657.25 | H60: 1 | I60: 51943.5 | J60: 7.54 | K60: 391653.99
C61: ВСЕГО по позиции: | H61: 51943.5 | J61: 391653.99
A63: 7 | B63: Прайс-лист | C63: ОБОРУДОВАНИЕ: Сплит-система, кассетный внутренний блок, цвет белый, inverter, R32. В комплекте ИК пульт,мощность на охлаждение 5,0 кВт, обогрев 5,3 кВт. Площадь помещения до 50-55 м2 4 793,22 = [42 300 / 1,22 / 7,54] + 3% Трансп + 1,2% Заг.скл | D63: ШТ | E63: 13 | F63: 4793.22 | H63: 1 | I63: 62311.86 | J63: 7.54 | K63: 469831.42
C64: ВСЕГО по позиции: | H64: 62311.86 | J64: 469831.42
A66: 8 | B66: Прайс-лист | C66: ОБОРУДОВАНИЕ: Сплит-система, кассетный внутренний блок, цвет белый, inverter, R32. В комплекте ИК пульт,мощность на охлаждение 3,4 кВт, обогрев 3,4 кВт. Площадь помещения до 35-40 м2 5 971,69 = [52 700 / 1,22 / 7,54] + 3% Трансп + 1,2% Заг.скл | D66: ШТ | E66: 1 | F66: 5971.69 | H66: 1 | I66: 5971.69 | J66: 7.54 | K66: 45026.54
C67: ВСЕГО по позиции: | H67: 5971.69 | J67: 45026.54
A69: 9 | B69: Прайс-лист | C69: ОБОРУДОВАНИЕ: Сплит-система, кассетный внутренний блок, цвет белый, inverter, R32. В комплекте ИК пульт,мощность на охлаждение 2,7 кВт, обогрев 2,9 кВт. Площадь помещения до 25 м2 5 189,82 = [45 800 / 1,22 / 7,54] + 3% Трансп + 1,2% Заг.скл | D69: ШТ | E69: 5 | F69: 5189.82 | H69: 1 | I69: 25949.1 | J69: 7.54 | K69: 195656.21
C70: ВСЕГО по позиции: | H70: 25949.1 | J70: 195656.21
A72: 10 | B72: 4.11-3-1 Поправка: Гл.12.Прил.8.п.8. 3_12.00.01.11.001 | C72: Установка прибора массой до 5 кг на металлоконструкциях или щитах | D72: 1 ШТ. | E72: 6
C73: Объем: 6=1+5
C74: ЗП | F74: 6.75 | G74: 1,2 | H74: 1 | I74: 48.6 | J74: 57.05 | K74: 2772.63
C75: НР от ФОТ | D75: % | E75: 90 | I75: 43.74 | J75: 90 | K75: 2495.37
C76: СП от ФОТ | D76: % | E76: 46 | I76: 22.36 | J76: 46 | K76: 1275.41
C77: ЗТР | D77: чел-ч | E77: 0.52 | G77: 1,2 | H77: 1 | I77: 3.74
C78: ВСЕГО работ по позиции: | H78: 114.7 | J78: 6543.41
C79: ВСЕГО по позиции: | H79: 114.7 | J79: 6543.41
A81: 11 | B81: Прайс-лист | C81: ОБОРУДОВАНИЕ: Устройства центрального управления кондиционерами 8 532,61 = [75 300 / 1,22 / 7,54] + 3% Трансп + 1,2% Заг.скл | D81: ШТ | E81: 1 | F81: 8532.61 | H81: 1 | I81: 8532.61 | J81: 7.54 | K81: 64335.88
C82: ВСЕГО по позиции: | H82: 8532.61 | J82: 64335.88
A84: 12 | B84: Прайс-лист | C84: ОБОРУДОВАНИЕ: Устройства центрального управления интерфейсный шлюз(конвертер) 1 631,51 = [14 398 / 1,22 / 7,54] + 3% Трансп + 1,2% Заг.скл | D84: ШТ | E84: 5 | F84: 1631.51 | H84: 1 | I84: 8157.55 | J84: 7.54 | K84: 61507.93
C85: ВСЕГО по позиции: | H85: 8157.55 | J85: 61507.93
A87: 13 | B87: 3.20-58-3 Поправка: Гл.12.Прил.8.п.8. 3_12.00.01.11.001 | C87: Добавлять/уменьшать на каждый 1 м трассы систем до 6,5 кВт | D87: 1 м трассы | E87: -2.5
C88: Объем: -2,5=(50+95-25*6)/2
C89: ЗП | F89: 5.59 | G89: 1,2 | H89: 1 | I89: -16.77 | J89: 57.05 | K89: -956.73
C90: ЭМ | F90: 0.07 | G90: 1,2 | H90: 1 | I90: -0.21 | J90: 18.71 | K90: -3.93
C91: в т.ч. ЗПМ | F91: 0.01 | G91: 1,2 | H91: 1 | I91: -0.03 | J91: 57.05 | K91: -1.71
C92: МР | F92: 30.57 | H92: 1 | I92: -76.43 | J92: 17.1 | K92: -1306.95
A93: 13,1 | B93: 1.1-1-3984 | C93: Хладагент типа R404А, R22 | D93: кг | E93: -0.0625 | F93: 40.29 | H93: 1 | I93: -2.52 | J93: 22.05 | K93: -55.57
A94: 13,2 | B94: 1.23-8-564 | C94: Кабель силовой с медными жилами, с изоляцией и оболочкой из ПВХ композиций пониженной пожароопасности, с пониженным дымо- и газовыделением, типа ВВГнг(А)-LS, напряжение 1000 В, число жил и сечение 2х1,5 мм2 | D94: км | E94: -0.0025 | F94: 4785.46 | H94: 1 | I94: -11.96 | J94: 8.51 | K94: -101.78
C95: НР от ФОТ | D95: % | E95: 109 | I95: -18.31 | J95: 109 | K95: -1044.7
C96: СП от ФОТ | D96: % | E96: 61 | I96: -10.25 | J96: 61 | K96: -584.65
C97: ЗТР | D97: чел-ч | E97: 0.44 | G97: 1,2 | H97: 1 | I97: -1.32
C98: ВСЕГО работ по позиции: | H98: -136.45 | J98: -4054.31
C99: ВСЕГО по позиции: | H99: -136.45 | J99: -4054.31
A101: 14 | B101: 1.12-7-186 | C101: Трубы медные для отопления и водоснабжения, наружный диаметр 6,35 мм, толщина стенки 0,76 мм | D101: м | E101: 52 | F101: 4.37 | H101: 1 | I101: 227.24 | J101: 35.03 | K101: 7960.22
C102: Объем: 52=50*1,04
C103: ВСЕГО по позиции: | H103: 227.24 | J103: 7960.22
A105: 15 | B105: 1.12-7-187 | C105: Трубы медные для отопления и водоснабжения, наружный диаметр 9,52 мм, толщина стенки 0,81 мм | D105: м | E105: 98.8 | F105: 7.73 | H105: 1 | I105: 763.72 | J105: 30.53 | K105: 23316.37
C106: Объем: 98,8=95*1,04
C107: ВСЕГО по позиции: | H107: 763.72 | J107: 23316.37
A109: 16 | B109: 1.1-1-3125 | C109: Трубки теплоизоляционные из вспененного каучука, для систем трубопроводов, диапазон температур применения от -200 до +110°C, коэффициент теплопроводности при температуре 0°C не более 0,032 Вт/(м х К), внутренний диаметр 22 мм, толщина 13 мм | D109: м | E109: 189 | F109: 23.19 | H109: 1 | I109: 4382.91 | J109: 4.04 | K109: 17706.96
C110: ВСЕГО по позиции: | H110: 4382.91 | J110: 17706.96
A112: 17 | B112: 1.12-5-150 | C112: Трубы напорные из полипропилена PP-R тип 3 (PRC-R), ГОСТ 32415-2013, номинальное давление PN10, наружный диаметр 20 мм | D112: м | E112: 102.5 | F112: 10.84 | H112: 1 | I112: 1111.1 | J112: 2.41 | K112: 2677.75
C113: ВСЕГО по позиции: | H113: 1111.1 | J113: 2677.75
A115: 18 | B115: 1.12-5-151 | C115: Трубы напорные из полипропилена PP-R тип 3 (PRC-R), ГОСТ 32415-2013, номинальное давление PN10, наружный диаметр 25 мм | D115: м | E115: 25.625 | F115: 17 | H115: 1 | I115: 435.63 | J115: 2.35 | K115: 1023.73
C116: ВСЕГО по позиции: | H116: 435.63 | J116: 1023.73
A118: 19 | B118: 1.12-5-152 | C118: Трубы напорные из полипропилена PP-R тип 3 (PRC-R), ГОСТ 32415-2013, номинальное давление PN10, наружный диаметр 32 мм | D118: м | E118: 10.25 | F118: 27.68 | H118: 1 | I118: 283.72 | J118: 2.52 | K118: 714.97
C119: ВСЕГО по позиции: | H119: 283.72 | J119: 714.97
A121: 20 | B121: 1.1-1-1273 | C121: Трубки теплоизоляционные из вспененного синтетического каучука, для систем трубопроводов отопления, водоснабжения и кондиционирования, диапазон температур применения от -50 до +110°С, теплопроводность при температуре 0°С не более 0,036 Вт/(м х К), внутренний диаметр 22 мм, толщина 13 мм | D121: м | E121: 105 | F121: 10.38 | H121: 1 | I121: 1089.9 | J121: 7.12 | K121: 7760.09
C122: Объем: 105=100*1,05
C123: ВСЕГО по позиции: | H123: 1089.9 | J123: 7760.09
A125: 21 | B125: 1.1-1-1274 | C125: Трубки теплоизоляционные из вспененного синтетического каучука, для систем трубопроводов отопления, водоснабжения и кондиционирования, диапазон температур применения от -50 до +110°С, теплопроводность при температуре 0°С не более 0,036 Вт/(м х К), внутренний диаметр 28 мм, толщина 13 мм | D125: м | E125: 26.25 | F125: 12.04 | H125: 1 | I125: 316.05 | J125: 7.25 | K125: 2291.36
C126: Объем: 26,25=25*1,05
...

Sheet ЛС 02-01-08
J2: Форма № 4б
A3: =ССРСС!A11 -> Выполнение работ по капитальному ремонту здания в Басманном районе ЦАО города Москвы
A4: (наименование стройки и/или объекта)
A6: ЛОКАЛЬНАЯ СМЕТА № 02-01-08
A8: Автоматическая пожарная сигнализация
A9: (наименование работ и затрат)
I12: В базисном уровне цен | J12: В текущем уровне цен
E13: Сметная стоимость | I13: 83.58 | J13: 1495.13 | K13: тыс.руб.
E14: Строительные работы | I14: 4.95 | J14: 50.39 | K14: тыс.руб.
E15: Работы по монтажу оборудования | I15: 25.23 | J15: 1044.06 | K15: тыс.руб.
E16: Оборудование | I16: 53.4 | J16: 400.68 | K16: тыс.руб.
E17: Средства на оплату труда | I17: 7.49 | J17: 427.18 | K17: тыс.руб.
E18: Затраты труда | I18: 603.27 | K18: чел.-ч.
A20: Составлен(а) по ТСН-2001 с учетом Дополнения №: 81
A21: № и период сборника коэффициентов (индексов) пересчета: Коэффициенты к ТСН-2001 МГЭ Дополнение 81, ремонт №220 II квартал 2026 года и Коэффициенты к ТСН-2001.13-2 Дополнение 47 №65 II квартал 2026 года
A22: № п/п | B22: Шифр расценки и коды ресурсов | C22: Наименование работ и затрат | D22: Ед. изм. | E22: Кол-во единиц | F22: Цена на ед. изм., руб. | G22: Попра- вочные коэффи- циенты | H22: Коэффи- циенты зимних удорожа- ний | I22: Всего в ценах на январь 2000 года, руб. | J22: Коэффи- циенты (индек- сы) пере- счета, нормы НР и СП | K22: ВСЕГО затрат в текущем уровне цен, руб.
A23: 1 | B23: 2 | C23: 3 | D23: 4 | E23: 5 | F23: 6 | G23: 7 | H23: 8 | I23: 9 | J23: 10 | K23: 11
A24: Раздел: Монтаж оборудования
A25: 1 | B25: 4.10-80-1 Поправка: Гл.12.Прил.8.п.8. 3_12.00.01.11.001 | C25: Аппараты приемные, приборы ПС приемно-контрольные, пусковые, концентратор, блок базовый на 10 лучей | D25: 1 ШТ. | E25: 2
C26: ЗП | F26: 95.04 | G26: 1,2 | H26: 1 | I26: 228.1 | J26: 57.05 | K26: 13013.11
C27: ЭМ | F27: 0.06 | G27: 1,2 | H27: 1 | I27: 0.14 | J27: 18.83 | K27: 2.64
C28: в т.ч. ЗПМ | F28: 0.01 | G28: 1,2 | H28: 1 | I28: 0.02 | J28: 57.05 | K28: 1.14
C29: МР | F29: 12.53 | H29: 1 | I29: 25.06 | J29: 10.18 | K29: 255.11
C30: НР от ФОТ | D30: % | E30: 90 | I30: 205.31 | J30: 90 | K30: 11712.83
C31: СП от ФОТ | D31: % | E31: 46 | I31: 104.94 | J31: 46 | K31: 5986.56
C32: ЗТР | D32: чел-ч | E32: 7.2 | G32: 1,2 | H32: 1 | I32: 17.28
C33: ВСЕГО работ по позиции: | H33: 563.55 | J33: 30970.25
C34: ВСЕГО по позиции: | H34: 563.55 | J34: 30970.25
A36: 2 | B36: Прайс-лист | C36: ОБОРУДОВАНИЕ: Прибор приемно-контрольный и управления охранно-пожарный адресный 4 870,40 = [42 981,21 / 1,22 / 7,54] + 3% Трансп + 1,2% Заг.скл | D36: ШТ | E36: 2 | F36: 4870.4 | H36: 1 | I36: 9740.8 | J36: 7.54 | K36: 73445.63
C37: ВСЕГО по позиции: | H37: 9740.8 | J37: 73445.63
A39: 3 | B39: 4.10-170-2 Поправка: Гл.12.Прил.8.п.8. 3_12.00.01.11.001 | C39: Монтаж блока информационно-управляющего (БИУ) в диспетчерской | D39: 1 ШТ. | E39: 1
C40: ЗП | F40: 33.47 | G40: 1,2 | H40: 1 | I40: 40.16 | J40: 57.05 | K40: 2291.13
C41: МР | F41: 2.34 | H41: 1 | I41: 2.34 | J41: 9.91 | K41: 23.19
C42: НР от ФОТ | D42: % | E42: 90 | I42: 36.14 | J42: 90 | K42: 2062.02
C43: СП от ФОТ | D43: % | E43: 46 | I43: 18.47 | J43: 46 | K43: 1053.92
C44: ЗТР | D44: чел-ч | E44: 2.65 | G44: 1,2 | H44: 1 | I44: 3.18
C45: ВСЕГО работ по позиции: | H45: 97.11 | J45: 5430.26
C46: ВСЕГО по позиции: | H46: 97.11 | J46: 5430.26
A48: 4 | B48: Прайс-лист | C48: ОБОРУДОВАНИЕ: Блок индикации и управления 2 394,57 = [21 132 / 1,22 / 7,54] + 3% Трансп + 1,2% Заг.скл | D48: ШТ | E48: 1 | F48: 2394.57 | H48: 1 | I48: 2394.57 | J48: 7.54 | K48: 18055.06
C49: ВСЕГО по позиции: | H49: 2394.57 | J49: 18055.06
A51: 5 | B51: 4.10-80-13 Поправка: Гл.12.Прил.8.п.8. 3_12.00.01.11.001 | C51: Аппараты приемные, устройства промежуточные на 1 луч | D51: 1 ШТ. | E51: 1
C52: ЗП | F52: 16.07 | G52: 1,2 | H52: 1 | I52: 19.28 | J52: 57.05 | K52: 1099.92
C53: ЭМ | F53: 0.05 | G53: 1,2 | H53: 1 | I53: 0.06 | J53: 20.4 | K53: 1.22
C54: в т.ч. ЗПМ | F54: 0.01 | G54: 1,2 | H54: 1 | I54: 0.01 | J54: 57.05 | K54: 0.57
C55: МР | F55: 1.96 | H55: 1 | I55: 1.96 | J55: 10.18 | K55: 19.95
C56: НР от ФОТ | D56: % | E56: 90 | I56: 17.36 | J56: 90 | K56: 990.44
C57: СП от ФОТ | D57: % | E57: 46 | I57: 8.87 | J57: 46 | K57: 506.23
C58: ЗТР | D58: чел-ч | E58: 1.2 | G58: 1,2 | H58: 1 | I58: 1.44
C59: ВСЕГО работ по позиции: | H59: 47.53 | J59: 2617.76
C60: ВСЕГО по позиции: | H60: 47.53 | J60: 2617.76
A62: 6 | B62: Прайс-лист | C62: ОБОРУДОВАНИЕ: Модуль связи 2 070,10 = [18 268,58 / 1,22 / 7,54] + 3% Трансп + 1,2% Заг.скл | D62: ШТ | E62: 1 | F62: 2070.1 | H62: 1 | I62: 2070.1 | J62: 7.54 | K62: 15608.55
C63: ВСЕГО по позиции: | H63: 2070.1 | J63: 15608.55
A65: 7 | B65: 4.10-81-2 Поправка: Гл.12.Прил.8.п.8. 3_12.00.01.11.001 | C65: Извещатели ПС автоматические, дымовой, фотоэлектрический, радиоизотопный, световой в нормальном исполнении | D65: 1 ШТ. | E65: 85
C66: ЗП | F66: 21.2 | G66: 1,2 | H66: 1 | I66: 2162.4 | J66: 57.05 | K66: 123364.92
C67: ЭМ | F67: 0.06 | G67: 1,2 | H67: 1 | I67: 6.12 | J67: 18.83 | K67: 115.24
C68: в т.ч. ЗПМ | F68: 0.01 | G68: 1,2 | H68: 1 | I68: 1.02 | J68: 57.05 | K68: 58.19
C69: МР | F69: 1.26 | H69: 1 | I69: 107.1 | J69: 10.18 | K69: 1090.28
C70: НР от ФОТ | D70: % | E70: 90 | I70: 1947.08 | J70: 90 | K70: 111080.8
C71: СП от ФОТ | D71: % | E71: 46 | I71: 995.17 | J71: 46 | K71: 56774.63
C72: ЗТР | D72: чел-ч | E72: 1.68 | G72: 1,2 | H72: 1 | I72: 171.36
C73: ВСЕГО работ по позиции: | H73: 5217.87 | J73: 292425.87
C74: ВСЕГО по позиции: | H74: 5217.87 | J74: 292425.87
A76: 8 | B76: Прайс-лист | C76: ОБОРУДОВАНИЕ: Извещатель пожарный дымовой оптико-электронный адресно-аналоговый 136,99 = [1 209 / 1,22 / 7,54] + 3% Трансп + 1,2% Заг.скл | D76: ШТ | E76: 85 | F76: 136.99 | H76: 1 | I76: 11644.15 | J76: 7.54 | K76: 87796.89
C77: ВСЕГО по позиции: | H77: 11644.15 | J77: 87796.89
A79: 9 | B79: 4.10-81-6 Поправка: Гл.12.Прил.8.п.8. 3_12.00.01.11.001 | C79: Конструкция для установки извещателя | D79: 1 ШТ. | E79: 85
C80: Объем: 85=22+63
C81: ЗП | F81: 4.42 | G81: 1,2 | H81: 1 | I81: 450.84 | J81: 57.05 | K81: 25720.42
C82: ЭМ | F82: 4.56 | G82: 1,2 | H82: 1 | I82: 465.12 | J82: 14.1 | K82: 6558.19
C83: в т.ч. ЗПМ | F83: 0.28 | G83: 1,2 | H83: 1 | I83: 28.56 | J83: 57.05 | K83: 1629.35
C84: МР | F84: 1.05 | H84: 1 | I84: 89.25 | J84: 10.18 | K84: 908.57
C85: НР от ФОТ | D85: % | E85: 90 | I85: 431.46 | J85: 90 | K85: 24614.79
C86: СП от ФОТ | D86: % | E86: 46 | I86: 220.52 | J86: 46 | K86: 12580.89
C87: ЗТР | D87: чел-ч | E87: 0.35 | G87: 1,2 | H87: 1 | I87: 35.7
C88: ВСЕГО работ по позиции: | H88: 1657.19 | J88: 70382.86
C89: ВСЕГО по позиции: | H89: 1657.19 | J89: 70382.86
A91: 10 | B91: Прайс-лист | C91: Базовое основание диаметр 143 мм, высота 60 мм. 42,95 = [523 / 1,22 / 10,18] + 2% Заг.скл | D91: ШТ | E91: 22 | F91: 42.95 | H91: 1 | I91: 944.9 | J91: 10.18 | K91: 9619.08
C92: ВСЕГО по позиции: | H92: 944.9 | J92: 9619.08
A94: 11 | B94: Прайс-лист | C94: Базовое основание,ширина 93 мм ,глубина 93 мм ,высота 25 мм 17,09 = [208 / 1,22 / 10,18] + 2% Заг.скл | D94: ШТ | E94: 63 | F94: 17.09 | H94: 1 | I94: 1076.67 | J94: 10.18 | K94: 10960.5
C95: ВСЕГО по позиции: | H95: 1076.67 | J95: 10960.5
A97: 12 | B97: 4.10-76-10 Поправка: Гл.12.Прил.8.п.8. 3_12.00.01.11.001 | C97: Монтаж ключа или кнопки на панели | D97: 1 ШТ. | E97: 4
C98: ЗП | F98: 11.89 | G98: 1,2 | H98: 1 | I98: 57.07 | J98: 57.05 | K98: 3255.84
C99: МР | F99: 1.67 | H99: 1 | I99: 6.68 | J99: 17.41 | K99: 116.3
C100: НР от ФОТ | D100: % | E100: 95 | I100: 54.22 | J100: 95 | K100: 3093.05
C101: СП от ФОТ | D101: % | E101: 53 | I101: 30.25 | J101: 53 | K101: 1725.6
C102: ЗТР | D102: чел-ч | E102: 1 | G102: 1,2 | H102: 1 | I102: 4.8
C103: ВСЕГО работ по позиции: | H103: 148.22 | J103: 8190.79
C104: ВСЕГО по позиции: | H104: 148.22 | J104: 8190.79
A106: 13 | B106: Прайс-лист | C106: ОБОРУДОВАНИЕ: Извещатель пожарный ручной адресный с изолятором короткого замыкания 136,44 = [1 204 / 1,22 / 7,54] + 3% Трансп + 1,2% Заг.скл | D106: ШТ | E106: 4 | F106: 136.44 | H106: 1 | I106: 545.76 | J106: 7.54 | K106: 4115.03
C107: ВСЕГО по позиции: | H107: 545.76 | J107: 4115.03
A109: 14 | B109: 4.10-80-13 Поправка: Гл.12.Прил.8.п.8. 3_12.00.01.11.001 | C109: Аппараты приемные, устройства промежуточные на 1 луч | D109: 1 ШТ. | E109: 28
C110: ЗП | F110: 16.07 | G110: 1,2 | H110: 1 | I110: 539.95 | J110: 57.05 | K110: 30804.15
C111: ЭМ | F111: 0.05 | G111: 1,2 | H111: 1 | I111: 1.68 | J111: 20.4 | K111: 34.27
C112: в т.ч. ЗПМ | F112: 0.01 | G112: 1,2 | H112: 1 | I112: 0.34 | J112: 57.05 | K112: 19.4
C113: МР | F113: 1.96 | H113: 1 | I113: 54.88 | J113: 10.18 | K113: 558.68
C114: НР от ФОТ | D114: % | E114: 90 | I114: 486.26 | J114: 90 | K114: 27741.2
C115: СП от ФОТ | D115: % | E115: 46 | I115: 248.53 | J115: 46 | K115: 14178.83
C116: ЗТР | D116: чел-ч | E116: 1.2 | G116: 1,2 | H116: 1 | I116: 40.32
C117: ВСЕГО работ по позиции: | H117: 1331.3 | J117: 73317.13
C118: ВСЕГО по позиции: | H118: 1331.3 | J118: 73317.13
A120: 15 | B120: Прайс-лист | C120: ОБОРУДОВАНИЕ: Изолятор шлейфа 77,21 = [681,36 / 1,22 / 7,54] + 3% Трансп + 1,2% Заг.скл | D120: ШТ | E120: 28 | F120: 77.21 | H120: 1 | I120: 2161.88 | J120: 7.54 | K120: 16300.58
...

Sheet ЛС 02-01-09
J2: Форма № 4б
A3: =ССРСС!A11 -> Выполнение работ по капитальному ремонту здания в Басманном районе ЦАО города Москвы
A4: (наименование стройки и/или объекта)
A6: ЛОКАЛЬНАЯ СМЕТА № 02-01-09
A8: Система оповещения и управления эвакуацией
A9: (наименование работ и затрат)
I12: В базисном уровне цен | J12: В текущем уровне цен
E13: Сметная стоимость | I13: 275.46 | J13: 1473.81 | K13: тыс.руб.
E14: Строительные работы | I14: 1.03 | J14: 9.71 | K14: тыс.руб.
E15: Работы по монтажу оборудования | I15: 244.95 | J15: 1243.28 | K15: тыс.руб.
E16: Оборудование | I16: 29.48 | J16: 220.82 | K16: тыс.руб.
E17: Средства на оплату труда | I17: 1.9 | J17: 108.15 | K17: тыс.руб.
E18: Затраты труда | I18: 159.63 | K18: чел.-ч.
A20: Составлен(а) по ТСН-2001 с учетом Дополнения №: 81
A21: № и период сборника коэффициентов (индексов) пересчета: Коэффициенты к ТСН-2001 МГЭ Дополнение 81, ремонт №220 II квартал 2026 года и Коэффициенты к ТСН-2001.13-2 Дополнение 47 №65 II квартал 2026 года
A22: № п/п | B22: Шифр расценки и коды ресурсов | C22: Наименование работ и затрат | D22: Ед. изм. | E22: Кол-во единиц | F22: Цена на ед. изм., руб. | G22: Попра- вочные коэффи- циенты | H22: Коэффи- циенты зимних удорожа- ний | I22: Всего в ценах на январь 2000 года, руб. | J22: Коэффи- циенты (индек- сы) пере- счета, нормы НР и СП | K22: ВСЕГО затрат в текущем уровне цен, руб.
A23: 1 | B23: 2 | C23: 3 | D23: 4 | E23: 5 | F23: 6 | G23: 7 | H23: 8 | I23: 9 | J23: 10 | K23: 11
A24: Раздел: Монтаж оборудования
A25: 1 | B25: 4.10-75-9 Поправка: Гл.12.Прил.8.п.8. 3_12.00.01.11.001 | C25: Монтаж аппаратуры настенной | D25: 1 ШТ. | E25: 1
C26: ЗП | F26: 89.44 | G26: 1,2 | H26: 1 | I26: 107.33 | J26: 57.05 | K26: 6123.18
C27: МР | F27: 24.1 | H27: 1 | I27: 24.1 | J27: 7.35 | K27: 177.14
C28: НР от ФОТ | D28: % | E28: 95 | I28: 101.96 | J28: 95 | K28: 5817.02
C29: СП от ФОТ | D29: % | E29: 53 | I29: 56.88 | J29: 53 | K29: 3245.29
C30: ЗТР | D30: чел-ч | E30: 8 | G30: 1,2 | H30: 1 | I30: 9.6
C31: ВСЕГО работ по позиции: | H31: 290.27 | J31: 15362.63
C32: ВСЕГО по позиции: | H32: 290.27 | J32: 15362.63
A34: 2 | B34: Прайс-лист | C34: ОБОРУДОВАНИЕ: Прибор управления оповещением 13 635,74 = [120 335 / 1,22 / 7,54] + 3% Трансп + 1,2% Заг.скл | D34: ШТ | E34: 1 | F34: 13635.74 | H34: 1 | I34: 13635.74 | J34: 7.54 | K34: 102813.48
C35: ВСЕГО по позиции: | H35: 13635.74 | J35: 102813.48
A37: 3 | B37: 4.11-7-1 Поправка: Гл.12.Прил.8.п.8. 3_12.00.01.11.001 | C37: Установка аппарата настольного массой до 0,015 т | D37: 1 ШТ. | E37: 1
C38: ЗП | F38: 11.52 | G38: 1,2 | H38: 1 | I38: 13.82 | J38: 57.05 | K38: 788.43
C39: ЭМ | F39: 13.3 | G39: 1,2 | H39: 1 | I39: 15.96 | J39: 17.45 | K39: 278.5
C40: в т.ч. ЗПМ | F40: 2.02 | G40: 1,2 | H40: 1 | I40: 2.42 | J40: 57.05 | K40: 138.06
C41: НР от ФОТ | D41: % | E41: 90 | I41: 14.62 | J41: 90 | K41: 833.84
C42: СП от ФОТ | D42: % | E42: 46 | I42: 7.47 | J42: 46 | K42: 426.19
C43: ЗТР | D43: чел-ч | E43: 1.03 | G43: 1,2 | H43: 1 | I43: 1.24
C44: ВСЕГО работ по позиции: | H44: 51.87 | J44: 2326.96
C45: ВСЕГО по позиции: | H45: 51.87 | J45: 2326.96
A47: 4 | B47: Прайс-лист | C47: ОБОРУДОВАНИЕ: Пульт микрофонный 1 781,64 = [15 722,82 / 1,22 / 7,54] + 3% Трансп + 1,2% Заг.скл | D47: ШТ | E47: 1 | F47: 1781.64 | H47: 1 | I47: 1781.64 | J47: 7.54 | K47: 13433.57
C48: ВСЕГО по позиции: | H48: 1781.64 | J48: 13433.57
A50: 5 | B50: 4.10-76-7 Поправка: Гл.12.Прил.8.п.8. 3_12.00.01.11.001 | C50: Монтаж громкоговорителя или звуковой колонки в помещении | D50: 1 ШТ. | E50: 35
C51: ЗП | F51: 23.78 | G51: 1,2 | H51: 1 | I51: 998.76 | J51: 57.05 | K51: 56979.26
C52: МР | F52: 24.46 | H52: 1 | I52: 856.1 | J52: 11.28 | K52: 9656.81
C53: НР от ФОТ | D53: % | E53: 95 | I53: 948.82 | J53: 95 | K53: 54130.3
C54: СП от ФОТ | D54: % | E54: 53 | I54: 529.34 | J54: 53 | K54: 30199.01
C55: ЗТР | D55: чел-ч | E55: 2 | G55: 1,2 | H55: 1 | I55: 84
C56: ВСЕГО работ по позиции: | H56: 3333.02 | J56: 150965.38
C57: ВСЕГО по позиции: | H57: 3333.02 | J57: 150965.38
A59: 6 | B59: Прайс-лист | C59: ОБОРУДОВАНИЕ: Оповещатель настенный 3/1,5Вт 305,38 = [2 695 / 1,22 / 7,54] + 3% Трансп + 1,2% Заг.скл | D59: ШТ | E59: 14 | F59: 305.38 | H59: 1 | I59: 4275.32 | J59: 7.54 | K59: 32235.91
C60: ВСЕГО по позиции: | H60: 4275.32 | J60: 32235.91
A62: 7 | B62: Прайс-лист | C62: ОБОРУДОВАНИЕ: Оповещатель потолочный 3/1,5Вт 289,96 = [2 558,84 / 1,22 / 7,54] + 3% Трансп + 1,2% Заг.скл | D62: ШТ | E62: 21 | F62: 289.96 | H62: 1 | I62: 6089.16 | J62: 7.54 | K62: 45912.27
C63: ВСЕГО по позиции: | H63: 6089.16 | J63: 45912.27
A65: 8 | B65: 4.10-118-12 Поправка: Гл.12.Прил.8.п.8. 3_12.00.01.11.001 | C65: Установка для трубных проводок коробки оконечной | D65: 100 шт. | E65: 0.02
C66: Объем: 0,02=2/100
C67: ЗП | F67: 278.64 | G67: 1,2 | H67: 1 | I67: 6.69 | J67: 57.05 | K67: 381.66
C68: МР | F68: 85.6 | H68: 1 | I68: 1.71 | J68: 4.64 | K68: 7.93
C69: НР от ФОТ | D69: % | E69: 90 | I69: 6.02 | J69: 90 | K69: 343.49
C70: СП от ФОТ | D70: % | E70: 46 | I70: 3.08 | J70: 46 | K70: 175.56
C71: ЗТР | D71: чел-ч | E71: 24 | G71: 1,2 | H71: 1 | I71: 0.58
C72: ВСЕГО работ по позиции: | H72: 17.5 | J72: 908.64
C73: ВСЕГО по позиции: | H73: 17.5 | J73: 908.64
A75: 9 | B75: Прайс-лист | C75: ОБОРУДОВАНИЕ: Фильтр оконечный 534,16 = [4 714 / 1,22 / 7,54] + 3% Трансп + 1,2% Заг.скл | D75: ШТ | E75: 2 | F75: 534.16 | H75: 1 | I75: 1068.32 | J75: 7.54 | K75: 8055.13
C76: ВСЕГО по позиции: | H76: 1068.32 | J76: 8055.13
A78: 10 | B78: 4.10-173-2 Поправка: Гл.12.Прил.8.п.8. 3_12.00.01.11.001 | C78: Монтаж блока бесперебойного питания (ББП) в диспетчерской | D78: 1 ШТ. | E78: 1
C79: ЗП | F79: 40.17 | G79: 1,2 | H79: 1 | I79: 48.2 | J79: 57.05 | K79: 2749.81
C80: МР | F80: 2.34 | H80: 1 | I80: 2.34 | J80: 9.91 | K80: 23.19
C81: НР от ФОТ | D81: % | E81: 90 | I81: 43.38 | J81: 90 | K81: 2474.83
C82: СП от ФОТ | D82: % | E82: 46 | I82: 22.17 | J82: 46 | K82: 1264.91
C83: ЗТР | D83: чел-ч | E83: 3.18 | G83: 1,2 | H83: 1 | I83: 3.82
C84: ВСЕГО работ по позиции: | H84: 116.09 | J84: 6512.74
C85: ВСЕГО по позиции: | H85: 116.09 | J85: 6512.74
A87: 11 | B87: Прайс-лист | C87: ОБОРУДОВАНИЕ: Блок резервного питания 641,70 = [5 663 / 1,22 / 7,54] + 3% Трансп + 1,2% Заг.скл | D87: ШТ | E87: 1 | F87: 641.7 | H87: 1 | I87: 641.7 | J87: 7.54 | K87: 4838.42
C88: ВСЕГО по позиции: | H88: 641.7 | J88: 4838.42
A90: 12 | B90: 13.1-1-451 | C90: ОБОРУДОВАНИЕ:_x000D_ Батарея аккумуляторная, емкость 40 А·ч, напряжение 12 В | D90: шт. | E90: 2 | F90: 698.81 | H90: 1 | I90: 1397.62 | J90: 6.51 | K90: 9098.51
C91: ВСЕГО по позиции: | H91: 1397.62 | J91: 9098.51
A93: 13 | B93: 4.8-237-17 Поправка: Гл.12.Прил.8.п.8. 3_12.00.01.11.001 | C93: Кожух металлический для защиты вводов и электрооборудования | D93: 1 кг | E93: 1.5
C94: ЗП | F94: 1.56 | G94: 1,2 | H94: 1 | I94: 2.81 | J94: 57.05 | K94: 160.31
C95: ЭМ | F95: 0.37 | G95: 1,2 | H95: 1 | I95: 0.67 | J95: 16.24 | K95: 10.88
C96: в т.ч. ЗПМ | F96: 0.04 | G96: 1,2 | H96: 1 | I96: 0.07 | J96: 57.05 | K96: 3.99
C97: МР | F97: 7 | H97: 1 | I97: 10.5 | J97: 10.18 | K97: 106.89
C98: НР от ФОТ | D98: % | E98: 97 | I98: 2.79 | J98: 97 | K98: 159.37
C99: СП от ФОТ | D99: % | E99: 51 | I99: 1.47 | J99: 51 | K99: 83.79
C100: ЗТР | D100: чел-ч | E100: 0.13 | G100: 1,2 | H100: 1 | I100: 0.23
C101: ВСЕГО работ по позиции: | H101: 18.24 | J101: 521.24
C102: ВСЕГО по позиции: | H102: 18.24 | J102: 521.24
A104: 14 | B104: Прайс-лист | C104: ОБОРУДОВАНИЕ: Кожух для моноблоков настенного исполнения 587,95 = [5 188,63 / 1,22 / 7,54] + 3% Трансп + 1,2% Заг.скл | D104: ШТ | E104: 1 | F104: 587.95 | H104: 1 | I104: 587.95 | J104: 7.54 | K104: 4433.14
C105: ВСЕГО по позиции: | H105: 587.95 | J105: 4433.14
A108: Итого по разделу: Монтаж оборудования | H108: 33304.44 | J108: 397418.02
A110: Раздел: Прокладка кабельных линий
A111: 15 | B111: 4.10-185-3 Поправка: Гл.12.Прил.8.п.8. 3_12.00.01.11.001 | C111: Прокладка кабеля связи огнестойкого в трубах гофрированных с использованием скобы СМО: по бетонным поверхностям | D111: 100 м | E111: 2
C112: Объем: 2=200/100
C113: ЗП | F113: 294.21 | G113: 1,2 | H113: 1 | I113: 706.1 | J113: 57.05 | K113: 40283.01
C114: ЭМ | F114: 4.05 | G114: 1,2 | H114: 1 | I114: 9.72 | J114: 11.41 | K114: 110.91
C115: МР | F115: 19.42 | H115: 1 | I115: 38.84 | J115: 6.38 | K115: 247.8
A116: 15,1 | B116: 1.12-5-372 | C116: Трубы электротехнические, гофрированные, из ПВХ, негорючие, с зондом, наружный диаметр 20 мм | D116: м | E116: 204 | F116: 3.45 | H116: 1 | I116: 703.8 | J116: 3.85 | K116: 2709.63
A117: 15,2 | B117: 1.21-5-1469 | C117: Скоба однолапковая стальная оцинкованная, для кабелей диаметром от 19 до 20 мм | D117: 1000 шт. | E117: 600 | F117: 396.59 | H117: 1 | I117: 237954 | J117: 4.05 | K117: 963713.7
A118: 15,3 | B118: 1.12-5-169 | C118: Муфта из полипропилена PP-R тип 3 (PRC-R), ГОСТ 32415-2013, соединительная, наружный диаметр 20 мм | D118: шт. | E118: 10 | F118: 2.47 | H118: 1 | I118: 24.7 | J118: 1.23 | K118: 30.38
A119: 15,4 | B119: 1.21-5-2488 | C119: Коробка ответвительная пластиковая, огнестойкая, 6 вводов для труб и кабеля, крышка с уплотнителем и фиксатором, с керамическими клеммными колодками, 4 контакта, степень защиты IP 55, габаритные размеры без учета кабельных вводов 100х100х50 мм | D119: шт. | E119: 4 | F119: 131.71 | H119: 1 | I119: 526.84 | J119: 5.15 | K119: 2713.23
C120: НР от ФОТ | D120: % | E120: 90 | I120: 635.49 | J120: 90 | K120: 36254.71
C121: СП от ФОТ | D121: % | E121: 46 | I121: 324.81 | J121: 46 | K121: 18530.18
C122: ЗТР | D122: чел-ч | E122: 24.76 | G122: 1,2 | H122: 1 | I122: 59.42
...

Sheet ЛС 02-01-10
J2: Форма № 4б
A3: =ССРСС!A11 -> Выполнение работ по капитальному ремонту здания в Басманном районе ЦАО города Москвы
A4: (наименование стройки и/или объекта)
A6: ЛОКАЛЬНАЯ СМЕТА № 02-01-10
A8: Система охранно-тревожной сигнализации
A9: (наименование работ и затрат)
I12: В базисном уровне цен | J12: В текущем уровне цен
E13: Сметная стоимость | I13: 84.65 | J13: 1286.63 | K13: тыс.руб.
E14: Строительные работы | I14: 8.52 | J14: 86.71 | K14: тыс.руб.
E15: Работы по монтажу оборудования | I15: 22.12 | J15: 792.76 | K15: тыс.руб.
E16: Оборудование | I16: 54.01 | J16: 407.16 | K16: тыс.руб.
E17: Средства на оплату труда | I17: 5.34 | J17: 304.39 | K17: тыс.руб.
E18: Затраты труда | I18: 419.05 | K18: чел.-ч.
A20: Составлен(а) по ТСН-2001 с учетом Дополнения №: 81
A21: № и период сборника коэффициентов (индексов) пересчета: Коэффициенты к ТСН-2001 МГЭ Дополнение 81, ремонт №220 II квартал 2026 года и Коэффициенты к ТСН-2001.13-2 Дополнение 47 №65 II квартал 2026 года
A22: № п/п | B22: Шифр расценки и коды ресурсов | C22: Наименование работ и затрат | D22: Ед. изм. | E22: Кол-во единиц | F22: Цена на ед. изм., руб. | G22: Попра- вочные коэффи- циенты | H22: Коэффи- циенты зимних удорожа- ний | I22: Всего в ценах на январь 2000 года, руб. | J22: Коэффи- циенты (индек- сы) пере- счета, нормы НР и СП | K22: ВСЕГО затрат в текущем уровне цен, руб.
A23: 1 | B23: 2 | C23: 3 | D23: 4 | E23: 5 | F23: 6 | G23: 7 | H23: 8 | I23: 9 | J23: 10 | K23: 11
A24: Раздел: АРМ СОТС
A25: 1 | B25: 4.11-7-2 Поправка: Гл.12.Прил.8.п.8. 3_12.00.01.11.001 | C25: Установка аппарата настольного массой до 0,03 т | D25: 1 ШТ. | E25: 1
C26: ЗП | F26: 34.55 | G26: 1,2 | H26: 1 | I26: 41.46 | J26: 57.05 | K26: 2365.29
C27: ЭМ | F27: 26.59 | G27: 1,2 | H27: 1 | I27: 31.91 | J27: 17.45 | K27: 556.83
C28: в т.ч. ЗПМ | F28: 4.04 | G28: 1,2 | H28: 1 | I28: 4.85 | J28: 57.05 | K28: 276.69
C29: НР от ФОТ | D29: % | E29: 90 | I29: 41.68 | J29: 90 | K29: 2377.78
C30: СП от ФОТ | D30: % | E30: 46 | I30: 21.3 | J30: 46 | K30: 1215.31
C31: ЗТР | D31: чел-ч | E31: 3.09 | G31: 1,2 | H31: 1 | I31: 3.71
C32: ВСЕГО работ по позиции: | H32: 136.35 | J32: 6515.21
C33: ВСЕГО по позиции: | H33: 136.35 | J33: 6515.21
A35: 2 | B35: Прайс-лист | C35: ОБОРУДОВАНИЕ: Автоматизированное рабочее место в комплекте (процессор, монитор, клавиатура, мышь) 9 679,34 = [85 420 / 1,22 / 7,54] + 3% Трансп + 1,2% Заг.скл | D35: ШТ | E35: 1 | F35: 9679.34 | H35: 1 | I35: 9679.34 | J35: 7.54 | K35: 72982.22
C36: ВСЕГО по позиции: | H36: 9679.34 | J36: 72982.22
A38: 3 | B38: Прайс-лист | C38: ОБОРУДОВАНИЕ: Операционная система 1 654,39 = [14 600 / 1,22 / 7,54] + 3% Трансп + 1,2% Заг.скл | D38: ШТ | E38: 1 | F38: 1654.39 | H38: 1 | I38: 1654.39 | J38: 7.54 | K38: 12474.1
C39: ВСЕГО по позиции: | H39: 1654.39 | J39: 12474.1
A41: 4 | B41: 4.10-173-2 Поправка: Гл.12.Прил.8.п.8. 3_12.00.01.11.001 | C41: Монтаж блока бесперебойного питания (ББП) в диспетчерской | D41: 1 ШТ. | E41: 1
C42: ЗП | F42: 40.17 | G42: 1,2 | H42: 1 | I42: 48.2 | J42: 57.05 | K42: 2749.81
C43: МР | F43: 2.34 | H43: 1 | I43: 2.34 | J43: 9.91 | K43: 23.19
C44: НР от ФОТ | D44: % | E44: 90 | I44: 43.38 | J44: 90 | K44: 2474.83
C45: СП от ФОТ | D45: % | E45: 46 | I45: 22.17 | J45: 46 | K45: 1264.91
C46: ЗТР | D46: чел-ч | E46: 3.18 | G46: 1,2 | H46: 1 | I46: 3.82
C47: ВСЕГО работ по позиции: | H47: 116.09 | J47: 6512.74
C48: ВСЕГО по позиции: | H48: 116.09 | J48: 6512.74
A50: 5 | B50: Прайс-лист | C50: ОБОРУДОВАНИЕ: Источник бесперебойного питания, 600Вт 1 083,57 = [9 562,46 / 1,22 / 7,54] + 3% Трансп + 1,2% Заг.скл | D50: ШТ | E50: 1 | F50: 1083.57 | H50: 1 | I50: 1083.57 | J50: 7.54 | K50: 8170.12
C51: ВСЕГО по позиции: | H51: 1083.57 | J51: 8170.12
A53: 6 | B53: Прайс-лист | C53: Патч-корд 11,60 = [141,18 / 1,22 / 10,18] + 2% Заг.скл | D53: ШТ | E53: 2 | F53: 11.6 | H53: 1 | I53: 23.2 | J53: 10.18 | K53: 236.18
C54: ВСЕГО по позиции: | H54: 23.2 | J54: 236.18
A57: Итого по разделу: АРМ СОТС | H57: 12692.94 | J57: 106890.57
A59: Раздел: Монтажные работы
A60: 7 | B60: 4.10-80-1 Поправка: Гл.12.Прил.8.п.8. 3_12.00.01.11.001 | C60: Аппараты приемные, приборы ПС приемно-контрольные, пусковые, концентратор, блок базовый на 10 лучей | D60: 1 ШТ. | E60: 1
C61: ЗП | F61: 95.04 | G61: 1,2 | H61: 1 | I61: 114.05 | J61: 57.05 | K61: 6506.55
C62: ЭМ | F62: 0.06 | G62: 1,2 | H62: 1 | I62: 0.07 | J62: 18.83 | K62: 1.32
C63: в т.ч. ЗПМ | F63: 0.01 | G63: 1,2 | H63: 1 | I63: 0.01 | J63: 57.05 | K63: 0.57
C64: МР | F64: 12.53 | H64: 1 | I64: 12.53 | J64: 10.18 | K64: 127.56
C65: НР от ФОТ | D65: % | E65: 90 | I65: 102.65 | J65: 90 | K65: 5856.41
C66: СП от ФОТ | D66: % | E66: 46 | I66: 52.47 | J66: 46 | K66: 2993.28
C67: ЗТР | D67: чел-ч | E67: 7.2 | G67: 1,2 | H67: 1 | I67: 8.64
C68: ВСЕГО работ по позиции: | H68: 281.77 | J68: 15485.12
C69: ВСЕГО по позиции: | H69: 281.77 | J69: 15485.12
A71: 8 | B71: Прайс-лист | C71: ОБОРУДОВАНИЕ: Прибор приемно-контрольный и управления,модуль сопряжения 4 870,38 = [42 981 / 1,22 / 7,54] + 3% Трансп + 1,2% Заг.скл | D71: ШТ | E71: 1 | F71: 4870.38 | H71: 1 | I71: 4870.38 | J71: 7.54 | K71: 36722.67
C72: ВСЕГО по позиции: | H72: 4870.38 | J72: 36722.67
A74: 9 | B74: 4.10-81-2 Поправка: Гл.12.Прил.8.п.8. 3_12.00.01.11.001 | C74: Извещатели ПС автоматические, дымовой, фотоэлектрический, радиоизотопный, световой в нормальном исполнении | D74: 1 ШТ. | E74: 1
C75: ЗП | F75: 21.2 | G75: 1,2 | H75: 1 | I75: 25.44 | J75: 57.05 | K75: 1451.35
C76: ЭМ | F76: 0.06 | G76: 1,2 | H76: 1 | I76: 0.07 | J76: 18.83 | K76: 1.32
C77: в т.ч. ЗПМ | F77: 0.01 | G77: 1,2 | H77: 1 | I77: 0.01 | J77: 57.05 | K77: 0.57
C78: МР | F78: 1.26 | H78: 1 | I78: 1.26 | J78: 10.18 | K78: 12.83
A79: 9,1 | B79: 13.1-2-611 | C79: ОБОРУДОВАНИЕ: Оповещатель охранно-пожарный световой. Напряжение питания от 10,2 до 15 В, потребляемый ток от 18 до 22 мА, степень защиты IP55 | D79: шт. | E79: 1 | F79: 53.88 | H79: 1 | I79: 53.88 | J79: 3.66 | K79: 197.2
C80: НР от ФОТ | D80: % | E80: 90 | I80: 22.91 | J80: 90 | K80: 1306.73
C81: СП от ФОТ | D81: % | E81: 46 | I81: 11.71 | J81: 46 | K81: 667.88
C82: ЗТР | D82: чел-ч | E82: 1.68 | G82: 1,2 | H82: 1 | I82: 2.02
C83: ВСЕГО работ по позиции: | H83: 61.39 | J83: 3440.11
C84: ВСЕГО оборудование по позиции: | H84: 53.88 | J84: 197.2
C85: ВСЕГО по позиции: | H85: 115.27 | J85: 3637.31
A87: 10 | B87: 4.10-80-13 Поправка: Гл.12.Прил.8.п.8. 3_12.00.01.11.001 | C87: Аппараты приемные, устройства промежуточные на 1 луч | D87: 1 ШТ. | E87: 1
C88: ЗП | F88: 16.07 | G88: 1,2 | H88: 1 | I88: 19.28 | J88: 57.05 | K88: 1099.92
C89: ЭМ | F89: 0.05 | G89: 1,2 | H89: 1 | I89: 0.06 | J89: 20.4 | K89: 1.22
C90: в т.ч. ЗПМ | F90: 0.01 | G90: 1,2 | H90: 1 | I90: 0.01 | J90: 57.05 | K90: 0.57
C91: МР | F91: 1.96 | H91: 1 | I91: 1.96 | J91: 10.18 | K91: 19.95
C92: НР от ФОТ | D92: % | E92: 90 | I92: 17.36 | J92: 90 | K92: 990.44
C93: СП от ФОТ | D93: % | E93: 46 | I93: 8.87 | J93: 46 | K93: 506.23
C94: ЗТР | D94: чел-ч | E94: 1.2 | G94: 1,2 | H94: 1 | I94: 1.44
C95: ВСЕГО работ по позиции: | H95: 47.53 | J95: 2617.76
C96: ВСЕГО по позиции: | H96: 47.53 | J96: 2617.76
A98: 11 | B98: Прайс-лист | C98: ОБОРУДОВАНИЕ: Модуль сопряжения 2 772,13 = [24 464 / 1,22 / 7,54] + 3% Трансп + 1,2% Заг.скл | D98: ШТ | E98: 1 | F98: 2772.13 | H98: 1 | I98: 2772.13 | J98: 7.54 | K98: 20901.86
C99: ВСЕГО по позиции: | H99: 2772.13 | J99: 20901.86
A101: 12 | B101: 4.10-170-2 Поправка: Гл.12.Прил.8.п.8. 3_12.00.01.11.001 | C101: Монтаж блока информационно-управляющего (БИУ) в диспетчерской | D101: 1 ШТ. | E101: 1
C102: ЗП | F102: 33.47 | G102: 1,2 | H102: 1 | I102: 40.16 | J102: 57.05 | K102: 2291.13
C103: МР | F103: 2.34 | H103: 1 | I103: 2.34 | J103: 9.91 | K103: 23.19
C104: НР от ФОТ | D104: % | E104: 90 | I104: 36.14 | J104: 90 | K104: 2062.02
C105: СП от ФОТ | D105: % | E105: 46 | I105: 18.47 | J105: 46 | K105: 1053.92
C106: ЗТР | D106: чел-ч | E106: 2.65 | G106: 1,2 | H106: 1 | I106: 3.18
C107: ВСЕГО работ по позиции: | H107: 97.11 | J107: 5430.26
C108: ВСЕГО по позиции: | H108: 97.11 | J108: 5430.26
A110: 13 | B110: Прайс-лист | C110: ОБОРУДОВАНИЕ: Блок индикации и управления 2 394,57 = [21 132 / 1,22 / 7,54] + 3% Трансп + 1,2% Заг.скл | D110: ШТ | E110: 1 | F110: 2394.57 | H110: 1 | I110: 2394.57 | J110: 7.54 | K110: 18055.06
C111: ВСЕГО по позиции: | H111: 2394.57 | J111: 18055.06
A113: 14 | B113: 4.10-173-2 Поправка: Гл.12.Прил.8.п.8. 3_12.00.01.11.001 | C113: Монтаж блока бесперебойного питания (ББП) в диспетчерской | D113: 1 ШТ. | E113: 2
C114: ЗП | F114: 40.17 | G114: 1,2 | H114: 1 | I114: 96.41 | J114: 57.05 | K114: 5500.19
C115: МР | F115: 2.34 | H115: 1 | I115: 4.68 | J115: 9.91 | K115: 46.38
C116: НР от ФОТ | D116: % | E116: 90 | I116: 86.77 | J116: 90 | K116: 4950.17
C117: СП от ФОТ | D117: % | E117: 46 | I117: 44.35 | J117: 46 | K117: 2530.09
C118: ЗТР | D118: чел-ч | E118: 3.18 | G118: 1,2 | H118: 1 | I118: 7.63
C119: ВСЕГО работ по позиции: | H119: 232.21 | J119: 13026.83
C120: ВСЕГО по позиции: | H120: 232.21 | J120: 13026.83
A122: 15 | B122: Прайс-лист | C122: ОБОРУДОВАНИЕ: Блок питания, 12В, 2А 761,02 = [6 716 / 1,22 / 7,54] + 3% Трансп + 1,2% Заг.скл | D122: ШТ | E122: 2 | F122: 761.02 | H122: 1 | I122: 1522.04 | J122: 7.54 | K122: 11476.18
...

Sheet ЛС 02-01-11
J2: Форма № 4б
A3: =ССРСС!A11 -> Выполнение работ по капитальному ремонту здания в Басманном районе ЦАО города Москвы
A4: (наименование стройки и/или объекта)
A6: ЛОКАЛЬНАЯ СМЕТА № 02-01-11
A8: Радиотрансляционная сеть
A9: (наименование работ и затрат)
I12: В базисном уровне цен | J12: В текущем уровне цен
E13: Сметная стоимость | I13: 179.2 | J13: 1463.47 | K13: тыс.руб.
E14: Строительные работы | I14: 0.7 | J14: 7.09 | K14: тыс.руб.
E15: Работы по монтажу оборудования | I15: 5.1 | J15: 146.82 | K15: тыс.руб.
E16: Оборудование | I16: 173.4 | J16: 1309.56 | K16: тыс.руб.
E17: Средства на оплату труда | I17: 0.9 | J17: 51.54 | K17: тыс.руб.
E18: Затраты труда | I18: 71.6 | K18: чел.-ч.
A20: Составлен(а) по ТСН-2001 с учетом Дополнения №: 81
A21: № и период сборника коэффициентов (индексов) пересчета: Коэффициенты к ТСН-2001 МГЭ Дополнение 81, ремонт №220 II квартал 2026 года и Коэффициенты к ТСН-2001.13-2 Дополнение 47 №65 II квартал 2026 года
A22: № п/п | B22: Шифр расценки и коды ресурсов | C22: Наименование работ и затрат | D22: Ед. изм. | E22: Кол-во единиц | F22: Цена на ед. изм., руб. | G22: Попра- вочные коэффи- циенты | H22: Коэффи- циенты зимних удорожа- ний | I22: Всего в ценах на январь 2000 года, руб. | J22: Коэффи- циенты (индек- сы) пере- счета, нормы НР и СП | K22: ВСЕГО затрат в текущем уровне цен, руб.
A23: 1 | B23: 2 | C23: 3 | D23: 4 | E23: 5 | F23: 6 | G23: 7 | H23: 8 | I23: 9 | J23: 10 | K23: 11
A24: Раздел: Оборудование
A25: 1 | B25: 4.10-75-1 Поправка: Гл.12.Прил.8.п.8. 3_12.00.01.11.001 | C25: Установка шкафа или статива (стойки) радиотрансляционных узлов массой до 100 кг | D25: 1 ШТ. | E25: 1
C26: ЗП | F26: 164.06 | G26: 1,2 | H26: 1 | I26: 196.87 | J26: 57.05 | K26: 11231.43
C27: НР от ФОТ | D27: % | E27: 95 | I27: 187.03 | J27: 95 | K27: 10669.86
C28: СП от ФОТ | D28: % | E28: 53 | I28: 104.34 | J28: 53 | K28: 5952.66
C29: ЗТР | D29: чел-ч | E29: 13 | G29: 1,2 | H29: 1 | I29: 15.6
C30: ВСЕГО работ по позиции: | H30: 488.24 | J30: 27853.95
C31: ВСЕГО по позиции: | H31: 488.24 | J31: 27853.95
A33: 2 | B33: Прайс-лист | C33: ОБОРУДОВАНИЕ: Устройство подачи программ вещания 56 920,27 = [502 320 / 1,22 / 7,54] + 3% Трансп + 1,2% Заг.скл | D33: ШТ | E33: 1 | F33: 56920.27 | H33: 1 | I33: 56920.27 | J33: 7.54 | K33: 429178.84
C34: ВСЕГО по позиции: | H34: 56920.27 | J34: 429178.84
A36: 3 | B36: 4.11-12-1 Поправка: Гл.12.Прил.8.п.8. 3_12.00.01.11.001 | C36: Установка съемных и выдвижных блоков (модулей, ячеек, ТЭЗ) массой до 5 кг | D36: 1 ШТ. | E36: 1
C37: ЗП | F37: 11.65 | G37: 1,2 | H37: 1 | I37: 13.98 | J37: 57.05 | K37: 797.56
C38: ЭМ | F38: 0.5 | G38: 1,2 | H38: 1 | I38: 0.6 | J38: 17.4 | K38: 10.44
C39: в т.ч. ЗПМ | F39: 0.08 | G39: 1,2 | H39: 1 | I39: 0.1 | J39: 57.05 | K39: 5.71
C40: НР от ФОТ | D40: % | E40: 90 | I40: 12.67 | J40: 90 | K40: 722.94
C41: СП от ФОТ | D41: % | E41: 46 | I41: 6.48 | J41: 46 | K41: 369.5
C42: ЗТР | D42: чел-ч | E42: 1.03 | G42: 1,2 | H42: 1 | I42: 1.24
C43: ВСЕГО работ по позиции: | H43: 33.73 | J43: 1900.44
C44: ВСЕГО по позиции: | H44: 33.73 | J44: 1900.44
A46: 4 | B46: Прайс-лист | C46: ОБОРУДОВАНИЕ:_x000D_ Модуль для приема потокового вещания «Радио Москвы» 3 467,44 = [30 600 / 1,22 / 7,54] + 3% Трансп + 1,2% Заг.скл | D46: ШТ | E46: 1 | F46: 3467.44 | H46: 1 | I46: 3467.44 | J46: 7.54 | K46: 26144.5
C47: ВСЕГО по позиции: | H47: 3467.44 | J47: 26144.5
A49: 5 | B49: 4.10-75-1 Поправка: Гл.12.Прил.8.п.8. 3_12.00.01.11.001 | C49: Установка шкафа или статива (стойки) радиотрансляционных узлов массой до 100 кг | D49: 1 ШТ. | E49: 1
C50: ЗП | F50: 164.06 | G50: 1,2 | H50: 1 | I50: 196.87 | J50: 57.05 | K50: 11231.43
C51: НР от ФОТ | D51: % | E51: 95 | I51: 187.03 | J51: 95 | K51: 10669.86
C52: СП от ФОТ | D52: % | E52: 53 | I52: 104.34 | J52: 53 | K52: 5952.66
C53: ЗТР | D53: чел-ч | E53: 13 | G53: 1,2 | H53: 1 | I53: 15.6
C54: ВСЕГО работ по позиции: | H54: 488.24 | J54: 27853.95
C55: ВСЕГО по позиции: | H55: 488.24 | J55: 27853.95
A57: 6 | B57: Прайс-лист | C57: ОБОРУДОВАНИЕ: Устройство сопряжения с РСО г. Москвы типа УС-1 93 484,69 = [825 000 / 1,22 / 7,54] + 3% Трансп + 1,2% Заг.скл | D57: ШТ | E57: 1 | F57: 93484.69 | H57: 1 | I57: 93484.69 | J57: 7.54 | K57: 704874.56
C58: ВСЕГО по позиции: | H58: 93484.69 | J58: 704874.56
A60: 7 | B60: 4.10-75-9 Поправка: Гл.12.Прил.8.п.8. 3_12.00.01.11.001 | C60: Монтаж аппаратуры настенной | D60: 1 ШТ. | E60: 1
C61: ЗП | F61: 89.44 | G61: 1,2 | H61: 1 | I61: 107.33 | J61: 57.05 | K61: 6123.18
C62: МР | F62: 24.1 | H62: 1 | I62: 24.1 | J62: 7.35 | K62: 177.14
C63: НР от ФОТ | D63: % | E63: 95 | I63: 101.96 | J63: 95 | K63: 5817.02
C64: СП от ФОТ | D64: % | E64: 53 | I64: 56.88 | J64: 53 | K64: 3245.29
C65: ЗТР | D65: чел-ч | E65: 8 | G65: 1,2 | H65: 1 | I65: 9.6
C66: ВСЕГО работ по позиции: | H66: 290.27 | J66: 15362.63
C67: ВСЕГО по позиции: | H67: 290.27 | J67: 15362.63
A69: 8 | B69: Прайс-лист | C69: ОБОРУДОВАНИЕ: Объектовая станция 13 325,82 = [117 600 / 1,22 / 7,54] + 3% Трансп + 1,2% Заг.скл | D69: ШТ | E69: 1 | F69: 13325.82 | H69: 1 | I69: 13325.82 | J69: 7.54 | K69: 100476.68
C70: ВСЕГО по позиции: | H70: 13325.82 | J70: 100476.68
A72: 9 | B72: Прайс-лист | C72: ОБОРУДОВАНИЕ: Радиоприемник трехпрограммный 829,47 = [7 320 / 1,22 / 7,54] + 3% Трансп + 1,2% Заг.скл | D72: ШТ | E72: 1 | F72: 829.47 | H72: 1 | I72: 829.47 | J72: 7.54 | K72: 6254.2
C73: ВСЕГО по позиции: | H73: 829.47 | J73: 6254.2
A76: Итого по разделу: Оборудование | H76: 169328.17 | J76: 1339899.8
A78: Раздел: Изделия
A79: 10 | B79: 4.8-333-7 Поправка: Гл.12.Прил.8.п.8. 3_12.00.01.11.001 | C79: Монтаж розетки штепсельной скрытого типа | D79: 100 шт. | E79: 0.01
C80: Объем: 0,01=1/100
C81: ЗП | F81: 210.57 | G81: 1,2 | H81: 1 | I81: 2.53 | J81: 57.05 | K81: 144.34
C82: ЭМ | F82: 0.83 | G82: 1,2 | H82: 1 | I82: 0.01 | J82: 17.47 | K82: 0.17
A83: 10,1 | B83: 1.14-1-23 | C83: Розетка радиотрансляционная, скрытой установки, типа РПВ-2 | D83: шт. | E83: 1 | F83: 3.16 | H83: 1 | I83: 3.16 | J83: 28.28 | K83: 89.36
C84: НР от ФОТ | D84: % | E84: 97 | I84: 2.45 | J84: 97 | K84: 140.01
C85: СП от ФОТ | D85: % | E85: 51 | I85: 1.29 | J85: 51 | K85: 73.61
C86: ЗТР | D86: чел-ч | E86: 18.84 | G86: 1,2 | H86: 1 | I86: 0.23
C87: ВСЕГО работ по позиции: | H87: 9.44 | J87: 447.49
C88: ВСЕГО по позиции: | H88: 9.44 | J88: 447.49
A90: 11 | B90: 1.14-1-13 | C90: Коробка радиотрансляционная, универсальная, для подключения радиотрансляционной сети, типа РОН | D90: шт. | E90: 1 | F90: 29.6 | H90: 1 | I90: 29.6 | J90: 6.17 | K90: 182.63
C91: ВСЕГО по позиции: | H91: 29.6 | J91: 182.63
A93: 12 | B93: 4.10-134-3 Поправка: Гл.12.Прил.8.п.8. 3_12.00.01.11.001 | C93: Монтаж металлоконструкций для телевизионных антенн | D93: 1 Т | E93: 0.0051
C94: ЗП | F94: 434.24 | G94: 1,2 | H94: 1 | I94: 2.66 | J94: 57.05 | K94: 151.75
C95: ЭМ | F95: 1.94 | G95: 1,2 | H95: 1 | I95: 0.01 | J95: 10.37 | K95: 0.1
C96: МР | F96: 108.97 | H96: 1 | I96: 0.56 | J96: 4.46 | K96: 2.5
A97: 12,1 | B97: 13.1-2-575 | C97: ОБОРУДОВАНИЕ:_x000D_ Мачта для телевизионной антенны, высота не более 6 м, без защелок-натяжителей и проволоки для оттяжек. Максимальное количество устанавливаемых антенн не более 3 шт. | D97: шт. | E97: 1 | F97: 342.13 | H97: 1 | I97: 342.13 | J97: 13.83 | K97: 4731.66
C98: НР от ФОТ | D98: % | E98: 95 | I98: 2.53 | J98: 95 | K98: 144.16
C99: СП от ФОТ | D99: % | E99: 53 | I99: 1.41 | J99: 53 | K99: 80.43
C100: ЗТР | D100: чел-ч | E100: 32 | G100: 1,2 | H100: 1 | I100: 0.2
C101: ВСЕГО работ по позиции: | H101: 7.17 | J101: 378.94
C102: ВСЕГО по позиции: | H102: 349.3 | J102: 5110.6
A104: 13 | B104: Прайс-лист | C104: ОБОРУДОВАНИЕ: Комплект крепления мачты 691,39 = [6 101,45 / 1,22 / 7,54] + 3% Трансп + 1,2% Заг.скл | D104: ШТ | E104: 1 | F104: 691.39 | H104: 1 | I104: 691.39 | J104: 7.54 | K104: 5213.08
C105: ВСЕГО по позиции: | H105: 691.39 | J105: 5213.08
A107: 14 | B107: 4.10-134-7 Поправка: Гл.12.Прил.8.п.8. 3_12.00.01.11.001 | C107: Монтаж антенны дополнительной для приема ТВ на ранее установленной опоре, с действующими ТВ антеннами | D107: 1 антенна | E107: 1
C108: ЗП | F108: 39.85 | G108: 1,2 | H108: 1 | I108: 47.82 | J108: 57.05 | K108: 2728.13
C109: МР | F109: 0.18 | H109: 1 | I109: 0.18 | J109: 5.61 | K109: 1.01
C110: НР от ФОТ | D110: % | E110: 95 | I110: 45.43 | J110: 95 | K110: 2591.72
C111: СП от ФОТ | D111: % | E111: 53 | I111: 25.34 | J111: 53 | K111: 1445.91
C112: ЗТР | D112: чел-ч | E112: 2.77 | G112: 1,2 | H112: 1 | I112: 3.32
C113: ВСЕГО работ по позиции: | H113: 118.77 | J113: 6766.77
C114: ВСЕГО по позиции: | H114: 118.77 | J114: 6766.77
A116: 15 | B116: Прайс-лист | C116: ОБОРУДОВАНИЕ: Антенна эфирная УКВ-FM диапазона 1 269,13 = [11 200 / 1,22 / 7,54] + 3% Трансп + 1,2% Заг.скл | D116: ШТ | E116: 1 | F116: 1269.13 | H116: 1 | I116: 1269.13 | J116: 7.54 | K116: 9569.24
C117: ВСЕГО по позиции: | H117: 1269.13 | J117: 9569.24
A119: 16 | B119: 4.10-134-4 Поправка: Гл.12.Прил.8.п.8. 3_12.00.01.11.001 | C119: Монтаж антенны коллективной для приема ТВ на антенной опоре высотой до 9 м с одним ярусом оттяжек | D119: 1 антенна | E119: 1
C120: ЗП | F120: 76.15 | G120: 1,2 | H120: 1 | I120: 91.38 | J120: 57.05 | K120: 5213.23
C121: МР | F121: 0.37 | H121: 1 | I121: 0.37 | J121: 5.46 | K121: 2.02
C122: НР от ФОТ | D122: % | E122: 95 | I122: 86.81 | J122: 95 | K122: 4952.57
C123: СП от ФОТ | D123: % | E123: 53 | I123: 48.43 | J123: 53 | K123: 2763.01
...

Sheet ЛС 02-01-12
J2: Форма № 4б
A3: =ССРСС!A11 -> Выполнение работ по капитальному ремонту здания в Басманном районе ЦАО города Москвы
A4: (наименование стройки и/или объекта)
A6: ЛОКАЛЬНАЯ СМЕТА № 02-01-12
A8: Система кабельного телевидения
A9: (наименование работ и затрат)
I12: В базисном уровне цен | J12: В текущем уровне цен
E13: Сметная стоимость | I13: 26.58 | J13: 331.72 | K13: тыс.руб.
E14: Строительные работы | I14: 0.6 | J14: 6.12 | K14: тыс.руб.
E15: Работы по монтажу оборудования | I15: 15.03 | J15: 243.07 | K15: тыс.руб.
E16: Оборудование | I16: 10.95 | J16: 82.53 | K16: тыс.руб.
E17: Средства на оплату труда | I17: 1.59 | J17: 90.48 | K17: тыс.руб.
E18: Затраты труда | I18: 111.37 | K18: чел.-ч.
A20: Составлен(а) по ТСН-2001 с учетом Дополнения №: 81
A21: № и период сборника коэффициентов (индексов) пересчета: Коэффициенты к ТСН-2001 МГЭ Дополнение 81, строительство №220 II квартал 2026 года и Коэффициенты к ТСН-2001.13-2 Дополнение 47 №65 II квартал 2026 года
A22: № п/п | B22: Шифр расценки и коды ресурсов | C22: Наименование работ и затрат | D22: Ед. изм. | E22: Кол-во единиц | F22: Цена на ед. изм., руб. | G22: Попра- вочные коэффи- циенты | H22: Коэффи- циенты зимних удорожа- ний | I22: Всего в ценах на январь 2000 года, руб. | J22: Коэффи- циенты (индек- сы) пере- счета, нормы НР и СП | K22: ВСЕГО затрат в текущем уровне цен, руб.
A23: 1 | B23: 2 | C23: 3 | D23: 4 | E23: 5 | F23: 6 | G23: 7 | H23: 8 | I23: 9 | J23: 10 | K23: 11
A24: Раздел: Монтажные работы
A25: 1 | B25: 4.10-136-5 Поправка: Гл.12.Прил.8.п.8. 3_12.00.01.11.001 | C25: Монтаж базового блока головной станции настенного типа | D25: 1 ШТ. | E25: 1
C26: ЗП | F26: 111.68 | G26: 1,2 | H26: 1 | I26: 134.02 | J26: 57.05 | K26: 7645.84
C27: МР | F27: 0.3 | H27: 1 | I27: 0.3 | J27: 7.37 | K27: 2.21
C28: НР от ФОТ | D28: % | E28: 95 | I28: 127.32 | J28: 95 | K28: 7263.55
C29: СП от ФОТ | D29: % | E29: 53 | I29: 71.03 | J29: 53 | K29: 4052.3
C30: ЗТР | D30: чел-ч | E30: 8 | G30: 1,2 | H30: 1 | I30: 9.6
C31: ВСЕГО работ по позиции: | H31: 332.67 | J31: 18963.9
C32: ВСЕГО по позиции: | H32: 332.67 | J32: 18963.9
A34: 2 | B34: Прайс-лист | C34: ОБОРУДОВАНИЕ: Головная станция 9 396,45 = [82 923,38 / 1,22 / 7,54] + 3% Трансп + 1,2% Заг.скл | D34: ШТ | E34: 1 | F34: 9396.45 | H34: 1 | I34: 9396.45 | J34: 7.54 | K34: 70849.23
C35: ВСЕГО по позиции: | H35: 9396.45 | J35: 70849.23
A37: 3 | B37: 4.10-136-3 Поправка: Гл.12.Прил.8.п.8. 3_12.00.01.11.001 | C37: Монтаж антенного ТВ усилителя на мачте (без измерений) без повала мачты | D37: 1 ШТ. | E37: 1
C38: ЗП | F38: 25.78 | G38: 1,2 | H38: 1 | I38: 30.94 | J38: 57.05 | K38: 1765.13
C39: МР | F39: 0.18 | H39: 1 | I39: 0.18 | J39: 5.61 | K39: 1.01
C40: НР от ФОТ | D40: % | E40: 95 | I40: 29.39 | J40: 95 | K40: 1676.87
C41: СП от ФОТ | D41: % | E41: 53 | I41: 16.4 | J41: 53 | K41: 935.52
C42: ЗТР | D42: чел-ч | E42: 1.9 | G42: 1,2 | H42: 1 | I42: 2.28
C43: ВСЕГО работ по позиции: | H43: 76.91 | J43: 4378.53
C44: ВСЕГО по позиции: | H44: 76.91 | J44: 4378.53
A46: 4 | B46: Прайс-лист | C46: ОБОРУДОВАНИЕ: Антенный усилитель с БП 12В, Ку= 14/27 237,96 = [2 100 / 1,22 / 7,54] + 3% Трансп + 1,2% Заг.скл | D46: ШТ | E46: 1 | F46: 237.96 | H46: 1 | I46: 237.96 | J46: 7.54 | K46: 1794.22
C47: ВСЕГО по позиции: | H47: 237.96 | J47: 1794.22
A49: 5 | B49: 4.10-136-1 Поправка: Гл.12.Прил.8.п.8. 3_12.00.01.11.001 | C49: Монтаж коробки телевизионной (ответвители, разветвители магистральные, домовые, абонентские), УСС, БФТК | D49: 1 ШТ. | E49: 1
C50: ЗП | F50: 11.02 | G50: 1,2 | H50: 1 | I50: 13.22 | J50: 57.05 | K50: 754.2
C51: МР | F51: 0.3 | H51: 1 | I51: 0.3 | J51: 7.37 | K51: 2.21
A52: 5,1 | B52: 1.14-1-249 | C52: Ответвитель на 4 направления, диапазон рабочих частот от 5 до 1300 МГц | D52: шт. | E52: 1 | F52: 330.92 | H52: 1 | I52: 330.92 | J52: 0.71 | K52: 234.95
C53: НР от ФОТ | D53: % | E53: 95 | I53: 12.56 | J53: 95 | K53: 716.49
C54: СП от ФОТ | D54: % | E54: 53 | I54: 7.01 | J54: 53 | K54: 399.73
C55: ЗТР | D55: чел-ч | E55: 0.8 | G55: 1,2 | H55: 1 | I55: 0.96
C56: ВСЕГО работ по позиции: | H56: 364.01 | J56: 2107.58
C57: ВСЕГО по позиции: | H57: 364.01 | J57: 2107.58
A59: 6 | B59: 4.10-134-4 Поправка: Гл.12.Прил.8.п.8. 3_12.00.01.11.001 | C59: Монтаж антенны коллективной для приема ТВ на антенной опоре высотой до 9 м с одним ярусом оттяжек | D59: 1 антенна | E59: 1
C60: ЗП | F60: 76.15 | G60: 1,2 | H60: 1 | I60: 91.38 | J60: 57.05 | K60: 5213.23
C61: МР | F61: 0.37 | H61: 1 | I61: 0.37 | J61: 5.46 | K61: 2.02
C62: НР от ФОТ | D62: % | E62: 95 | I62: 86.81 | J62: 95 | K62: 4952.57
C63: СП от ФОТ | D63: % | E63: 53 | I63: 48.43 | J63: 53 | K63: 2763.01
C64: ЗТР | D64: чел-ч | E64: 5.37 | G64: 1,2 | H64: 1 | I64: 6.44
C65: ВСЕГО работ по позиции: | H65: 226.99 | J65: 12930.83
C66: ВСЕГО по позиции: | H66: 226.99 | J66: 12930.83
A68: 7 | B68: Прайс-лист | C68: ОБОРУДОВАНИЕ: Антенна 623,23 = [5 500 / 1,22 / 7,54] + 3% Трансп + 1,2% Заг.скл | D68: ШТ | E68: 1 | F68: 623.23 | H68: 1 | I68: 623.23 | J68: 7.54 | K68: 4699.15
C69: ВСЕГО по позиции: | H69: 623.23 | J69: 4699.15
A71: 8 | B71: 4.10-136-1 Поправка: Гл.12.Прил.8.п.8. 3_12.00.01.11.001 | C71: Монтаж коробки телевизионной (ответвители, разветвители магистральные, домовые, абонентские), УСС, БФТК | D71: 1 ШТ. | E71: 1
C72: ЗП | F72: 11.02 | G72: 1,2 | H72: 1 | I72: 13.22 | J72: 57.05 | K72: 754.2
C73: МР | F73: 0.3 | H73: 1 | I73: 0.3 | J73: 7.37 | K73: 2.21
C74: НР от ФОТ | D74: % | E74: 95 | I74: 12.56 | J74: 95 | K74: 716.49
C75: СП от ФОТ | D75: % | E75: 53 | I75: 7.01 | J75: 53 | K75: 399.73
C76: ЗТР | D76: чел-ч | E76: 0.8 | G76: 1,2 | H76: 1 | I76: 0.96
C77: ВСЕГО работ по позиции: | H77: 33.09 | J77: 1872.63
C78: ВСЕГО по позиции: | H78: 33.09 | J78: 1872.63
A80: 9 | B80: Прайс-лист | C80: ОБОРУДОВАНИЕ: Грозозащита на 75 Ом 687,94 = [6 071,03 / 1,22 / 7,54] + 3% Трансп + 1,2% Заг.скл | D80: ШТ | E80: 1 | F80: 687.94 | H80: 1 | I80: 687.94 | J80: 7.54 | K80: 5187.07
C81: ВСЕГО по позиции: | H81: 687.94 | J81: 5187.07
A83: 10 | B83: 4.11-13-47 Поправка: Гл.12.Прил.8.п.8. 3_12.00.01.11.001 | C83: Монтаж разъема штепсельного с разделкой и включением радиочастотного коаксиального кабеля диаметром оболочки до 6 мм | D83: 1 ШТ. | E83: 64
C84: Объем: 64=20+15+29
C85: ЗП | F85: 14.98 | G85: 1,2 | H85: 1 | I85: 1150.46 | J85: 57.05 | K85: 65633.74
C86: МР | F86: 4.92 | H86: 1 | I86: 314.88 | J86: 6.84 | K86: 2153.78
A87: 10,1 | B87: 1.14-1-281 | C87: Разъем телевизионный F для коаксиального кабеля стандарта RG11 | D87: шт. | E87: 20 | F87: 30.69 | H87: 1 | I87: 613.8 | J87: 5.76 | K87: 3535.49
A88: 10,2 | B88: 1.14-1-280 | C88: Разъем телевизионный F для коаксиального кабеля стандарта RG6 | D88: шт. | E88: 15 | F88: 9.12 | H88: 1 | I88: 136.8 | J88: 2.74 | K88: 374.83
A89: 10,3 | B89: 1.14-1-219 | C89: Заглушка коаксиальной линии, номинальное волновое сопротивление 75 Ом, с емкостной развязкой, разъем типа F | D89: шт. | E89: 29 | F89: 15.9 | H89: 1 | I89: 461.1 | J89: 3.69 | K89: 1701.46
C90: НР от ФОТ | D90: % | E90: 90 | I90: 1035.41 | J90: 90 | K90: 59070.37
C91: СП от ФОТ | D91: % | E91: 46 | I91: 529.21 | J91: 46 | K91: 30191.52
C92: ЗТР | D92: чел-ч | E92: 1.03 | G92: 1,2 | H92: 1 | I92: 79.1
C93: ВСЕГО работ по позиции: | H93: 4241.66 | J93: 162661.19
C94: ВСЕГО по позиции: | H94: 4241.66 | J94: 162661.19
A96: 11 | B96: 4.8-333-7 Поправка: Гл.12.Прил.8.п.8. 3_12.00.01.11.001 | C96: Монтаж розетки штепсельной скрытого типа | D96: 100 шт. | E96: 0.02
C97: Объем: 0,02=2/100
C98: ЗП | F98: 210.57 | G98: 1,2 | H98: 1 | I98: 5.05 | J98: 57.05 | K98: 288.1
C99: ЭМ | F99: 0.83 | G99: 1,2 | H99: 1 | I99: 0.02 | J99: 17.47 | K99: 0.35
C100: НР от ФОТ | D100: % | E100: 97 | I100: 4.9 | J100: 97 | K100: 279.46
C101: СП от ФОТ | D101: % | E101: 51 | I101: 2.58 | J101: 51 | K101: 146.93
C102: ЗТР | D102: чел-ч | E102: 18.84 | G102: 1,2 | H102: 1 | I102: 0.45
C103: ВСЕГО работ по позиции: | H103: 12.55 | J103: 714.84
C104: ВСЕГО по позиции: | H104: 12.55 | J104: 714.84
A106: 12 | B106: Прайс-лист | C106: ТВ розетка, оконечная 1Дб 47,80 = [582 / 1,22 / 10,18] + 2% Заг.скл | D106: ШТ | E106: 2 | F106: 47.8 | H106: 1 | I106: 95.6 | J106: 10.18 | K106: 973.21
C107: ВСЕГО по позиции: | H107: 95.6 | J107: 973.21
A109: 13 | B109: Прайс-лист | C109: Коробка установочная 0,69 = [8,45 / 1,22 / 10,18] + 2% Заг.скл | D109: ШТ | E109: 1 | F109: 0.69 | H109: 1 | I109: 0.69 | J109: 10.18 | K109: 7.02
C110: ВСЕГО по позиции: | H110: 0.69 | J110: 7.02
A113: Итого по разделу: Монтажные работы | H113: 16329.75 | J113: 287139.4
A115: Раздел: Прокладка кабельных линий
A116: 14 | B116: 4.8-175-1 Поправка: Гл.12.Прил.8.п.8. 3_12.00.01.11.001 | C116: Затягивание провода в проложенные трубы и металлические рукава, первого одножильного или многожильного в общей оплетке, суммарное сечение до 2,5 мм2 | D116: 100 м | E116: 0.48
C117: Объем: 0,48=48/100
C118: ЗП | F118: 55.23 | G118: 1,2 | H118: 1 | I118: 31.81 | J118: 57.05 | K118: 1814.76
C119: ЭМ | F119: 2.62 | G119: 1,2 | H119: 1 | I119: 1.51 | J119: 15.96 | K119: 24.1
C120: в т.ч. ЗПМ | F120: 0.3 | G120: 1,2 | H120: 1 | I120: 0.17 | J120: 57.05 | K120: 9.7
C121: МР | F121: 58.15 | H121: 1 | I121: 27.91 | J121: 3.64 | K121: 101.59
...

Sheet ЛС 02-01-13
J2: Форма № 4б
A3: =ССРСС!A11 -> Выполнение работ по капитальному ремонту здания в Басманном районе ЦАО города Москвы
A4: (наименование стройки и/или объекта)
A6: ЛОКАЛЬНАЯ СМЕТА № 02-01-13
A8: Структурированная кабельная сеть
A9: (наименование работ и затрат)
I12: В базисном уровне цен | J12: В текущем уровне цен
E13: Сметная стоимость | I13: 398.57 | J13: 3916.82 | K13: тыс.руб.
E14: Строительные работы | I14: 34.13 | J14: 347.43 | K14: тыс.руб.
E15: Работы по монтажу оборудования | I15: 52.48 | J15: 1217.23 | K15: тыс.руб.
E16: Оборудование | I16: 311.96 | J16: 2352.16 | K16: тыс.руб.
E17: Средства на оплату труда | I17: 7.81 | J17: 445.71 | K17: тыс.руб.
E18: Затраты труда | I18: 632.84 | K18: чел.-ч.
A20: Составлен(а) по ТСН-2001 с учетом Дополнения №: 81
A21: № и период сборника коэффициентов (индексов) пересчета: Коэффициенты к ТСН-2001 МГЭ Дополнение 81, строительство №220 II квартал 2026 года и Коэффициенты к ТСН-2001.13-2 Дополнение 47 №65 II квартал 2026 года
A22: № п/п | B22: Шифр расценки и коды ресурсов | C22: Наименование работ и затрат | D22: Ед. изм. | E22: Кол-во единиц | F22: Цена на ед. изм., руб. | G22: Попра- вочные коэффи- циенты | H22: Коэффи- циенты зимних удорожа- ний | I22: Всего в ценах на январь 2000 года, руб. | J22: Коэффи- циенты (индек- сы) пере- счета, нормы НР и СП | K22: ВСЕГО затрат в текущем уровне цен, руб.
A23: 1 | B23: 2 | C23: 3 | D23: 4 | E23: 5 | F23: 6 | G23: 7 | H23: 8 | I23: 9 | J23: 10 | K23: 11
A24: Раздел: Оборудование
A25: 1 | B25: 4.10-32-1 Поправка: Гл.12.Прил.8.п.8. 3_12.00.01.11.001 | C25: Монтаж стойки, полустойки, каркаса стойки или шкафа массой до 100 кг | D25: 1 ШТ. | E25: 1
C26: ЗП | F26: 91.68 | G26: 1,2 | H26: 1 | I26: 110.02 | J26: 57.05 | K26: 6276.64
C27: ЭМ | F27: 38.92 | G27: 1,2 | H27: 1 | I27: 46.7 | J27: 16.34 | K27: 763.08
C28: в т.ч. ЗПМ | F28: 4.16 | G28: 1,2 | H28: 1 | I28: 4.99 | J28: 57.05 | K28: 284.68
C29: МР | F29: 3.92 | H29: 1 | I29: 3.92 | J29: 7.06 | K29: 27.68
C30: НР от ФОТ | D30: % | E30: 90 | I30: 103.51 | J30: 90 | K30: 5905.19
C31: СП от ФОТ | D31: % | E31: 46 | I31: 52.9 | J31: 46 | K31: 3018.21
C32: ЗТР | D32: чел-ч | E32: 8.2 | G32: 1,2 | H32: 1 | I32: 9.84
C33: ВСЕГО работ по позиции: | H33: 317.05 | J33: 15990.8
C34: ВСЕГО по позиции: | H34: 317.05 | J34: 15990.8
A36: 2 | B36: Прайс-лист | C36: ОБОРУДОВАНИЕ: Телекоммуникационный шкаф типоразмера 19", 42U шир.800мм, гл.800мм, 3 каб.ввода передняя дверь стеклянная,задняя дв.перфорированные,1-створчатые, боковые панели,шнуры заземления,ножки-4поворотных колеса,белый 20 560,41 = [181 445 / 1,22 / 7,54] + 3% Трансп + 1,2% Заг.скл | D36: ШТ | E36: 1 | F36: 20560.41 | H36: 1 | I36: 20560.41 | J36: 7.54 | K36: 155025.49
C37: ВСЕГО по позиции: | H37: 20560.41 | J37: 155025.49
A39: 3 | B39: 4.10-1-13 Поправка: Гл.12.Прил.8.п.8. 3_12.00.01.11.001 | C39: Установка рамки со штифтами на винтах и гайках с шайбами | D39: 1 рамка | E39: 1
C40: ЗП | F40: 1.45 | G40: 1,2 | H40: 1 | I40: 1.74 | J40: 57.05 | K40: 99.27
C41: НР от ФОТ | D41: % | E41: 90 | I41: 1.57 | J41: 90 | K41: 89.34
C42: СП от ФОТ | D42: % | E42: 46 | I42: 0.8 | J42: 46 | K42: 45.66
C43: ЗТР | D43: чел-ч | E43: 0.13 | G43: 1,2 | H43: 1 | I43: 0.16
C44: ВСЕГО работ по позиции: | H44: 4.11 | J44: 234.27
C45: ВСЕГО по позиции: | H45: 4.11 | J45: 234.27
A47: 4 | B47: Прайс-лист | C47: ОБОРУДОВАНИЕ: Вертикальный органайзер с крышкой , 2шт 4 839,73 = [42 710,46 / 1,22 / 7,54] + 3% Трансп + 1,2% Заг.скл | D47: КОМПЛ | E47: 1 | F47: 4839.73 | H47: 1 | I47: 4839.73 | J47: 7.54 | K47: 36491.56
C48: ВСЕГО по позиции: | H48: 4839.73 | J48: 36491.56
A50: 5 | B50: Прайс-лист | C50: ОБОРУДОВАНИЕ: Шина заземления 19" (500мм), 20 точек,5х15мм 494,16 = [4 361 / 1,22 / 7,54] + 3% Трансп + 1,2% Заг.скл | D50: ШТ | E50: 1 | F50: 494.16 | H50: 1 | I50: 494.16 | J50: 7.54 | K50: 3725.97
C51: ВСЕГО по позиции: | H51: 494.16 | J51: 3725.97
A53: 6 | B53: Прайс-лист | C53: ОБОРУДОВАНИЕ: Набор проводов заземления, 4 провода 250мм х4мм2, 4 провода 150мм х4мм2 93,43 = [824,5 / 1,22 / 7,54] + 3% Трансп + 1,2% Заг.скл | D53: КОМПЛ | E53: 1 | F53: 93.43 | H53: 1 | I53: 93.43 | J53: 7.54 | K53: 704.46
C54: ВСЕГО по позиции: | H54: 93.43 | J54: 704.46
A56: 7 | B56: 4.11-12-1 Поправка: Гл.12.Прил.8.п.8. 3_12.00.01.11.001 | C56: Установка съемных и выдвижных блоков (модулей, ячеек, ТЭЗ) массой до 5 кг | D56: 1 ШТ. | E56: 1
C57: ЗП | F57: 11.65 | G57: 1,2 | H57: 1 | I57: 13.98 | J57: 57.05 | K57: 797.56
C58: ЭМ | F58: 0.5 | G58: 1,2 | H58: 1 | I58: 0.6 | J58: 17.4 | K58: 10.44
C59: в т.ч. ЗПМ | F59: 0.08 | G59: 1,2 | H59: 1 | I59: 0.1 | J59: 57.05 | K59: 5.71
C60: НР от ФОТ | D60: % | E60: 90 | I60: 12.67 | J60: 90 | K60: 722.94
C61: СП от ФОТ | D61: % | E61: 46 | I61: 6.48 | J61: 46 | K61: 369.5
C62: ЗТР | D62: чел-ч | E62: 1.03 | G62: 1,2 | H62: 1 | I62: 1.24
C63: ВСЕГО работ по позиции: | H63: 33.73 | J63: 1900.44
C64: ВСЕГО по позиции: | H64: 33.73 | J64: 1900.44
A66: 8 | B66: Прайс-лист | C66: ОБОРУДОВАНИЕ: Вентиляторная панель 19" 1U, 6 вентиляторов, с контроллером 1 879,15 = [16 583,5 / 1,22 / 7,54] + 3% Трансп + 1,2% Заг.скл | D66: ШТ | E66: 1 | F66: 1879.15 | H66: 1 | I66: 1879.15 | J66: 7.54 | K66: 14168.79
C67: ВСЕГО по позиции: | H67: 1879.15 | J67: 14168.79
A69: 9 | B69: Прайс-лист | C69: Шнур питания для вент .панели с разъемом питания через УЗО 17,25 = [210 / 1,22 / 10,18] + 2% Заг.скл | D69: ШТ | E69: 1 | F69: 17.25 | H69: 1 | I69: 17.25 | J69: 10.18 | K69: 175.61
C70: ВСЕГО по позиции: | H70: 17.25 | J70: 175.61
A72: 10 | B72: Прайс-лист | C72: Выдвижная полка для клавиатуры, 450мм 538,26 = [6 554 / 1,22 / 10,18] + 2% Заг.скл | D72: ШТ | E72: 1 | F72: 538.26 | H72: 1 | I72: 538.26 | J72: 10.18 | K72: 5479.49
C73: ВСЕГО по позиции: | H73: 538.26 | J73: 5479.49
A75: 11 | B75: 4.10-1-12 Поправка: Гл.12.Прил.8.п.8. 3_12.00.01.11.001 | C75: Установка рамки со штифтами на винтах в нарезных отверстиях | D75: 1 рамка | E75: 1
C76: ЗП | F76: 0.78 | G76: 1,2 | H76: 1 | I76: 0.94 | J76: 57.05 | K76: 53.63
C77: НР от ФОТ | D77: % | E77: 90 | I77: 0.85 | J77: 90 | K77: 48.27
C78: СП от ФОТ | D78: % | E78: 46 | I78: 0.43 | J78: 46 | K78: 24.67
C79: ЗТР | D79: чел-ч | E79: 0.07 | G79: 1,2 | H79: 1 | I79: 0.08
C80: ВСЕГО работ по позиции: | H80: 2.22 | J80: 126.57
C81: ВСЕГО по позиции: | H81: 2.22 | J81: 126.57
A83: 12 | B83: Прайс-лист | C83: Полка стационарная регулируемая 1U до 50кг,370мм, для 600мм 315,68 = [3 843,7 / 1,22 / 10,18] + 2% Заг.скл | D83: ШТ | E83: 1 | F83: 315.68 | H83: 1 | I83: 315.68 | J83: 10.18 | K83: 3213.62
C84: ВСЕГО по позиции: | H84: 315.68 | J84: 3213.62
A86: 13 | B86: Прайс-лист | C86: Набор для крепления лотков к крышке шкафов, высота 50мм 156,05 = [1 900,09 / 1,22 / 10,18] + 2% Заг.скл | D86: ШТ | E86: 1 | F86: 156.05 | H86: 1 | I86: 156.05 | J86: 10.18 | K86: 1588.59
C87: ВСЕГО по позиции: | H87: 156.05 | J87: 1588.59
A89: 14 | B89: 4.8-323-2 Поправка: Гл.12.Прил.8.п.8. 3_12.00.01.11.001 | C89: Установка светильников светодиодных накладных линейных длиной до 3 м, устанавливаемых внутри здания | D89: 100 шт. | E89: 0.01
C90: Объем: 0,01=1/100
C91: ЗП | F91: 1106.26 | G91: 1,2 | H91: 1 | I91: 13.28 | J91: 57.05 | K91: 757.62
C92: ЭМ | F92: 52.1 | G92: 1,2 | H92: 1 | I92: 0.63 | J92: 16.9 | K92: 10.65
C93: в т.ч. ЗПМ | F93: 7.07 | G93: 1,2 | H93: 1 | I93: 0.08 | J93: 57.05 | K93: 4.56
C94: МР | F94: 109.58 | H94: 1 | I94: 1.1 | J94: 3.05 | K94: 3.36
C95: НР от ФОТ | D95: % | E95: 97 | I95: 12.96 | J95: 97 | K95: 739.31
C96: СП от ФОТ | D96: % | E96: 51 | I96: 6.81 | J96: 51 | K96: 388.71
C97: ЗТР | D97: чел-ч | E97: 84.74 | G97: 1,2 | H97: 1 | I97: 1.02
C98: ВСЕГО работ по позиции: | H98: 34.78 | J98: 1899.65
C99: ВСЕГО по позиции: | H99: 34.78 | J99: 1899.65
A101: 15 | B101: Прайс-лист | C101: ОБОРУДОВАНИЕ: Панель освещения на магнитах, универсальная цвет белый 965,96 = [8 524,65 / 1,22 / 7,54] + 3% Трансп + 1,2% Заг.скл | D101: ШТ | E101: 1 | F101: 965.96 | H101: 1 | I101: 965.96 | J101: 7.54 | K101: 7283.34
C102: ВСЕГО по позиции: | H102: 965.96 | J102: 7283.34
A105: Итого по разделу: Оборудование | H105: 30251.97 | J105: 248008.65
A107: Раздел: Источники электропитания
A108: 16 | B108: 4.10-173-2 Поправка: Гл.12.Прил.8.п.8. 3_12.00.01.11.001 | C108: Монтаж блока бесперебойного питания (ББП) в диспетчерской | D108: 1 ШТ. | E108: 1
C109: ЗП | F109: 40.17 | G109: 1,2 | H109: 1 | I109: 48.2 | J109: 57.05 | K109: 2749.81
C110: МР | F110: 2.34 | H110: 1 | I110: 2.34 | J110: 9.91 | K110: 23.19
C111: НР от ФОТ | D111: % | E111: 90 | I111: 43.38 | J111: 90 | K111: 2474.83
C112: СП от ФОТ | D112: % | E112: 46 | I112: 22.17 | J112: 46 | K112: 1264.91
C113: ЗТР | D113: чел-ч | E113: 3.18 | G113: 1,2 | H113: 1 | I113: 3.82
C114: ВСЕГО работ по позиции: | H114: 116.09 | J114: 6512.74
C115: ВСЕГО по позиции: | H115: 116.09 | J115: 6512.74
A117: 17 | B117: Прайс-лист | C117: ОБОРУДОВАНИЕ: Источник бесперебойного питания 5000VA/3500W, 230В, 8 выходов, 2U 9A/ч в комплекте диск с ПО, крепление для установки в 19"стойку встроенная панель с клеммной колодкой для подключения эл.кабеля 7 832,09 = [69 118 / 1,22 / 7,54] + 3% Трансп + 1,2% Заг.скл | D117: КОМПЛ | E117: 1 | F117: 7832.09 | H117: 1 | I117: 7832.09 | J117: 7.54 | K117: 59053.96
C118: ВСЕГО по позиции: | H118: 7832.09 | J118: 59053.96
A120: 18 | B120: Прайс-лист | C120: ОБОРУДОВАНИЕ: Батарейный блок 3 798,73 = [33 523,78 / 1,22 / 7,54] + 3% Трансп + 1,2% Заг.скл | D120: КОМПЛ | E120: 1 | F120: 3798.73 | H120: 1 | I120: 3798.73 | J120: 7.54 | K120: 28642.42
C121: ВСЕГО по позиции: | H121: 3798.73 | J121: 28642.42
A123: 19 | B123: 4.8-335-6 Поправка: Гл.12.Прил.8.п.8. 3_12.00.01.11.001 | C123: Монтаж розетки штепсельной накладного типа | D123: 100 шт. | E123: 0.02
C124: Объем: 0,02=2/100
C125: ЗП | F125: 257.88 | G125: 1,2 | H125: 1 | I125: 6.19 | J125: 57.05 | K125: 353.14
C126: ЭМ | F126: 2.31 | G126: 1,2 | H126: 1 | I126: 0.06 | J126: 11.29 | K126: 0.68
...

Sheet ЛС 02-01-14
J2: Форма № 4б
A3: =ССРСС!A11 -> Выполнение работ по капитальному ремонту здания в Басманном районе ЦАО города Москвы
A4: (наименование стройки и/или объекта)
A6: ЛОКАЛЬНАЯ СМЕТА № 02-01-14
A8: Система охранного теленаблюдения
A9: (наименование работ и затрат)
I12: В базисном уровне цен | J12: В текущем уровне цен
E13: Сметная стоимость | I13: 116.6 | J13: 1565.76 | K13: тыс.руб.
E14: Строительные работы | I14: 12.38 | J14: 126.04 | K14: тыс.руб.
E15: Работы по монтажу оборудования | I15: 28.89 | J15: 872.27 | K15: тыс.руб.
E16: Оборудование | I16: 75.33 | J16: 567.45 | K16: тыс.руб.
E17: Средства на оплату труда | I17: 5.68 | J17: 324.17 | K17: тыс.руб.
E18: Затраты труда | I18: 456.19 | K18: чел.-ч.
A20: Составлен(а) по ТСН-2001 с учетом Дополнения №: 81
A21: № и период сборника коэффициентов (индексов) пересчета: Коэффициенты к ТСН-2001 МГЭ Дополнение 81, строительство №220 II квартал 2026 года и Коэффициенты к ТСН-2001.13-2 Дополнение 47 №65 II квартал 2026 года
A22: № п/п | B22: Шифр расценки и коды ресурсов | C22: Наименование работ и затрат | D22: Ед. изм. | E22: Кол-во единиц | F22: Цена на ед. изм., руб. | G22: Попра- вочные коэффи- циенты | H22: Коэффи- циенты зимних удорожа- ний | I22: Всего в ценах на январь 2000 года, руб. | J22: Коэффи- циенты (индек- сы) пере- счета, нормы НР и СП | K22: ВСЕГО затрат в текущем уровне цен, руб.
A23: 1 | B23: 2 | C23: 3 | D23: 4 | E23: 5 | F23: 6 | G23: 7 | H23: 8 | I23: 9 | J23: 10 | K23: 11
A24: Раздел: Оборудование
A25: 1 | B25: 4.10-174-2 Поправка: Гл.12.Прил.8.п.8. 3_12.00.01.11.001 | C25: Монтаж наружной камеры видеонаблюдения | D25: 10 шт. | E25: 0.5
C26: Объем: 0,5=5/10
C27: ЗП | F27: 401.27 | G27: 1,2 | H27: 1 | I27: 240.76 | J27: 57.05 | K27: 13735.36
C28: ЭМ | F28: 2.36 | G28: 1,2 | H28: 1 | I28: 1.42 | J28: 11.47 | K28: 16.29
C29: в т.ч. ЗПМ | F29: 0.13 | G29: 1,2 | H29: 1 | I29: 0.08 | J29: 57.05 | K29: 4.56
C30: МР | F30: 42.51 | H30: 1 | I30: 21.26 | J30: 1.84 | K30: 39.12
C31: НР от ФОТ | D31: % | E31: 90 | I31: 216.76 | J31: 90 | K31: 12365.93
C32: СП от ФОТ | D32: % | E32: 46 | I32: 110.79 | J32: 46 | K32: 6320.36
C33: ЗТР | D33: чел-ч | E33: 25.33 | G33: 1,2 | H33: 1 | I33: 15.2
C34: ВСЕГО работ по позиции: | H34: 590.99 | J34: 32477.06
C35: ВСЕГО по позиции: | H35: 590.99 | J35: 32477.06
A37: 2 | B37: Прайс-лист | C37: ОБОРУДОВАНИЕ: Цилиндрическая IP-видеокамера с фиксированным объективом IP 4 Мп; размер матрицы 1/2.9"; встроенный микрофон; Дальность ИК подсветки 80м; режим "день/ночь"; PoE 7 Вт; -40 ~ +60°C, (2/8-12) 1 236,60 = [10 913 / 1,22 / 7,54] + 3% Трансп + 1,2% Заг.скл | D37: ШТ | E37: 5 | F37: 1236.6 | H37: 1 | I37: 6183 | J37: 7.54 | K37: 46619.82
C38: ВСЕГО по позиции: | H38: 6183 | J38: 46619.82
A40: 3 | B40: 4.10-136-1 Поправка: Гл.12.Прил.8.п.8. 3_12.00.01.11.001 | C40: Монтаж коробки телевизионной (ответвители, разветвители магистральные, домовые, абонентские), УСС, БФТК | D40: 1 ШТ. | E40: 5
C41: ЗП | F41: 11.02 | G41: 1,2 | H41: 1 | I41: 66.12 | J41: 57.05 | K41: 3772.15
C42: МР | F42: 0.3 | H42: 1 | I42: 1.5 | J42: 7.37 | K42: 11.06
C43: НР от ФОТ | D43: % | E43: 95 | I43: 62.81 | J43: 95 | K43: 3583.54
C44: СП от ФОТ | D44: % | E44: 53 | I44: 35.04 | J44: 53 | K44: 1999.24
C45: ЗТР | D45: чел-ч | E45: 0.8 | G45: 1,2 | H45: 1 | I45: 4.8
C46: ВСЕГО работ по позиции: | H46: 165.47 | J46: 9365.99
C47: ВСЕГО по позиции: | H47: 165.47 | J47: 9365.99
A49: 4 | B49: Прайс-лист | C49: ОБОРУДОВАНИЕ: Устройство грозозащиты 326,34 = [2 880 / 1,22 / 7,54] + 3% Трансп + 1,2% Заг.скл | D49: ШТ | E49: 5 | F49: 326.34 | H49: 1 | I49: 1631.7 | J49: 7.54 | K49: 12303.02
C50: ВСЕГО по позиции: | H50: 1631.7 | J50: 12303.02
A52: 5 | B52: 4.10-174-1 Поправка: Гл.12.Прил.8.п.8. 3_12.00.01.11.001 | C52: Монтаж внутренней камеры видеонаблюдения | D52: 10 шт. | E52: 1.7
C53: Объем: 1,7=17/10
C54: ЗП | F54: 247.42 | G54: 1,2 | H54: 1 | I54: 504.74 | J54: 57.05 | K54: 28795.42
C55: ЭМ | F55: 2.36 | G55: 1,2 | H55: 1 | I55: 4.81 | J55: 11.47 | K55: 55.17
C56: в т.ч. ЗПМ | F56: 0.13 | G56: 1,2 | H56: 1 | I56: 0.27 | J56: 57.05 | K56: 15.4
C57: МР | F57: 42.51 | H57: 1 | I57: 72.27 | J57: 1.84 | K57: 132.98
C58: НР от ФОТ | D58: % | E58: 90 | I58: 454.51 | J58: 90 | K58: 25929.74
C59: СП от ФОТ | D59: % | E59: 46 | I59: 232.3 | J59: 46 | K59: 13252.98
C60: ЗТР | D60: чел-ч | E60: 15.54 | G60: 1,2 | H60: 1 | I60: 31.7
C61: ВСЕГО работ по позиции: | H61: 1268.63 | J61: 68166.29
C62: ВСЕГО по позиции: | H62: 1268.63 | J62: 68166.29
A64: 6 | B64: Прайс-лист | C64: ОБОРУДОВАНИЕ: IP-видеокамера купольная 4Мп с фиксированным объективом 2,8мм 1 585,28 = [13 990 / 1,22 / 7,54] + 3% Трансп + 1,2% Заг.скл | D64: ШТ | E64: 17 | F64: 1585.28 | H64: 1 | I64: 26949.76 | J64: 7.54 | K64: 203201.19
C65: ВСЕГО по позиции: | H65: 26949.76 | J65: 203201.19
A67: 7 | B67: 4.10-72-14 Поправка: Гл.12.Прил.8.п.8. 3_12.00.01.11.001 | C67: Монтаж устройства цифровой регистрации | D67: 1 устройство | E67: 1
C68: ЗП | F68: 95.12 | G68: 1,2 | H68: 1 | I68: 114.14 | J68: 57.05 | K68: 6511.69
C69: МР | F69: 1.1 | H69: 1 | I69: 1.1 | J69: 14.2 | K69: 15.62
C70: НР от ФОТ | D70: % | E70: 95 | I70: 108.43 | J70: 95 | K70: 6186.11
C71: СП от ФОТ | D71: % | E71: 53 | I71: 60.49 | J71: 53 | K71: 3451.2
C72: ЗТР | D72: чел-ч | E72: 8 | G72: 1,2 | H72: 1 | I72: 9.6
C73: ВСЕГО работ по позиции: | H73: 284.16 | J73: 16164.62
C74: ВСЕГО по позиции: | H74: 284.16 | J74: 16164.62
A76: 8 | B76: Прайс-лист | C76: ОБОРУДОВАНИЕ: Видеорегистратор до 32 IP-видеокамер 2 275,93 = [20 085 / 1,22 / 7,54] + 3% Трансп + 1,2% Заг.скл | D76: ШТ | E76: 1 | F76: 2275.93 | H76: 1 | I76: 2275.93 | J76: 7.54 | K76: 17160.51
C77: ВСЕГО по позиции: | H77: 2275.93 | J77: 17160.51
A79: 9 | B79: 4.10-34-5 Поправка: Гл.12.Прил.8.п.8. 3_12.00.01.11.001 | C79: Монтаж коммутатора служебной связи | D79: 1 ШТ. | E79: 1
C80: ЗП | F80: 78.24 | G80: 1,2 | H80: 1 | I80: 93.89 | J80: 57.05 | K80: 5356.42
C81: ЭМ | F81: 28.71 | G81: 1,2 | H81: 1 | I81: 34.45 | J81: 16.51 | K81: 568.77
C82: в т.ч. ЗПМ | F82: 3.16 | G82: 1,2 | H82: 1 | I82: 3.79 | J82: 57.05 | K82: 216.22
C83: МР | F83: 12.35 | H83: 1 | I83: 12.35 | J83: 14.64 | K83: 180.8
C84: НР от ФОТ | D84: % | E84: 90 | I84: 87.91 | J84: 90 | K84: 5015.38
C85: СП от ФОТ | D85: % | E85: 46 | I85: 44.93 | J85: 46 | K85: 2563.41
C86: ЗТР | D86: чел-ч | E86: 6.2 | G86: 1,2 | H86: 1 | I86: 7.44
C87: ВСЕГО работ по позиции: | H87: 273.53 | J87: 13684.78
C88: ВСЕГО по позиции: | H88: 273.53 | J88: 13684.78
A90: 10 | B90: Прайс-лист | C90: ОБОРУДОВАНИЕ: Коммутатор сетевой 4 798,88 = [42 350 / 1,22 / 7,54] + 3% Трансп + 1,2% Заг.скл | D90: ШТ | E90: 1 | F90: 4798.88 | H90: 1 | I90: 4798.88 | J90: 7.54 | K90: 36183.56
C91: ВСЕГО по позиции: | H91: 4798.88 | J91: 36183.56
A93: 11 | B93: 4.10-32-4 Поправка: Гл.12.Прил.8.п.8. 3_12.00.01.11.001 | C93: Монтаж платы дополнительной, устанавливаемой на готовом месте стойки | D93: 1 ШТ. | E93: 2
C94: Объем: 2=1+1
C95: ЗП | F95: 23.48 | G95: 1,2 | H95: 1 | I95: 56.35 | J95: 57.05 | K95: 3214.77
C96: ЭМ | F96: 9.19 | G96: 1,2 | H96: 1 | I96: 22.06 | J96: 16.5 | K96: 363.99
C97: в т.ч. ЗПМ | F97: 1.01 | G97: 1,2 | H97: 1 | I97: 2.42 | J97: 57.05 | K97: 138.06
C98: НР от ФОТ | D98: % | E98: 90 | I98: 52.89 | J98: 90 | K98: 3017.55
C99: СП от ФОТ | D99: % | E99: 46 | I99: 27.03 | J99: 46 | K99: 1542.3
C100: ЗТР | D100: чел-ч | E100: 2.1 | G100: 1,2 | H100: 1 | I100: 5.04
C101: ВСЕГО работ по позиции: | H101: 158.33 | J101: 8138.61
C102: ВСЕГО по позиции: | H102: 158.33 | J102: 8138.61
A104: 12 | B104: Прайс-лист | C104: ОБОРУДОВАНИЕ: Модуль защиты 220,86 = [1 949 / 1,22 / 7,54] + 3% Трансп + 1,2% Заг.скл | D104: ШТ | E104: 1 | F104: 220.86 | H104: 1 | I104: 220.86 | J104: 7.54 | K104: 1665.28
C105: ВСЕГО по позиции: | H105: 220.86 | J105: 1665.28
A107: 13 | B107: Прайс-лист | C107: ОБОРУДОВАНИЕ: Универсальный корпус 19" 363,07 = [3 204 / 1,22 / 7,54] + 3% Трансп + 1,2% Заг.скл | D107: ШТ | E107: 1 | F107: 363.07 | H107: 1 | I107: 363.07 | J107: 7.54 | K107: 2737.55
C108: ВСЕГО по позиции: | H108: 363.07 | J108: 2737.55
A110: 14 | B110: 4.11-7-1 Поправка: Гл.12.Прил.8.п.8. 3_12.00.01.11.001 | C110: Установка аппарата настольного массой до 0,015 т | D110: 1 ШТ. | E110: 1
C111: ЗП | F111: 11.52 | G111: 1,2 | H111: 1 | I111: 13.82 | J111: 57.05 | K111: 788.43
C112: ЭМ | F112: 13.3 | G112: 1,2 | H112: 1 | I112: 15.96 | J112: 17.45 | K112: 278.5
C113: в т.ч. ЗПМ | F113: 2.02 | G113: 1,2 | H113: 1 | I113: 2.42 | J113: 57.05 | K113: 138.06
C114: НР от ФОТ | D114: % | E114: 90 | I114: 14.62 | J114: 90 | K114: 833.84
C115: СП от ФОТ | D115: % | E115: 46 | I115: 7.47 | J115: 46 | K115: 426.19
C116: ЗТР | D116: чел-ч | E116: 1.03 | G116: 1,2 | H116: 1 | I116: 1.24
C117: ВСЕГО работ по позиции: | H117: 51.87 | J117: 2326.96
C118: ВСЕГО по позиции: | H118: 51.87 | J118: 2326.96
A120: 15 | B120: Прайс-лист | C120: ОБОРУДОВАНИЕ: Автоматизированное рабочее место, моноблок 16 661,80 = [147 040 / 1,22 / 7,54] + 3% Трансп + 1,2% Заг.скл | D120: ШТ | E120: 1 | F120: 16661.8 | H120: 1 | I120: 16661.8 | J120: 7.54 | K120: 125629.97
...

Sheet ЛС 02-01-15
A1: Smeta.RU (495) 974-1589
J2: Форма № 4б
A3: =ССРСС!A11 -> Выполнение работ по капитальному ремонту здания в Басманном районе ЦАО города Москвы
A4: (наименование стройки и/или объекта)
A6: ЛОКАЛЬНАЯ СМЕТА № 02-01-15
A8: Система контроля и управления доступом
A9: (наименование работ и затрат)
I12: В базисном уровне цен | J12: В текущем уровне цен
E13: Сметная стоимость | I13: 618.22 | J13: 4232.3 | K13: тыс.руб.
E14: Строительные работы | I14: 3.74 | J14: 37.84 | K14: тыс.руб.
E15: Работы по монтажу оборудования | I15: 412.08 | J15: 2662.88 | K15: тыс.руб.
E16: Оборудование | I16: 202.4 | J16: 1531.58 | K16: тыс.руб.
E17: Средства на оплату труда | I17: 8.35 | J17: 476.62 | K17: тыс.руб.
E18: Затраты труда | I18: 633.61 | K18: чел.-ч.
A20: Составлен(а) по ТСН-2001 с учетом Дополнения №: 81
A21: № и период сборника коэффициентов (индексов) пересчета: Коэффициенты к ТСН-2001 МГЭ Дополнение 81, строительство №220 II квартал 2026 года и Коэффициенты к ТСН-2001.13-2 Дополнение 47 №65 II квартал 2026 года
A22: № п/п | B22: Шифр расценки и коды ресурсов | C22: Наименование работ и затрат | D22: Ед. изм. | E22: Кол-во единиц | F22: Цена на ед. изм., руб. | G22: Попра- вочные коэффи- циенты | H22: Коэффи- циенты зимних удорожа- ний | I22: Всего в ценах на январь 2000 года, руб. | J22: Коэффи- циенты (индек- сы) пере- счета, нормы НР и СП | K22: ВСЕГО затрат в текущем уровне цен, руб.
A23: 1 | B23: 2 | C23: 3 | D23: 4 | E23: 5 | F23: 6 | G23: 7 | H23: 8 | I23: 9 | J23: 10 | K23: 11
A24: Раздел: Оборудование
A25: 1 | B25: 4.10-176-1 Поправка: Гл.12.Прил.8.п.8. 3_12.00.01.11.001 | C25: Монтаж блока контроля датчиков (контроллер) | D25: 10 шт. | E25: 0.7
C26: Объем: 0,7=7/10
C27: ЗП | F27: 470.94 | G27: 1,2 | H27: 1 | I27: 395.59 | J27: 57.05 | K27: 22568.41
C28: ЭМ | F28: 1.1 | G28: 1,2 | H28: 1 | I28: 0.92 | J28: 16.77 | K28: 15.43
C29: в т.ч. ЗПМ | F29: 0.13 | G29: 1,2 | H29: 1 | I29: 0.11 | J29: 57.05 | K29: 6.28
C30: МР | F30: 1.29 | H30: 1 | I30: 0.9 | J30: 7.62 | K30: 6.86
C31: НР от ФОТ | D31: % | E31: 90 | I31: 356.13 | J31: 90 | K31: 20317.22
C32: СП от ФОТ | D32: % | E32: 46 | I32: 182.02 | J32: 46 | K32: 10384.36
C33: ЗТР | D33: чел-ч | E33: 29.96 | G33: 1,2 | H33: 1 | I33: 25.17
C34: ВСЕГО работ по позиции: | H34: 935.56 | J34: 53292.28
C35: ВСЕГО по позиции: | H35: 935.56 | J35: 53292.28
A37: 2 | B37: Прайс-лист | C37: ОБОРУДОВАНИЕ: Сетевой контроллер доступа до 8 точек, встроенное ПО 7 308,80 = [64 500 / 1,22 / 7,54] + 3% Трансп + 1,2% Заг.скл | D37: ШТ | E37: 7 | F37: 7308.8 | H37: 1 | I37: 51161.6 | J37: 7.54 | K37: 385758.46
C38: ВСЕГО по позиции: | H38: 51161.6 | J38: 385758.46
A40: 3 | B40: 4.10-80-9 Поправка: Гл.12.Прил.8.п.8. 3_12.00.01.11.001 | C40: Аппараты приемные, приборы приемно-контрольные объектовые на 2 луча | D40: 1 ШТ. | E40: 23
C41: ЗП | F41: 77.35 | G41: 1,2 | H41: 1 | I41: 2134.86 | J41: 57.05 | K41: 121793.76
C42: ЭМ | F42: 0.05 | G42: 1,2 | H42: 1 | I42: 1.38 | J42: 20.4 | K42: 28.15
C43: в т.ч. ЗПМ | F43: 0.01 | G43: 1,2 | H43: 1 | I43: 0.28 | J43: 57.05 | K43: 15.97
C44: МР | F44: 4.83 | H44: 1 | I44: 111.09 | J44: 10.18 | K44: 1130.9
C45: НР от ФОТ | D45: % | E45: 90 | I45: 1921.63 | J45: 90 | K45: 109628.76
C46: СП от ФОТ | D46: % | E46: 46 | I46: 982.16 | J46: 46 | K46: 56032.48
C47: ЗТР | D47: чел-ч | E47: 5.7 | G47: 1,2 | H47: 1 | I47: 157.32
C48: ВСЕГО работ по позиции: | H48: 5151.12 | J48: 288614.05
C49: ВСЕГО по позиции: | H49: 5151.12 | J49: 288614.05
A51: 4 | B51: Прайс-лист | C51: ОБОРУДОВАНИЕ: Модуль доступа-контроллер доступа на 2 точки прохода, встроенный источник питания и место под АБК 1 801,70 = [15 900 / 1,22 / 7,54] + 3% Трансп + 1,2% Заг.скл | D51: ШТ | E51: 23 | F51: 1801.7 | H51: 1 | I51: 41439.1 | J51: 7.54 | K51: 312450.81
C52: ВСЕГО по позиции: | H52: 41439.1 | J52: 312450.81
A54: 5 | B54: 4.11-16-1 Поправка: Гл.12.Прил.8.п.8. 3_12.00.01.11.001 | C54: Монтаж механизма исполнительного массой до 20 кг | D54: 1 ШТ. | E54: 23
C55: ЗП | F55: 5.81 | G55: 1,2 | H55: 1 | I55: 160.36 | J55: 57.05 | K55: 9148.54
C56: ЭМ | F56: 28.19 | G56: 1,2 | H56: 1 | I56: 778.04 | J56: 15.9 | K56: 12370.84
C57: в т.ч. ЗПМ | F57: 3.16 | G57: 1,2 | H57: 1 | I57: 87.22 | J57: 57.05 | K57: 4975.9
C58: НР от ФОТ | D58: % | E58: 90 | I58: 222.82 | J58: 90 | K58: 12712
C59: СП от ФОТ | D59: % | E59: 46 | I59: 113.89 | J59: 46 | K59: 6497.24
C60: ЗТР | D60: чел-ч | E60: 0.52 | G60: 1,2 | H60: 1 | I60: 14.35
C61: ВСЕГО работ по позиции: | H61: 1275.11 | J61: 40728.62
C62: ВСЕГО по позиции: | H62: 1275.11 | J62: 40728.62
A64: 6 | B64: Прайс-лист | C64: ОБОРУДОВАНИЕ: Электромагнитный замок с монтажным комплектом 1 846,47 = [16 295,1 / 1,22 / 7,54] + 3% Трансп + 1,2% Заг.скл | D64: КОМПЛ | E64: 23 | F64: 1846.47 | H64: 1 | I64: 42468.81 | J64: 7.54 | K64: 320214.83
C65: ВСЕГО по позиции: | H65: 42468.81 | J65: 320214.83
A67: 7 | B67: 4.10-81-4 Поправка: Гл.12.Прил.8.п.8. 3_12.00.01.11.001 | C67: Извещатели ОС автоматические, контактный, магнито-контактный на открывание окон, дверей | D67: 1 ШТ. | E67: 24
C68: Объем: 24=2+22
C69: ЗП | F69: 10.6 | G69: 1,2 | H69: 1 | I69: 305.28 | J69: 57.05 | K69: 17416.22
C70: МР | F70: 1.05 | H70: 1 | I70: 25.2 | J70: 10.18 | K70: 256.54
A71: 7,1 | B71: 13.1-2-598 | C71: ОБОРУДОВАНИЕ: Извещатель охранный точечный, магнитоконтактный, накладной. В составе: датчик магнитоуправляемый на основе геркона и магнит, расстояние между герконом и магнитом при размыкании контактов - 70 мм и более, при замыкании - 25 мм и менее, материал корпусов пластик, степень защиты IP55, диапазон рабочих температур от -50 до +50°С, габаритные размеры корпусов 130х30х20 мм, кабель 2х0,2 длина 0,35 м | D71: шт. | E71: 2 | F71: 34.13 | H71: 1 | I71: 68.26 | J71: 10.59 | K71: 722.87
A72: 7,2 | B72: 13.1-2-599 | C72: ОБОРУДОВАНИЕ: Извещатель охранный точечный, магнитоконтактный, накладной для немагнитных конструкций. В составе: датчик магнитоуправляемый на основе геркона и магнит, расстояние между герконом и магнитом при размыкании контактов - 45 мм и более, при замыкании - 10 мм и менее, степень защиты IP44, диапазон рабочих температур от -50 до +50°С, габаритные размеры корпусов 58х11х11,6 мм | D72: шт. | E72: 22 | F72: 10.94 | H72: 1 | I72: 240.68 | J72: 8.9 | K72: 2142.05
C73: НР от ФОТ | D73: % | E73: 90 | I73: 274.75 | J73: 90 | K73: 15674.6
C74: СП от ФОТ | D74: % | E74: 46 | I74: 140.43 | J74: 46 | K74: 8011.46
C75: ЗТР | D75: чел-ч | E75: 0.84 | G75: 1,2 | H75: 1 | I75: 24.19
C76: ВСЕГО работ по позиции: | H76: 745.66 | J76: 41358.82
C77: ВСЕГО оборудование по позиции: | H77: 308.94 | J77: 2864.92
C78: ВСЕГО по позиции: | H78: 1054.6 | J78: 44223.74
A80: 8 | B80: 4.10-168-1 Поправка: Гл.12.Прил.8.п.8. 3_12.00.01.11.001 | C80: Монтаж блока считывания кода (БСК) и считыватель в диспетчерской | D80: 1 ШТ. | E80: 26
C81: ЗП | F81: 59.08 | G81: 1,2 | H81: 1 | I81: 1843.3 | J81: 57.05 | K81: 105160.27
C82: ЭМ | F82: 1.65 | G82: 1,2 | H82: 1 | I82: 51.48 | J82: 10.76 | K82: 553.92
C83: МР | F83: 14.92 | H83: 1 | I83: 387.92 | J83: 4.3 | K83: 1668.06
C84: НР от ФОТ | D84: % | E84: 90 | I84: 1658.97 | J84: 90 | K84: 94644.24
C85: СП от ФОТ | D85: % | E85: 46 | I85: 847.92 | J85: 46 | K85: 48373.72
C86: ЗТР | D86: чел-ч | E86: 4.68 | G86: 1,2 | H86: 1 | I86: 146.02
C87: ВСЕГО работ по позиции: | H87: 4789.59 | J87: 250400.21
C88: ВСЕГО по позиции: | H88: 4789.59 | J88: 250400.21
A90: 9 | B90: Прайс-лист | C90: ОБОРУДОВАНИЕ: Считыватель для установке на улице и в помещение, интерфейс 26-58, форматы карт Mifare, EM-Marin, HID Prox II 1 801,70 = [15 900 / 1,22 / 7,54] + 3% Трансп + 1,2% Заг.скл | D90: ШТ | E90: 26 | F90: 1801.7 | H90: 1 | I90: 46844.2 | J90: 7.54 | K90: 353205.27
C91: ВСЕГО по позиции: | H91: 46844.2 | J91: 353205.27
A93: 10 | B93: Прайс-лист | C93: ОБОРУДОВАНИЕ: Карта формата Mifare стандартная 2,04 = [18 / 1,22 / 7,54] + 3% Трансп + 1,2% Заг.скл | D93: ШТ | E93: 50 | F93: 2.04 | H93: 1 | I93: 102 | J93: 7.54 | K93: 769.08
C94: ВСЕГО по позиции: | H94: 102 | J94: 769.08
A96: 11 | B96: 4.10-76-10 Поправка: Гл.12.Прил.8.п.8. 3_12.00.01.11.001 | C96: Монтаж ключа или кнопки на панели | D96: 1 ШТ. | E96: 43
C97: Объем: 43=20+23
C98: ЗП | F98: 11.89 | G98: 1,2 | H98: 1 | I98: 613.52 | J98: 57.05 | K98: 35001.32
C99: МР | F99: 1.67 | H99: 1 | I99: 71.81 | J99: 17.41 | K99: 1250.21
A100: 11,1 | B100: 13.1-2-492 | C100: ОБОРУДОВАНИЕ: Извещатель охранно-пожарный ручной, "Аварийный выход" с двумя группами контактов. Тип коммутирующих контактов НЗ/НР, диапазон коммутируемых напряжений постоянного или переменного тока от 5 до 250 В, диапазон коммутируемых токов от 0,1 до 3000 мА, габаритные размеры 109х94х47мм /Кнопка разблокировки дверей "АВАРИЙНЫЙ ВЫХОД" | D100: шт. | E100: 23 | F100: 71.12 | H100: 1 | I100: 1635.76 | J100: 10.97 | K100: 17944.29
C101: НР от ФОТ | D101: % | E101: 95 | I101: 582.84 | J101: 95 | K101: 33251.25
C102: СП от ФОТ | D102: % | E102: 53 | I102: 325.17 | J102: 53 | K102: 18550.7
C103: ЗТР | D103: чел-ч | E103: 1 | G103: 1,2 | H103: 1 | I103: 51.6
C104: ВСЕГО работ по позиции: | H104: 1593.34 | J104: 88053.48
C105: ВСЕГО оборудование по позиции: | H105: 1635.76 | J105: 17944.29
C106: ВСЕГО по позиции: | H106: 3229.1 | J106: 105997.77
A108: 12 | B108: Прайс-лист | C108: ОБОРУДОВАНИЕ: Кнопка выхода 130,32 = [1 150 / 1,22 / 7,54] + 3% Трансп + 1,2% Заг.скл | D108: ШТ | E108: 20 | F108: 130.32 | H108: 1 | I108: 2606.4 | J108: 7.54 | K108: 19652.26
C109: ВСЕГО по позиции: | H109: 2606.4 | J109: 19652.26
A111: 13 | B111: 4.10-167-1 Поправка: Гл.12.Прил.8.п.8. 3_12.00.01.11.001 | C111: Монтаж блока питания сети (БПС) в диспетчерской | D111: 1 ШТ. | E111: 4
C112: ЗП | F112: 18.94 | G112: 1,2 | H112: 1 | I112: 90.91 | J112: 57.05 | K112: 5186.42
C113: ЭМ | F113: 0.02 | G113: 1,2 | H113: 1 | I113: 0.1 | J113: 13.5 | K113: 1.35
C114: МР | F114: 2.34 | H114: 1 | I114: 9.36 | J114: 9.91 | K114: 92.76
C115: НР от ФОТ | D115: % | E115: 90 | I115: 81.82 | J115: 90 | K115: 4667.78
C116: СП от ФОТ | D116: % | E116: 46 | I116: 41.82 | J116: 46 | K116: 2385.75
C117: ЗТР | D117: чел-ч | E117: 1.36 | G117: 1,2 | H117: 1 | I117: 6.53
...

Sheet ЛС 02-01-16
J2: Форма № 4б
A3: =ССРСС!A11 -> Выполнение работ по капитальному ремонту здания в Басманном районе ЦАО города Москвы
A4: (наименование стройки и/или объекта)
A6: ЛОКАЛЬНАЯ СМЕТА № 02-01-16
A8: Система двусторонней связи
A9: (наименование работ и затрат)
I12: В базисном уровне цен | J12: В текущем уровне цен
E13: Сметная стоимость | I13: 8.28 | J13: 97.28 | K13: тыс.руб.
E14: Строительные работы | I14: 0.24 | J14: 2.49 | K14: тыс.руб.
E15: Работы по монтажу оборудования | I15: 0.84 | J15: 40.54 | K15: тыс.руб.
E16: Оборудование | I16: 7.2 | J16: 54.25 | K16: тыс.руб.
E17: Средства на оплату труда | I17: 0.29 | J17: 16.32 | K17: тыс.руб.
E18: Затраты труда | I18: 22.01 | K18: чел.-ч.
A20: Составлен(а) по ТСН-2001 с учетом Дополнения №: 81
A21: № и период сборника коэффициентов (индексов) пересчета: Коэффициенты к ТСН-2001 МГЭ Дополнение 81, строительство №220 II квартал 2026 года и Коэффициенты к ТСН-2001.13-2 Дополнение 47 №65 II квартал 2026 года
A22: № п/п | B22: Шифр расценки и коды ресурсов | C22: Наименование работ и затрат | D22: Ед. изм. | E22: Кол-во единиц | F22: Цена на ед. изм., руб. | G22: Попра- вочные коэффи- циенты | H22: Коэффи- циенты зимних удорожа- ний | I22: Всего в ценах на январь 2000 года, руб. | J22: Коэффи- циенты (индек- сы) пере- счета, нормы НР и СП | K22: ВСЕГО затрат в текущем уровне цен, руб.
A23: 1 | B23: 2 | C23: 3 | D23: 4 | E23: 5 | F23: 6 | G23: 7 | H23: 8 | I23: 9 | J23: 10 | K23: 11
A24: Раздел: Монтажные работы
A25: 1 | B25: 4.10-151-1 Поправка: Гл.12.Прил.8.п.8. 3_12.00.01.11.001 | C25: Установка пульта или табло вызывной сигнализации с количеством сигналов до 5 | D25: 1 ШТ. | E25: 1
C26: ЗП | F26: 45.8 | G26: 1,2 | H26: 1 | I26: 54.96 | J26: 57.05 | K26: 3135.47
C27: ЭМ | F27: 0.08 | G27: 1,2 | H27: 1 | I27: 0.1 | J27: 9.88 | K27: 0.99
C28: МР | F28: 1.78 | H28: 1 | I28: 1.78 | J28: 0.93 | K28: 1.66
C29: НР от ФОТ | D29: % | E29: 90 | I29: 49.46 | J29: 90 | K29: 2821.92
C30: СП от ФОТ | D30: % | E30: 46 | I30: 25.28 | J30: 46 | K30: 1442.32
C31: ЗТР | D31: чел-ч | E31: 4 | G31: 1,2 | H31: 1 | I31: 4.8
C32: ВСЕГО работ по позиции: | H32: 131.58 | J32: 7402.36
C33: ВСЕГО по позиции: | H33: 131.58 | J33: 7402.36
A35: 2 | B35: Прайс-лист | C35: ОБОРУДОВАНИЕ: Пульт громкой связи на 1 абонента 2 262,61 = [19 967,5 / 1,22 / 7,54] + 3% Трансп + 1,2% Заг.скл | D35: ШТ | E35: 1 | F35: 2262.61 | H35: 1 | I35: 2262.61 | J35: 7.54 | K35: 17060.08
C36: ВСЕГО по позиции: | H36: 2262.61 | J36: 17060.08
A38: 3 | B38: 4.10-177-1 Поправка: Гл.12.Прил.8.п.8. 3_12.00.01.11.001 | C38: Монтаж устройства связи с согласующим устройством (вызывная панель) | D38: 10 шт. | E38: 0.1
C39: Объем: 0,1=1/10
C40: ЗП | F40: 227.44 | G40: 1,2 | H40: 1 | I40: 27.29 | J40: 57.05 | K40: 1556.89
C41: ЭМ | F41: 6.07 | G41: 1,2 | H41: 1 | I41: 0.73 | J41: 16.43 | K41: 11.99
C42: в т.ч. ЗПМ | F42: 0.76 | G42: 1,2 | H42: 1 | I42: 0.09 | J42: 57.05 | K42: 5.13
C43: МР | F43: 2.44 | H43: 1 | I43: 0.24 | J43: 7.61 | K43: 1.83
C44: НР от ФОТ | D44: % | E44: 90 | I44: 24.64 | J44: 90 | K44: 1405.82
C45: СП от ФОТ | D45: % | E45: 46 | I45: 12.59 | J45: 46 | K45: 718.53
C46: ЗТР | D46: чел-ч | E46: 14.64 | G46: 1,2 | H46: 1 | I46: 1.76
C47: ВСЕГО работ по позиции: | H47: 65.49 | J47: 3695.06
C48: ВСЕГО по позиции: | H48: 65.49 | J48: 3695.06
A50: 4 | B50: Прайс-лист | C50: ОБОРУДОВАНИЕ: Абонентское устройство громкой связи (врезное) 1 401,07 = [12 364,44 / 1,22 / 7,54] + 3% Трансп + 1,2% Заг.скл | D50: ШТ | E50: 1 | F50: 1401.07 | H50: 1 | I50: 1401.07 | J50: 7.54 | K50: 10564.07
C51: ВСЕГО по позиции: | H51: 1401.07 | J51: 10564.07
A53: 5 | B53: 4.10-58-1 Поправка: Гл.12.Прил.8.п.8. 3_12.00.01.11.001 | C53: Монтаж фидера воздушного однопроводного с установкой специальных изоляторов в установленном экранирующем коробе из медной трубы диаметром до 10 мм, изготовляемого на месте | D53: 1 М | E53: 2
C54: ЗП | F54: 29.08 | G54: 1,2 | H54: 1 | I54: 69.79 | J54: 57.05 | K54: 3981.52
C55: НР от ФОТ | D55: % | E55: 95 | I55: 66.3 | J55: 95 | K55: 3782.44
C56: СП от ФОТ | D56: % | E56: 53 | I56: 36.99 | J56: 53 | K56: 2110.21
C57: ЗТР | D57: чел-ч | E57: 2 | G57: 1,2 | H57: 1 | I57: 4.8
C58: ВСЕГО работ по позиции: | H58: 173.08 | J58: 9874.17
C59: ВСЕГО по позиции: | H59: 173.08 | J59: 9874.17
A61: 6 | B61: Прайс-лист | C61: ОБОРУДОВАНИЕ: Сигнальная лампа 493,94 = [4 358,96 / 1,22 / 7,54] + 3% Трансп + 1,2% Заг.скл | D61: ШТ | E61: 2 | F61: 493.94 | H61: 1 | I61: 987.88 | J61: 7.54 | K61: 7448.62
C62: ВСЕГО по позиции: | H62: 987.88 | J62: 7448.62
A64: 7 | B64: 4.10-76-10 Поправка: Гл.12.Прил.8.п.8. 3_12.00.01.11.001 | C64: Монтаж ключа или кнопки на панели | D64: 1 ШТ. | E64: 2
C65: ЗП | F65: 11.89 | G65: 1,2 | H65: 1 | I65: 28.54 | J65: 57.05 | K65: 1628.21
C66: МР | F66: 1.67 | H66: 1 | I66: 3.34 | J66: 17.41 | K66: 58.15
C67: НР от ФОТ | D67: % | E67: 95 | I67: 27.11 | J67: 95 | K67: 1546.8
C68: СП от ФОТ | D68: % | E68: 53 | I68: 15.13 | J68: 53 | K68: 862.95
C69: ЗТР | D69: чел-ч | E69: 1 | G69: 1,2 | H69: 1 | I69: 2.4
C70: ВСЕГО работ по позиции: | H70: 74.12 | J70: 4096.11
C71: ВСЕГО по позиции: | H71: 74.12 | J71: 4096.11
A73: 8 | B73: Прайс-лист | C73: ОБОРУДОВАНИЕ: Проводная кнопка сброса 925,19 = [8 164,8 / 1,22 / 7,54] + 3% Трансп + 1,2% Заг.скл | D73: ШТ | E73: 1 | F73: 925.19 | H73: 1 | I73: 925.19 | J73: 7.54 | K73: 6975.93
C74: ВСЕГО по позиции: | H74: 925.19 | J74: 6975.93
A76: 9 | B76: Прайс-лист | C76: ОБОРУДОВАНИЕ: Проводная влагозащищенная кнопка вызова со шнуром 1 153,55 = [10 180 / 1,22 / 7,54] + 3% Трансп + 1,2% Заг.скл | D76: ШТ | E76: 1 | F76: 1153.55 | H76: 1 | I76: 1153.55 | J76: 7.54 | K76: 8697.77
C77: ВСЕГО по позиции: | H77: 1153.55 | J77: 8697.77
A79: 10 | B79: 4.10-173-2 Поправка: Гл.12.Прил.8.п.8. 3_12.00.01.11.001 | C79: Монтаж блока бесперебойного питания (ББП) в диспетчерской | D79: 1 ШТ. | E79: 1
C80: ЗП | F80: 40.17 | G80: 1,2 | H80: 1 | I80: 48.2 | J80: 57.05 | K80: 2749.81
C81: МР | F81: 2.34 | H81: 1 | I81: 2.34 | J81: 9.91 | K81: 23.19
C82: НР от ФОТ | D82: % | E82: 90 | I82: 43.38 | J82: 90 | K82: 2474.83
C83: СП от ФОТ | D83: % | E83: 46 | I83: 22.17 | J83: 46 | K83: 1264.91
C84: ЗТР | D84: чел-ч | E84: 3.18 | G84: 1,2 | H84: 1 | I84: 3.82
C85: ВСЕГО работ по позиции: | H85: 116.09 | J85: 6512.74
C86: ВСЕГО по позиции: | H86: 116.09 | J86: 6512.74
A88: 11 | B88: Прайс-лист | C88: ОБОРУДОВАНИЕ: Источник бесперебойного питания 465,17 = [4 105,08 / 1,22 / 7,54] + 3% Трансп + 1,2% Заг.скл | D88: ШТ | E88: 1 | F88: 465.17 | H88: 1 | I88: 465.17 | J88: 7.54 | K88: 3507.38
C89: ВСЕГО по позиции: | H89: 465.17 | J89: 3507.38
A92: Итого по разделу: Монтажные работы | H92: 7755.83 | J92: 85834.29
A94: Раздел: Прокладка кабельных линий
A95: 12 | B95: 4.8-288-2 Поправка: Гл.12.Прил.8.п.8. 3_12.00.01.11.001 | C95: Трубы гофрированные поливинилхлоридные наружным диаметром 20 мм открыто по стенам и потолкам с установкой соединительных коробок | D95: 100 м | E95: 0.15
C96: Объем: 0,15=15/100
C97: ЗП | F97: 192.26 | G97: 1,2 | H97: 1 | I97: 34.61 | J97: 57.05 | K97: 1974.5
C98: ЭМ | F98: 32.87 | G98: 1,2 | H98: 1 | I98: 5.92 | J98: 19.24 | K98: 113.9
C99: в т.ч. ЗПМ | F99: 5.71 | G99: 1,2 | H99: 1 | I99: 1.03 | J99: 57.05 | K99: 58.76
C100: МР | F100: 314.29 | H100: 1 | I100: 47.14 | J100: 10.18 | K100: 479.89
A101: 12,1 | B101: 1.12-5-372 | C101: Трубы электротехнические, гофрированные, из ПВХ, негорючие, с зондом, наружный диаметр 20 мм | D101: м | E101: 15.3 | F101: 3.45 | H101: 1 | I101: 52.79 | J101: 3.85 | K101: 203.24
C102: НР от ФОТ | D102: % | E102: 97 | I102: 34.57 | J102: 97 | K102: 1972.26
C103: СП от ФОТ | D103: % | E103: 51 | I103: 18.18 | J103: 51 | K103: 1036.96
C104: ЗТР | D104: чел-ч | E104: 15 | G104: 1,2 | H104: 1 | I104: 2.7
C105: ВСЕГО работ по позиции: | H105: 193.21 | J105: 5780.75
C106: ВСЕГО по позиции: | H106: 193.21 | J106: 5780.75
A108: 13 | B108: 4.8-175-2 Поправка: Гл.12.Прил.8.п.8. 3_12.00.01.11.001 | C108: Затягивание провода в проложенные трубы и металлические рукава, первого одножильного или многожильного в общей оплетке, суммарное сечение до 6 мм2 | D108: 100 м | E108: 0.15
C109: Объем: 0,15=15/100
C110: ЗП | F110: 66.3 | G110: 1,2 | H110: 1 | I110: 11.93 | J110: 57.05 | K110: 680.61
C111: ЭМ | F111: 5.25 | G111: 1,2 | H111: 1 | I111: 0.95 | J111: 15.93 | K111: 15.13
C112: в т.ч. ЗПМ | F112: 0.59 | G112: 1,2 | H112: 1 | I112: 0.11 | J112: 57.05 | K112: 6.28
C113: МР | F113: 61.98 | H113: 1 | I113: 9.3 | J113: 4.5 | K113: 41.85
C114: НР от ФОТ | D114: % | E114: 97 | I114: 11.68 | J114: 97 | K114: 666.28
C115: СП от ФОТ | D115: % | E115: 51 | I115: 6.14 | J115: 51 | K115: 350.31
C116: ЗТР | D116: чел-ч | E116: 5.39 | G116: 1,2 | H116: 1 | I116: 0.97
C117: ВСЕГО работ по позиции: | H117: 40 | J117: 1754.18
C118: ВСЕГО по позиции: | H118: 40 | J118: 1754.18
A120: 14 | B120: 4.8-175-9 Поправка: Гл.12.Прил.8.п.8. 3_12.00.01.11.001 | C120: Добавлять на затягивание провода в проложенные трубы и металлические рукава каждого последующего одножильного или многожильного в общей оплетке, суммарное сечение до 6 мм2 (к нормам и расценкам 4.8-175-1 и 4.8-175-2) | D120: 100 м | E120: 0.35
C121: Объем: 0,35=35/100
...

Sheet ЛС 02-01-17
A1: Smeta.RU (495) 974-1589
J2: Форма № 4б
A3: =ССРСС!A11 -> Выполнение работ по капитальному ремонту здания в Басманном районе ЦАО города Москвы
A4: (наименование стройки и/или объекта)
A6: ЛОКАЛЬНАЯ СМЕТА № 02-01-17
A8: Автоматизация и диспетчеризация инженерных систем
A9: (наименование работ и затрат)
I12: В базисном уровне цен | J12: В текущем уровне цен
E13: Сметная стоимость | I13: 27.09 | J13: 376.01 | K13: тыс.руб.
E14: Работы по монтажу оборудования | I14: 10.66 | J14: 269.15 | K14: тыс.руб.
E15: Оборудование | I15: 16.43 | J15: 106.86 | K15: тыс.руб.
E16: Средства на оплату труда | I16: 1.54 | J16: 87.96 | K16: тыс.руб.
E17: Затраты труда | I17: 117.19 | K17: чел.-ч.
A19: Составлен(а) по ТСН-2001 с учетом Дополнения №: 81
A20: № и период сборника коэффициентов (индексов) пересчета: Коэффициенты к ТСН-2001 МГЭ Дополнение 81, строительство №220 II квартал 2026 года и Коэффициенты к ТСН-2001.13-2 Дополнение 47 №65 II квартал 2026 года
A21: № п/п | B21: Шифр расценки и коды ресурсов | C21: Наименование работ и затрат | D21: Ед. изм. | E21: Кол-во единиц | F21: Цена на ед. изм., руб. | G21: Попра- вочные коэффи- циенты | H21: Коэффи- циенты зимних удорожа- ний | I21: Всего в ценах на январь 2000 года, руб. | J21: Коэффи- циенты (индек- сы) пере- счета, нормы НР и СП | K21: ВСЕГО затрат в текущем уровне цен, руб.
A22: 1 | B22: 2 | C22: 3 | D22: 4 | E22: 5 | F22: 6 | G22: 7 | H22: 8 | I22: 9 | J22: 10 | K22: 11
A23: Раздел: Система управления и диспетчерского контроля инженерного оборудования
A25: Подраздел: Приборы и средства автоматизации
A26: 1 | B26: 4.8-240-4 Поправка: Гл.12.Прил.8.п.8. 3_12.00.01.11.001 | C26: Монтаж пультов и шкафов управления, шкафа (пульта) управления навесного, высотой, шириной, глубиной до 600х600х350 мм | D26: 1 ШТ. | E26: 1
C27: ЗП | F27: 26.76 | G27: 1,2 | H27: 1 | I27: 32.11 | J27: 57.05 | K27: 1831.88
C28: ЭМ | F28: 17.42 | G28: 1,2 | H28: 1 | I28: 20.9 | J28: 20.11 | K28: 420.3
C29: в т.ч. ЗПМ | F29: 3.16 | G29: 1,2 | H29: 1 | I29: 3.79 | J29: 57.05 | K29: 216.22
C30: МР | F30: 1.46 | H30: 1 | I30: 1.46 | J30: 13.13 | K30: 19.17
A31: 1,1 | B31: 1.1-1-60 | C31: Болты строительные с шестигранной головкой с гайками, М6 | D31: т | E31: 0.0001 | F31: 22524.65 | H31: 1 | I31: 2.25 | J31: 5.94 | K31: 13.37
A32: 1,2 | B32: 1.21-1-63 | C32: Щит навесной, с дверцей и замком, степень защиты IР55, размер 600х600х250 мм, металлоконструкция без аппаратов / ЩМП-3-0 74, У2, IP54, 650х500х220 | D32: шт. | E32: 1 | F32: 1975.19 | H32: 1 | I32: 1975.19 | J32: 6.59 | K32: 13016.5
C33: НР от ФОТ | D33: % | E33: 97 | I33: 34.82 | J33: 97 | K33: 1986.66
C34: СП от ФОТ | D34: % | E34: 51 | I34: 18.31 | J34: 51 | K34: 1044.53
C35: ЗТР | D35: чел-ч | E35: 2.06 | G35: 1,2 | H35: 1 | I35: 2.47
C36: ВСЕГО работ по позиции: | H36: 2085.04 | J36: 18332.41
C37: ВСЕГО по позиции: | H37: 2085.04 | J37: 18332.41
A39: 2 | B39: 4.10-176-1 Поправка: Гл.12.Прил.8.п.8. 3_12.00.01.11.001 | C39: Монтаж блока контроля датчиков (контроллер) | D39: 10 шт. | E39: 0.1
C40: Объем: 0,1=1/10
C41: ЗП | F41: 470.94 | G41: 1,2 | H41: 1 | I41: 56.51 | J41: 57.05 | K41: 3223.9
C42: ЭМ | F42: 1.1 | G42: 1,2 | H42: 1 | I42: 0.13 | J42: 16.77 | K42: 2.18
C43: в т.ч. ЗПМ | F43: 0.13 | G43: 1,2 | H43: 1 | I43: 0.02 | J43: 57.05 | K43: 1.14
C44: МР | F44: 1.29 | H44: 1 | I44: 0.13 | J44: 7.62 | K44: 0.99
A45: 2,1 | B45: Прайс-лист | C45: ОБОРУДОВАНИЕ: Контроллер 4 131,92 = [36 464 / 1,22 / 7,54] + 3% Трансп + 1,2% Заг.скл | D45: ШТ | E45: 1 | F45: 4131.92 | H45: 1 | I45: 4131.92 | J45: 7.54 | K45: 31154.68
C46: НР от ФОТ | D46: % | E46: 90 | I46: 50.88 | J46: 90 | K46: 2902.54
C47: СП от ФОТ | D47: % | E47: 46 | I47: 26 | J47: 46 | K47: 1483.52
C48: ЗТР | D48: чел-ч | E48: 29.96 | G48: 1,2 | H48: 1 | I48: 3.6
C49: ВСЕГО работ по позиции: | H49: 133.65 | J49: 7613.13
C50: ВСЕГО оборудование по позиции: | H50: 4131.92 | J50: 31154.68
C51: ВСЕГО по позиции: | H51: 4265.57 | J51: 38767.81
A53: 3 | B53: 4.10-173-2 Поправка: Гл.12.Прил.8.п.8. 3_12.00.01.11.001 | C53: Монтаж блока бесперебойного питания (ББП) в диспетчерской | D53: 1 ШТ. | E53: 1
C54: ЗП | F54: 40.17 | G54: 1,2 | H54: 1 | I54: 48.2 | J54: 57.05 | K54: 2749.81
C55: МР | F55: 2.34 | H55: 1 | I55: 2.34 | J55: 9.91 | K55: 23.19
C56: НР от ФОТ | D56: % | E56: 90 | I56: 43.38 | J56: 90 | K56: 2474.83
C57: СП от ФОТ | D57: % | E57: 46 | I57: 22.17 | J57: 46 | K57: 1264.91
C58: ЗТР | D58: чел-ч | E58: 3.18 | G58: 1,2 | H58: 1 | I58: 3.82
C59: ВСЕГО работ по позиции: | H59: 116.09 | J59: 6512.74
C60: ВСЕГО по позиции: | H60: 116.09 | J60: 6512.74
A62: 4 | B62: Прайс-лист | C62: ОБОРУДОВАНИЕ: Источник бесперебойного питания 6 498,38 = [57 348 / 1,22 / 7,54] + 3% Трансп + 1,2% Заг.скл | D62: ШТ | E62: 1 | F62: 6498.38 | H62: 1 | I62: 6498.38 | J62: 7.54 | K62: 48997.79
C63: ВСЕГО по позиции: | H63: 6498.38 | J63: 48997.79
A66: Итого по подразделу: Приборы и средства автоматизации | H66: 12965.08 | J66: 112610.75
A68: Подраздел: Прокладка кабельных линий
A69: 5 | B69: 4.8-288-2 Поправка: Гл.12.Прил.8.п.8. 3_12.00.01.11.001 | C69: Трубы гофрированные поливинилхлоридные наружным диаметром 20 мм открыто по стенам и потолкам с установкой соединительных коробок | D69: 100 м | E69: 2
C70: Объем: 2=200/100
C71: ЗП | F71: 192.26 | G71: 1,2 | H71: 1 | I71: 461.42 | J71: 57.05 | K71: 26324.01
C72: ЭМ | F72: 32.87 | G72: 1,2 | H72: 1 | I72: 78.89 | J72: 19.24 | K72: 1517.84
C73: в т.ч. ЗПМ | F73: 5.71 | G73: 1,2 | H73: 1 | I73: 13.7 | J73: 57.05 | K73: 781.59
C74: МР | F74: 314.29 | H74: 1 | I74: 628.58 | J74: 10.18 | K74: 6398.94
A75: 5,1 | B75: 1.12-5-372 | C75: Трубы электротехнические, гофрированные, из ПВХ, негорючие, с зондом, наружный диаметр 20 мм | D75: м | E75: 204 | F75: 3.45 | H75: 1 | I75: 703.8 | J75: 3.85 | K75: 2709.63
C76: НР от ФОТ | D76: % | E76: 97 | I76: 460.87 | J76: 97 | K76: 26292.43
C77: СП от ФОТ | D77: % | E77: 51 | I77: 242.31 | J77: 51 | K77: 13823.86
C78: ЗТР | D78: чел-ч | E78: 15 | G78: 1,2 | H78: 1 | I78: 36
C79: ВСЕГО работ по позиции: | H79: 2575.87 | J79: 77066.71
C80: ВСЕГО по позиции: | H80: 2575.87 | J80: 77066.71
A82: 6 | B82: 4.8-175-1 Поправка: Гл.12.Прил.8.п.8. 3_12.00.01.11.001 | C82: Затягивание провода в проложенные трубы и металлические рукава, первого одножильного или многожильного в общей оплетке, суммарное сечение до 2,5 мм2 | D82: 100 м | E82: 2
C83: Объем: 2=200/100
C84: ЗП | F84: 55.23 | G84: 1,2 | H84: 1 | I84: 132.55 | J84: 57.05 | K84: 7561.98
C85: ЭМ | F85: 2.62 | G85: 1,2 | H85: 1 | I85: 6.29 | J85: 15.96 | K85: 100.39
C86: в т.ч. ЗПМ | F86: 0.3 | G86: 1,2 | H86: 1 | I86: 0.72 | J86: 57.05 | K86: 41.08
C87: МР | F87: 58.15 | H87: 1 | I87: 116.3 | J87: 3.64 | K87: 423.33
A88: 6,1 | B88: Прайс-лист | C88: Кабель для систем передачи данных ТЭТ типа нг(А)-HF 1x2x0,75 6,05 = [73,63 / 1,22 / 10,18] + 2% Заг.скл | D88: м | E88: 204 | F88: 6.05 | H88: 1 | I88: 1234.2 | J88: 10.18 | K88: 12564.16
C89: НР от ФОТ | D89: % | E89: 97 | I89: 129.27 | J89: 97 | K89: 7374.97
C90: СП от ФОТ | D90: % | E90: 51 | I90: 67.97 | J90: 51 | K90: 3877.56
C91: ЗТР | D91: чел-ч | E91: 4.49 | G91: 1,2 | H91: 1 | I91: 10.78
C92: ВСЕГО работ по позиции: | H92: 1686.58 | J92: 31902.39
C93: ВСЕГО по позиции: | H93: 1686.58 | J93: 31902.39
A96: Итого по подразделу: Прокладка кабельных линий | H96: 4262.45 | J96: 108969.1
A98: Итого по разделу: Система управления и диспетчерского контроля инженерного оборудования | H98: 17227.53 | J98: 221579.85
A100: Раздел: Автоматизация противопожарных мероприятий
A102: Подраздел: Приборы и средства автоматизации
A103: 7 | B103: 4.10-80-13 Поправка: Гл.12.Прил.8.п.8. 3_12.00.01.11.001 | C103: Аппараты приемные, устройства промежуточные на 1 луч | D103: 1 ШТ. | E103: 1
C104: ЗП | F104: 16.07 | G104: 1,2 | H104: 1 | I104: 19.28 | J104: 57.05 | K104: 1099.92
C105: ЭМ | F105: 0.05 | G105: 1,2 | H105: 1 | I105: 0.06 | J105: 20.4 | K105: 1.22
C106: в т.ч. ЗПМ | F106: 0.01 | G106: 1,2 | H106: 1 | I106: 0.01 | J106: 57.05 | K106: 0.57
C107: МР | F107: 1.96 | H107: 1 | I107: 1.96 | J107: 10.18 | K107: 19.95
C108: НР от ФОТ | D108: % | E108: 90 | I108: 17.36 | J108: 90 | K108: 990.44
C109: СП от ФОТ | D109: % | E109: 46 | I109: 8.87 | J109: 46 | K109: 506.23
C110: ЗТР | D110: чел-ч | E110: 1.2 | G110: 1,2 | H110: 1 | I110: 1.44
C111: ВСЕГО работ по позиции: | H111: 47.53 | J111: 2617.76
C112: ВСЕГО по позиции: | H112: 47.53 | J112: 2617.76
A114: 8 | B114: Прайс-лист | C114: ОБОРУДОВАНИЕ: Модуль релейный 352,19 = [3 108 / 1,22 / 7,54] + 3% Трансп + 1,2% Заг.скл | D114: ШТ | E114: 1 | F114: 352.19 | H114: 1 | I114: 352.19 | J114: 7.54 | K114: 2655.51
C115: ВСЕГО по позиции: | H115: 352.19 | J115: 2655.51
A118: Итого по подразделу: Приборы и средства автоматизации | H118: 399.72 | J118: 5273.27
A120: Подраздел: Прокладка кабельных линий
A121: 9 | B121: 4.10-15-5 Поправка: Гл.12.Прил.8.п.8. 3_12.00.01.11.001 | C121: Прокладка по стене бетонной кабеля массой 1 м до 1 кг | D121: 100 м | E121: 0.2
C122: Объем: 0,2=20/100
...

Sheet ЛС 02-01-18
J2: Форма № 4б
A3: =ССРСС!A11 -> Выполнение работ по капитальному ремонту здания в Басманном районе ЦАО города Москвы
A4: (наименование стройки и/или объекта)
A6: ЛОКАЛЬНАЯ СМЕТА № 02-01-18
A8: Мероприятия по противодействию террористическим актам
A9: (наименование работ и затрат)
I12: В базисном уровне цен | J12: В текущем уровне цен
E13: Сметная стоимость | I13: 403.22 | J13: 2437.21 | K13: тыс.руб.
E14: Оборудование | I14: 403.22 | J14: 2437.21 | K14: тыс.руб.
A16: Составлен(а) по ТСН-2001 с учетом Дополнения №: 81
A17: № и период сборника коэффициентов (индексов) пересчета: Коэффициенты к ТСН-2001 МГЭ Дополнение 81, ремонт №220 II квартал 2026 года и Коэффициенты к ТСН-2001.13-2 Дополнение 47 №65 II квартал 2026 года
A18: № п/п | B18: Шифр расценки и коды ресурсов | C18: Наименование работ и затрат | D18: Ед. изм. | E18: Кол-во единиц | F18: Цена на ед. изм., руб. | G18: Попра- вочные коэффи- циенты | H18: Коэффи- циенты зимних удорожа- ний | I18: Всего в ценах на январь 2000 года, руб. | J18: Коэффи- циенты (индек- сы) пере- счета, нормы НР и СП | K18: ВСЕГО затрат в текущем уровне цен, руб.
A19: 1 | B19: 2 | C19: 3 | D19: 4 | E19: 5 | F19: 6 | G19: 7 | H19: 8 | I19: 9 | J19: 10 | K19: 11
A20: Раздел: Оборудование
A21: 1 | B21: 13.1-2-193 | C21: ОБОРУДОВАНИЕ: Металлоискатель портативный микропроцессорный селективный, со световой, звуковой и вибро индикацией, светодиодной подсветкой, в комплекте с футляром и зарядным устройством. Расстояние обнаружения: пистолет - 30 см, граната - 26 см, нож (лезвие 20 см) - 20 см, лезвие безопасной бритвы - 5 см, медный диск (25х1 мм) - 14 см, кольцо золотое (вес 1 г) - 5 см, 2 уровня чувствительности, рабочая частота 8 (13) кГц, питание от 4 аккумуляторов формата АА суммарным напряжением от 4,8 до 6 В, корпус из ударопрочного пластика, | D21: КОМПЛЕКТ | E21: 2 | F21: 878.39 | H21: 1 | I21: 1756.78 | J21: 13.8 | K21: 24243.56
C22: ВСЕГО по позиции: | H22: 1756.78 | J22: 24243.56
A24: 2 | B24: Прайс-лист | C24: ОБОРУДОВАНИЕ: Досмотровый эндоскоп 10 764,90 = [95 000 / 1,22 / 7,54] + 3% Трансп + 1,2% Заг.скл | D24: ШТ | E24: 1 | F24: 10764.9 | H24: 1 | I24: 10764.9 | J24: 7.54 | K24: 81167.35
C25: ВСЕГО по позиции: | H25: 10764.9 | J25: 81167.35
A27: 3 | B27: 13.1-2-203 | C27: ОБОРУДОВАНИЕ:_x000D_ Устройство досмотровое (зеркало) для осмотра грузов, транспортных средств, неосвещенных и труднодоступных мест в помещениях. В составе: телескопическая штанга со встроенными светодиодами, с регулировкой длины от 600 до 1850 мм, набор зеркал различного размера и формы - 4 шт. Время непрерывной работы светодиодов не менее 9 часов, диапазон рабочих температур от -20 до +50°С | D27: КОМПЛЕКТ | E27: 1 | F27: 866.44 | H27: 1 | I27: 866.44 | J27: 11.24 | K27: 9738.79
C28: ВСЕГО по позиции: | H28: 866.44 | J28: 9738.79
A30: 4 | B30: 13.3-9-187 | C30: ОБОРУДОВАНИЕ: Устройство для защиты от взрыва . Мобильное устройство для подавления не более 2000 г ТНТ, локализуемый объем до 90 дм3, выполнено в форме купола с двумя ручками, стенки и верх купола наполнены специальным диспенсером, поглощающим тепловую и ударную волну | D30: шт. | E30: 1 | F30: 10969.27 | H30: 1 | I30: 10969.27 | J30: 10.16 | K30: 111447.78
C31: ВСЕГО по позиции: | H31: 10969.27 | J31: 111447.78
A33: 5 | B33: 13.1-2-363 | C33: ОБОРУДОВАНИЕ: Монитор радиационный для обнаружения ядерных и радиоактивных материалов в составе комплекса автоматизированного радиационного контроля. Зона контроля не более 0,8х2 м, время измерения от 1 до 2 с, частота ложных срабатываний не более 1/1000, потребляемая мощность не более 10 Вт, степень защиты IP54, габаритные размеры 560х126х90 мм | D33: шт. | E33: 1 | F33: 100498.71 | H33: 1 | I33: 100498.71 | J33: 3.3 | K33: 331645.74
C34: ВСЕГО по позиции: | H34: 100498.71 | J34: 331645.74
A36: 6 | B36: 13.1-3-231 | C36: ОБОРУДОВАНИЕ:_x000D_ Детектор ионно-дрейфовый для обнаружения взрывчатых, наркотических, аварийно-химических, опасных и боевых отравляющих веществ, с комплектом ЗИП. Время: установления рабочего режима - 15 мин, измерения - 5 с, автономной работы со штатным аккумулятором - 2 часа, очистки детектора - 3 мин, интерфейсы Ethernet, USB (х2), в комплекте: сумка-чехол, флэш-накопитель; вещества обнаруживаемые детектором: нитрат аммония, динитротолуол, тринитротолуол, тринитрорезорцин, тринитрофенол, динитронафталин, диметилдинитробутан, этиленгликольдинитрат, нитроглицерин, пентаэритриттетранитрат, гексоген, октоген, тетрил, тетразол, бензофуроксан, триперекись ацетона, гексаметилентрипероксиддиамин, ПВВ на основе гексогена, октол, семтекс, аммонит, амфетамин, метамфетамин, кокаин, героин,
C37: тетрагидроканнабинол, метилендиоксиамфетамин, метилендиоксиметамфетамин, сероводород, хлороводород, фтороводород, сернистый ангидрид, хлор, аммиак, оксид азота, диоксид азота, несимметричный, диметилгидразин, зарин, зоман, иприт, Vx, фосген, синильная кислота; мощность не более 60 ВА | D37: КОМПЛЕКТ | E37: 1 | F37: 278365.6 | H37: 1 | I37: 278365.6 | J37: 6.75 | K37: 1878967.8
C38: ВСЕГО по позиции: | H38: 278365.6 | J38: 1878967.8
A41: Итого по разделу: Оборудование | H41: 403221.7 | J41: 2437211
A43: Итого по смете: | H43: 403221.7 | J43: 2437211

Sheet ЛС 02-01-19
A1: Smeta.RU (495) 974-1589
J2: Форма № 4б
A3: =ССРСС!A11 -> Выполнение работ по капитальному ремонту здания в Басманном районе ЦАО города Москвы
A4: (наименование стройки и/или объекта)
A6: ЛОКАЛЬНАЯ СМЕТА № 02-01-19
A8: Мероприятия по обеспечению доступа инвалидов
A9: (наименование работ и затрат)
I12: В базисном уровне цен | J12: В текущем уровне цен
E13: Сметная стоимость | I13: 13.39 | J13: 126.18 | K13: тыс.руб.
E14: Строительные работы | I14: 5.64 | J14: 65.76 | K14: тыс.руб.
E15: Работы по монтажу оборудования | I15: 0.04 | J15: 2.31 | K15: тыс.руб.
E16: Оборудование (не облагаемое НДС) | I16: 7.71 | J16: 58.11 | K16: тыс.руб.
E17: Средства на оплату труда | I17: 0.21 | J17: 11.75 | K17: тыс.руб.
E18: Затраты труда | I18: 17.85 | K18: чел.-ч.
A20: Составлен(а) по ТСН-2001 с учетом Дополнения №: 81
A21: № и период сборника коэффициентов (индексов) пересчета: Коэффициенты к ТСН-2001 МГЭ Дополнение 81, ремонт №220 II квартал 2026 года и Коэффициенты к ТСН-2001.13-2 Дополнение 47 №65 II квартал 2026 года
A22: № п/п | B22: Шифр расценки и коды ресурсов | C22: Наименование работ и затрат | D22: Ед. изм. | E22: Кол-во единиц | F22: Цена на ед. изм., руб. | G22: Попра- вочные коэффи- циенты | H22: Коэффи- циенты зимних удорожа- ний | I22: Всего в ценах на январь 2000 года, руб. | J22: Коэффи- циенты (индек- сы) пере- счета, нормы НР и СП | K22: ВСЕГО затрат в текущем уровне цен, руб.
A23: 1 | B23: 2 | C23: 3 | D23: 4 | E23: 5 | F23: 6 | G23: 7 | H23: 8 | I23: 9 | J23: 10 | K23: 11
A24: Раздел: Информационно-тактильные знаки
A25: 1 | B25: 3.9-65-2 | C25: Установка номерных табличек для этажа, подъезда | D25: 1 ШТ. | E25: 18
C26: Объем: 18=2+2+3+1+1+3+1+1+1+1+1+1
C27: ЗП | F27: 5.81 | H27: 1 | I27: 104.58 | J27: 57.05 | K27: 5966.29
C28: МР | F28: 0.5 | H28: 1 | I28: 9 | J28: 16.42 | K28: 147.78
C29: НР от ФОТ | D29: % | E29: 84 | I29: 87.85 | J29: 84 | K29: 5011.68
C30: СП от ФОТ | D30: % | E30: 53 | I30: 55.43 | J30: 53 | K30: 3162.13
C31: ЗТР | D31: чел-ч | E31: 0.52 | H31: 1 | I31: 9.36
C32: ВСЕГО работ по позиции: | H32: 256.86 | J32: 14287.88
C33: ВСЕГО по позиции: | H33: 256.86 | J33: 14287.88
A35: 2 | B35: Прайс-лист | C35: Эвакуационный знак 150х150 " Выход здесь" 32,44 = [395 / 1,22 / 10,18] + 2% Заг.скл | D35: ШТ | E35: 2 | F35: 32.44 | H35: 1 | I35: 64.88 | J35: 10.18 | K35: 660.48
C36: ВСЕГО по позиции: | H36: 64.88 | J36: 660.48
A38: 3 | B38: Прайс-лист | C38: Эвакуационный знак 150х150 мм "Направляющая стрелка" 9,04 = [110 / 1,22 / 10,18] + 2% Заг.скл | D38: ШТ | E38: 2 | F38: 9.04 | H38: 1 | I38: 18.08 | J38: 10.18 | K38: 184.05
C39: ВСЕГО по позиции: | H39: 18.08 | J39: 184.05
A41: 4 | B41: Прайс-лист | C41: Эвакуационный знак E 22 "Указатель выхода" 22,01 = [268 / 1,22 / 10,18] + 2% Заг.скл | D41: ШТ | E41: 3 | F41: 22.01 | H41: 1 | I41: 66.03 | J41: 10.18 | K41: 672.19
C42: ВСЕГО по позиции: | H42: 66.03 | J42: 672.19
A44: 5 | B44: Прайс-лист | C44: Тактильный знак СП 10, 150х150 мм "Выход из помещения" 32,53 = [396 / 1,22 / 10,18] + 2% Заг.скл | D44: ШТ | E44: 1 | F44: 32.53 | H44: 1 | I44: 32.53 | J44: 10.18 | K44: 331.16
C45: ВСЕГО по позиции: | H45: 32.53 | J45: 331.16
A47: 6 | B47: Прайс-лист | C47: Тактильный знак СП 18, 150х150 мм "Туалет для инвалидов" 32,53 = [396 / 1,22 / 10,18] + 2% Заг.скл | D47: ШТ | E47: 1 | F47: 32.53 | H47: 1 | I47: 32.53 | J47: 10.18 | K47: 331.16
C48: ВСЕГО по позиции: | H48: 32.53 | J48: 331.16
A50: 7 | B50: Прайс-лист | C50: Тактильная табличка со шрифтом Брайля, 150х300мм "Название помещения" 92,47 = [1 126 / 1,22 / 10,18] + 2% Заг.скл | D50: ШТ | E50: 3 | F50: 92.47 | H50: 1 | I50: 277.41 | J50: 10.18 | K50: 2824.03
C51: ВСЕГО по позиции: | H51: 277.41 | J51: 2824.03
A53: 8 | B53: Прайс-лист | C53: Тактильный знак 150х150 мм "Доступность для инвалидов по зрению" 32,53 = [396 / 1,22 / 10,18] + 2% Заг.скл | D53: ШТ | E53: 1 | F53: 32.53 | H53: 1 | I53: 32.53 | J53: 10.18 | K53: 331.16
C54: ВСЕГО по позиции: | H54: 32.53 | J54: 331.16
A56: 9 | B56: Прайс-лист | C56: Тактильный знак 150х150 мм "Доступность для инвалидов по слуху" 32,53 = [396 / 1,22 / 10,18] + 2% Заг.скл | D56: ШТ | E56: 1 | F56: 32.53 | H56: 1 | I56: 32.53 | J56: 10.18 | K56: 331.16
C57: ВСЕГО по позиции: | H57: 32.53 | J57: 331.16
A59: 10 | B59: Прайс-лист | C59: Тактильная мнемосхема санузла, полноцветная на стальной основе 321х411х2 мм 345,84 = [4 211 / 1,22 / 10,18] + 2% Заг.скл | D59: ШТ | E59: 1 | F59: 345.84 | H59: 1 | I59: 345.84 | J59: 10.18 | K59: 3520.65
C60: ВСЕГО по позиции: | H60: 345.84 | J60: 3520.65
A62: 11 | B62: Прайс-лист | C62: Тактильная мнемосхема этажа, полноцветная на основе оргстекла, 470x610х8 мм 866,29 = [10 548 / 1,22 / 10,18] + 2% Заг.скл | D62: ШТ | E62: 1 | F62: 866.29 | H62: 1 | I62: 866.29 | J62: 10.18 | K62: 8818.83
C63: ВСЕГО по позиции: | H63: 866.29 | J63: 8818.83
A65: 12 | B65: Прайс-лист | C65: Знак обозначения кнопки вызова персонала для оказания ситуационной помощи 150х180 мм 34,08 = [415 / 1,22 / 10,18] + 2% Заг.скл | D65: ШТ | E65: 1 | F65: 34.08 | H65: 1 | I65: 34.08 | J65: 10.18 | K65: 346.93
C66: ВСЕГО по позиции: | H66: 34.08 | J66: 346.93
A68: 13 | B68: Прайс-лист | C68: Тактильный знак СП 18, 150х150 мм "Туалет для инвалидов" 32,53 = [396 / 1,22 / 10,18] + 2% Заг.скл | D68: ШТ | E68: 1 | F68: 32.53 | H68: 1 | I68: 32.53 | J68: 10.18 | K68: 331.16
C69: ВСЕГО по позиции: | H69: 32.53 | J69: 331.16
A71: 14 | B71: 3.15-129-3 | C71: Оклейка стен поливинилхлоридной декоративно-отделочной самоклеющейся пленкой по листовым материалам | D71: 100 м2 оклеиваемой поверхности | E71: 0.010048
C72: Объем: 0,010048=(3,14*0,2*0,2*8)/100
C73: ЗП | F73: 844.8 | H73: 1 | I73: 8.49 | J73: 57.05 | K73: 484.35
C74: ЭМ | F74: 5.82 | H74: 1 | I74: 0.06 | J74: 17.44 | K74: 1.05
C75: в т.ч. ЗПМ | F75: 0.88 | H75: 1 | I75: 0.01 | J75: 57.05 | K75: 0.57
C76: МР | F76: 1073.97 | H76: 1 | I76: 10.79 | J76: 3.63 | K76: 39.17
C77: НР от ФОТ | D77: % | E77: 90 | I77: 7.65 | J77: 90 | K77: 436.43
C78: СП от ФОТ | D78: % | E78: 42 | I78: 3.57 | J78: 42 | K78: 203.67
C79: ЗТР | D79: чел-ч | E79: 64 | H79: 1 | I79: 0.64
C80: ВСЕГО работ по позиции: | H80: 30.56 | J80: 1164.67
C81: ВСЕГО по позиции: | H81: 30.56 | J81: 1164.67
A83: 15 | B83: Прайс-лист | C83: Наклейка, цвет желтый, Д=20 см 4,11 = [50 / 1,22 / 10,18] + 2% Заг.скл | D83: ШТ | E83: 8 | F83: 4.11 | H83: 1 | I83: 32.88 | J83: 10.18 | K83: 334.72
C84: ВСЕГО по позиции: | H84: 32.88 | J84: 334.72
A87: Итого по разделу: Информационно-тактильные знаки | H87: 2155.56 | J87: 34470.23
A89: Раздел: Оборудование и материал санузла для МГН
A90: 16 | B90: 3.17-2-14 | C90: Установка гарнитуры туалетной: поручней для ванн | D90: 100 шт. | E90: 0.24
C91: Объем: 0,24=(0,9+0,9+0,6)/10
C92: ЗП | F92: 188.72 | H92: 1 | I92: 45.29 | J92: 57.05 | K92: 2583.79
C93: ЭМ | F93: 7.54 | H93: 1 | I93: 1.81 | J93: 14.86 | K93: 26.9
C94: в т.ч. ЗПМ | F94: 0.5 | H94: 1 | I94: 0.12 | J94: 57.05 | K94: 6.85
C95: МР | F95: 5229.82 | H95: 1 | I95: 1255.16 | J95: 0.48 | K95: 602.48
C96: НР от ФОТ | D96: % | E96: 109 | I96: 49.5 | J96: 109 | K96: 2823.8
C97: СП от ФОТ | D97: % | E97: 61 | I97: 27.7 | J97: 61 | K97: 1580.29
C98: ЗТР | D98: чел-ч | E98: 16.89 | H98: 1 | I98: 4.05
C99: ВСЕГО работ по позиции: | H99: 1379.46 | J99: 7617.26
C100: ВСЕГО по позиции: | H100: 1379.46 | J100: 7617.26
A102: 17 | B102: 3.17-2-13 Поправка: Гл.12.Прил.8.п.8. 3_12.00.01.11.001 Поправка: Гл.6.Прил.2.2.п.2.2.6_06.00.01.07.001 | C102: Установка гарнитуры туалетной: вешалок, подстаканников, дозаторов настенных и т.п. | D102: 100 шт. | E102: 0.01
C103: Объем: 0,01=1/100
C104: ЗП | F104: 95.59 | G104: 1,2*1,15 | H104: 1 | I104: 1.32 | J104: 57.05 | K104: 75.31
C105: ЭМ | F105: 8.97 | G105: 1,2*1,25 | H105: 1 | I105: 0.13 | J105: 16.35 | K105: 2.13
C106: в т.ч. ЗПМ | F106: 1.01 | G106: 1,2*1,25 | H106: 1 | I106: 0.02 | J106: 57.05 | K106: 1.14
C107: МР | F107: 2202.04 | H107: 1 | I107: 22.02 | J107: 0.48 | K107: 10.57
C108: НР от ФОТ | D108: % | E108: 109 | I108: 1.46 | J108: 109 | K108: 83.33
C109: СП от ФОТ | D109: % | E109: 61 | I109: 0.82 | J109: 61 | K109: 46.63
C110: ЗТР | D110: чел-ч | E110: 8.58 | G110: 1,2*1,15 | H110: 1 | I110: 0.12
C111: ВСЕГО работ по позиции: | H111: 25.75 | J111: 217.97
C112: ВСЕГО по позиции: | H112: 25.75 | J112: 217.97
A114: 18 | B114: Прайс-лист | C114: Сенсорный дозатор мыла для людей с ограниченными возможностями 210х140х105мм, 450мл, h=1000мм 412,28 = [5 020 / 1,22 / 10,18] + 2% Заг.скл | D114: ШТ | E114: 1 | F114: 412.28 | H114: 1 | I114: 412.28 | J114: 10.18 | K114: 4197.01
C115: ВСЕГО по позиции: | H115: 412.28 | J115: 4197.01
A117: 19 | B117: 3.17-2-13 Поправка: Гл.12.Прил.8.п.8. 3_12.00.01.11.001 Поправка: Гл.6.Прил.2.2.п.2.2.6_06.00.01.07.001 | C117: Установка гарнитуры туалетной: вешалок, подстаканников, дозаторов настенных и т.п./Крючок-держатель, универсальный крючок | D117: 100 шт. | E117: 0.02
C118: Объем: 0,02=2/100
C119: ЗП | F119: 95.59 | G119: 1,2*1,15 | H119: 1 | I119: 2.64 | J119: 57.05 | K119: 150.61
C120: ЭМ | F120: 8.97 | G120: 1,2*1,25 | H120: 1 | I120: 0.27 | J120: 16.35 | K120: 4.41
C121: в т.ч. ЗПМ | F121: 1.01 | G121: 1,2*1,25 | H121: 1 | I121: 0.03 | J121: 57.05 | K121: 1.71
C122: МР | F122: 2202.04 | H122: 1 | I122: 44.04 | J122: 0.48 | K122: 21.14
C123: НР от ФОТ | D123: % | E123: 109 | I123: 2.91 | J123: 109 | K123: 166.03
C124: СП от ФОТ | D124: % | E124: 61 | I124: 1.63 | J124: 61 | K124: 92.92
C125: ЗТР | D125: чел-ч | E125: 8.58 | G125: 1,2*1,15 | H125: 1 | I125: 0.24
...

Sheet ЛС 09-01-01
J2: Форма № 4б
A3: =ССРСС!A11 -> Выполнение работ по капитальному ремонту здания в Басманном районе ЦАО города Москвы
A4: (наименование стройки и/или объекта)
A6: ЛОКАЛЬНАЯ СМЕТА № 09-01-01
A8: ПНР
A9: (наименование работ и затрат)
I12: В базисном уровне цен | J12: В текущем уровне цен
E13: Сметная стоимость | I13: 35.23 | J13: 2010 | K13: тыс.руб.
E14: Прочие работы и затраты | I14: 35.23 | J14: 2010 | K14: тыс.руб.
E15: Средства на оплату труда | I15: 16.78 | J15: 957.14 | K15: тыс.руб.
E16: Затраты труда | I16: 991.33 | K16: чел.-ч.
A18: Составлен(а) по ТСН-2001 с учетом Дополнения №: 81
A19: № и период сборника коэффициентов (индексов) пересчета: Коэффициенты к ТСН-2001 МГЭ Дополнение 81, строительство №220 II квартал 2026 года и Коэффициенты к ТСН-2001.13-2 Дополнение 47 №65 II квартал 2026 года
A20: № п/п | B20: Шифр расценки и коды ресурсов | C20: Наименование работ и затрат | D20: Ед. изм. | E20: Кол-во единиц | F20: Цена на ед. изм., руб. | G20: Попра- вочные коэффи- циенты | H20: Коэффи- циенты зимних удорожа- ний | I20: Всего в ценах на январь 2000 года, руб. | J20: Коэффи- циенты (индек- сы) пере- счета, нормы НР и СП | K20: ВСЕГО затрат в текущем уровне цен, руб.
A21: 1 | B21: 2 | C21: 3 | D21: 4 | E21: 5 | F21: 6 | G21: 7 | H21: 8 | I21: 9 | J21: 10 | K21: 11
A22: Раздел: Электрооборудование
A23: 1 | B23: 5.1-151-1 | C23: Измерение сопротивления растеканию тока заземлителя | D23: 1 измерение | E23: 5
C24: ЗП | F24: 12.66 | H24: 1 | I24: 63.3 | J24: 57.05 | K24: 3611.27
C25: НР от ФОТ | D25: % | E25: 74 | I25: 46.84 | J25: 74 | K25: 2672.34
C26: СП от ФОТ | D26: % | E26: 36 | I26: 22.79 | J26: 36 | K26: 1300.06
C27: ЗТР | D27: чел-ч | E27: 0.8 | H27: 1 | I27: 4
C28: ВСЕГО работ по позиции: | H28: 132.93 | J28: 7583.67
C29: ВСЕГО по позиции: | H29: 132.93 | J29: 7583.67
A31: 2 | B31: 5.1-154-1 | C31: Замер полного сопротивления цепи "фаза-нуль" | D31: 1 токоприемник | E31: 128
C32: Объем: 128=3+6+3+6+4+8+12+9+12+9+8+13+13+13+9
C33: ЗП | F33: 12.66 | H33: 1 | I33: 1620.48 | J33: 57.05 | K33: 92448.38
C34: НР от ФОТ | D34: % | E34: 74 | I34: 1199.16 | J34: 74 | K34: 68411.8
C35: СП от ФОТ | D35: % | E35: 36 | I35: 583.37 | J35: 36 | K35: 33281.42
C36: ЗТР | D36: чел-ч | E36: 0.8 | H36: 1 | I36: 102.4
C37: ВСЕГО работ по позиции: | H37: 3403.01 | J37: 194141.6
C38: ВСЕГО по позиции: | H38: 3403.01 | J38: 194141.6
A40: 3 | B40: 5.1-162-1 | C40: Измерение сопротивления изоляции мегаомметром кабельных и других линий напряжением до 1 кВ, предназначенных для передачи электроэнергии к распределительным устройствам, щитам, шкафам и коммутационным аппаратам | D40: 1 измерение | E40: 128
C41: ЗП | F41: 4.56 | H41: 1 | I41: 583.68 | J41: 57.05 | K41: 33298.94
C42: НР от ФОТ | D42: % | E42: 74 | I42: 431.92 | J42: 74 | K42: 24641.22
C43: СП от ФОТ | D43: % | E43: 36 | I43: 210.12 | J43: 36 | K43: 11987.62
C44: ЗТР | D44: чел-ч | E44: 0.29 | H44: 1 | I44: 37.12
C45: ВСЕГО работ по позиции: | H45: 1225.72 | J45: 69927.78
C46: ВСЕГО по позиции: | H46: 1225.72 | J46: 69927.78
A48: 4 | B48: 5.1-152-1 | C48: Проверка наличия цепи между заземлителями и заземленными элементами | D48: 1 ТОЧКА | E48: 10
C49: Объем: 10=5*2
C50: ЗП | F50: 1.9 | H50: 1 | I50: 19 | J50: 57.05 | K50: 1083.95
C51: НР от ФОТ | D51: % | E51: 74 | I51: 14.06 | J51: 74 | K51: 802.12
C52: СП от ФОТ | D52: % | E52: 36 | I52: 6.84 | J52: 36 | K52: 390.22
C53: ЗТР | D53: чел-ч | E53: 0.12 | H53: 1 | I53: 1.2
C54: ВСЕГО работ по позиции: | H54: 39.9 | J54: 2276.29
C55: ВСЕГО по позиции: | H55: 39.9 | J55: 2276.29
A57: 5 | B57: 5.1-158-1 | C57: Фазировка электрической линии или трансформатора с сетью напряжением до 1 кВ | D57: 1 фазировка | E57: 5
C58: ЗП | F58: 11.39 | H58: 1 | I58: 56.95 | J58: 57.05 | K58: 3249
C59: НР от ФОТ | D59: % | E59: 74 | I59: 42.14 | J59: 74 | K59: 2404.26
C60: СП от ФОТ | D60: % | E60: 36 | I60: 20.5 | J60: 36 | K60: 1169.64
C61: ЗТР | D61: чел-ч | E61: 0.72 | H61: 1 | I61: 3.6
C62: ВСЕГО работ по позиции: | H62: 119.59 | J62: 6822.9
C63: ВСЕГО по позиции: | H63: 119.59 | J63: 6822.9
A66: Итого по разделу: Электрооборудование | H66: 4921.15 | J66: 280752.24
A68: Раздел: Кондиционирование
A69: 6 | B69: 5.3-29-1 | C69: Кондиционер местный неавтономный с централизованным тепло- и холодоснабжением (вентиляторные теплообменники, эжекционные доводчики и т.п.) номинальной подачей по воздуху до 3 тыс.м3/ч, при количестве однотипных кондиционеров в одном помещении до 5 | D69: 1 кондиционер | E69: 25
C70: Объем: 25=2+2+2+1+1+1+1+1+1+1+1+1+1+1+1+1+1+1+1+1+1+1
C71: ЗП | F71: 87.74 | H71: 1 | I71: 2193.5 | J71: 57.05 | K71: 125139.18
C72: НР от ФОТ | D72: % | E72: 74 | I72: 1623.19 | J72: 74 | K72: 92602.99
C73: СП от ФОТ | D73: % | E73: 36 | I73: 789.66 | J73: 36 | K73: 45050.1
C74: ЗТР | D74: чел-ч | E74: 4.96 | H74: 1 | I74: 124
C75: ВСЕГО работ по позиции: | H75: 4606.35 | J75: 262792.27
C76: ВСЕГО по позиции: | H76: 4606.35 | J76: 262792.27
A79: Итого по разделу: Кондиционирование | H79: 4606.35 | J79: 262792.27
A81: Раздел: АПС
A82: 7 | B82: 5.2-35-1 | C82: Комплексная пусконаладка системы | D82: 1 ШТ. | E82: 1
C83: ЗП | F83: 30.78 | H83: 1 | I83: 30.78 | J83: 57.05 | K83: 1756
C84: НР от ФОТ | D84: % | E84: 74 | I84: 22.78 | J84: 74 | K84: 1299.44
C85: СП от ФОТ | D85: % | E85: 36 | I85: 11.08 | J85: 36 | K85: 632.16
C86: ЗТР | D86: чел-ч | E86: 1.66 | H86: 1 | I86: 1.66
C87: ВСЕГО работ по позиции: | H87: 64.64 | J87: 3687.6
C88: ВСЕГО по позиции: | H88: 64.64 | J88: 3687.6
A90: 8 | B90: 5.2-35-2 | C90: Комплексная пусконаладка системы, добавлять к позиции 5.2-35-1 на каждое адресное устройство | D90: 1 ШТ. | E90: 107
C91: Объем: 107=2+1+1+85+4+13+1
C92: ЗП | F92: 18.51 | H92: 1 | I92: 1980.57 | J92: 57.05 | K92: 112991.52
C93: НР от ФОТ | D93: % | E93: 74 | I93: 1465.62 | J93: 74 | K93: 83613.72
C94: СП от ФОТ | D94: % | E94: 36 | I94: 713.01 | J94: 36 | K94: 40676.95
C95: ЗТР | D95: чел-ч | E95: 1.27 | H95: 1 | I95: 135.89
C96: ВСЕГО работ по позиции: | H96: 4159.2 | J96: 237282.19
C97: ВСЕГО по позиции: | H97: 4159.2 | J97: 237282.19
A100: Итого по разделу: АПС | H100: 4223.84 | J100: 240969.79
A102: Раздел: СОУЭ
A103: 9 | B103: 5.2-35-1 | C103: Комплексная пусконаладка системы | D103: 1 ШТ. | E103: 1
C104: ЗП | F104: 30.78 | H104: 1 | I104: 30.78 | J104: 57.05 | K104: 1756
C105: НР от ФОТ | D105: % | E105: 74 | I105: 22.78 | J105: 74 | K105: 1299.44
C106: СП от ФОТ | D106: % | E106: 36 | I106: 11.08 | J106: 36 | K106: 632.16
C107: ЗТР | D107: чел-ч | E107: 1.66 | H107: 1 | I107: 1.66
C108: ВСЕГО работ по позиции: | H108: 64.64 | J108: 3687.6
C109: ВСЕГО по позиции: | H109: 64.64 | J109: 3687.6
A111: 10 | B111: 5.2-35-2 | C111: Комплексная пусконаладка системы, добавлять к позиции 5.2-35-1 на каждое адресное устройство | D111: 1 ШТ. | E111: 35
C112: Объем: 35=14+21
C113: ЗП | F113: 18.51 | H113: 1 | I113: 647.85 | J113: 57.05 | K113: 36959.84
C114: НР от ФОТ | D114: % | E114: 74 | I114: 479.41 | J114: 74 | K114: 27350.28
C115: СП от ФОТ | D115: % | E115: 36 | I115: 233.23 | J115: 36 | K115: 13305.54
C116: ЗТР | D116: чел-ч | E116: 1.27 | H116: 1 | I116: 44.45
C117: ВСЕГО работ по позиции: | H117: 1360.49 | J117: 77615.66
C118: ВСЕГО по позиции: | H118: 1360.49 | J118: 77615.66
A121: Итого по разделу: СОУЭ | H121: 1425.13 | J121: 81303.26
A123: Раздел: РТС
A124: 11 | B124: 5.2-35-1 | C124: Комплексная пусконаладка системы | D124: 1 ШТ. | E124: 1
...

Sheet Возврат
J2: Форма № 4б
A3: =ССРСС!A11 -> Выполнение работ по капитальному ремонту здания в Басманном районе ЦАО города Москвы
A4: (наименование стройки и/или объекта)
A6: ЛОКАЛЬНЫЙ СМЕТНЫЙ РАСЧЕТ № б/н
A8: Возвратные средства
A9: (наименование работ и затрат)
I12: В базисном уровне цен | J12: В текущем уровне цен
E13: Возврат материалов | I13: 2.48 | J13: 31.51 | K13: тыс.руб.
A15: Составлен(а) по ТСН-2001 с учетом Дополнения №: 81
A16: № и период сборника коэффициентов (индексов) пересчета: Коэффициенты к ТСН-2001 МГЭ Дополнение 81, ремонт №220 II квартал 2026 года и Коэффициенты к ТСН-2001.13-2 Дополнение 47 №65 II квартал 2026 года
A17: № п/п | B17: Шифр расценки и коды ресурсов | C17: Наименование работ и затрат | D17: Ед. изм. | E17: Кол-во единиц | F17: Цена на ед. изм., руб. | G17: Попра- вочные коэффи- циенты | H17: Коэффи- циенты зимних удорожа- ний | I17: Всего в ценах на январь 2000 года, руб. | J17: Коэффи- циенты (индек- сы) пере- счета, нормы НР и СП | K17: ВСЕГО затрат в текущем уровне цен, руб.
A18: 1 | B18: 2 | C18: 3 | D18: 4 | E18: 5 | F18: 6 | G18: 7 | H18: 8 | I18: 9 | J18: 10 | K18: 11
A19: Раздел: Возвратные средства
A20: 1 | B20: 1.7-11-61 | C20: ВОЗВРАТ_x000D_ Лом стальной, вид лома 12А, для расчета возвратных сумм | D20: т | E20: 1.23125 | F20: 1853.64 | H20: 1 | I20: 2282.29 | J20: 12.79 | K20: 29190.49
C21: ВСЕГО по позиции: | H21: 2282.29 | J21: 29190.49
A23: 2 | B23: 1.7-11-63 | C23: ВОЗВРАТ_x000D_ Лом чугунный, вид лома 22А, для расчета возвратных сумм | D23: т | E23: 0.091 | F23: 2205.03 | H23: 1 | I23: 200.66 | J23: 11.56 | K23: 2319.63
C24: ВСЕГО по позиции: | H24: 200.66 | J24: 2319.63
A27: Итого возвратных сумм | H27: 2482.95 | J27: 31510.12
